Workbook

Sheet INS
C2: ~TFM_DINS-TS: Region=AT,BE,BG,CY,CZ,DE,DK,EE,ES,FI,FR,EL,HU,IE,IT,LT,LU,LV,MT,NL,PL,PT,RO,SE,SI,SK,UK,CH,IS,NO,AL,BA,HR,KS,ME,MK,RS
C3: Pset_PN | D3: Curr | E3: Attribute | F3: 2015 | G3: 2020 | H3: 2025 | I3: 2030 | J3: 2035 | K3: 2040 | L3: 2045 | M3: 2050 | N3: 2060 | O3: 2070
A4: Tidal energy stream | C4: EUOCETID01 | D4: EUR17 | E4: NCAP_COST | F4: =Ocean_Summary!AF66 -> 7840 | G4: =Ocean_Summary!AG66 -> 5530 | H4: =Ocean_Summary!AH66 -> 5130 | I4: =Ocean_Summary!AI66 -> 4250 | J4: =Ocean_Summary!AJ66 -> 3370 | K4: =Ocean_Summary!AK66 -> 2780 | L4: =Ocean_Summary!AL66 -> 2320 | M4: =Ocean_Summary!AM66 -> 1980 | N4: 1980 | O4: 1980
A5: Wave (nearshore) | C5: EUOCEWAV01 | D5: EUR17 | E5: NCAP_COST | F5: =Ocean_Summary!AF67 -> 7910 | G5: =Ocean_Summary!AG67 -> 5580 | H5: =Ocean_Summary!AH67 -> 5170 | I5: =Ocean_Summary!AI67 -> 4290 | J5: =Ocean_Summary!AJ67 -> 3400 | K5: =Ocean_Summary!AK67 -> 2810 | L5: =Ocean_Summary!AL67 -> 2350 | M5: =Ocean_Summary!AM67 -> 2000 | N5: 2000 | O5: 2000
A6: Wave (offshore) | C6: EUOCEWAV02 | D6: EUR17 | E6: NCAP_COST | F6: =Ocean_Summary!AF68 -> 7910 | G6: =Ocean_Summary!AG68 -> 5580 | H6: =Ocean_Summary!AH68 -> 5170 | I6: =Ocean_Summary!AI68 -> 4290 | J6: =Ocean_Summary!AJ68 -> 3400 | K6: =Ocean_Summary!AK68 -> 2810 | L6: =Ocean_Summary!AL68 -> 2350 | M6: =Ocean_Summary!AM68 -> 2000 | N6: 2000 | O6: 2000
A7: Tidal energy stream | C7: EUOCETID01 | D7: EUR17 | E7: NCAP_FOM | F7: =Ocean_Summary!AR66 -> 493.44914 | G7: =Ocean_Summary!AS66 -> 360.22897 | H7: =Ocean_Summary!AT66 -> 316.31024 | I7: =Ocean_Summary!AU66 -> 238.88999 | J7: =Ocean_Summary!AV66 -> 200.07165 | K7: =Ocean_Summary!AW66 -> 175.55367 | L7: =Ocean_Summary!AX66 -> 133.08181 | M7: =Ocean_Summary!AY66 -> 97.440874 | N7: 97.440874 | O7: 97.440874
A8: Wave (nearshore) | C8: EUOCEWAV01 | D8: EUR17 | E8: NCAP_FOM | F8: =Ocean_Summary!AR67 -> 312.8177 | G8: =Ocean_Summary!AS67 -> 220.82653 | H8: =Ocean_Summary!AT67 -> 204.56105 | I8: =Ocean_Summary!AU67 -> 150.05345 | J8: =Ocean_Summary!AV67 -> 134.48404 | K8: =Ocean_Summary!AW67 -> 110.95853 | L8: =Ocean_Summary!AX67 -> 92.751853 | M8: =Ocean_Summary!AY67 -> 78.961762 | N8: 78.961762 | O8: 78.961762
A9: Wave (offshore) | C9: EUOCEWAV02 | D9: EUR17 | E9: NCAP_FOM | F9: =Ocean_Summary!AR68 -> 324.30202 | G9: =Ocean_Summary!AS68 -> 240.16201 | H9: =Ocean_Summary!AT68 -> 219.29006 | I9: =Ocean_Summary!AU68 -> 178.43704 | J9: =Ocean_Summary!AV68 -> 151.16394 | K9: =Ocean_Summary!AW68 -> 140.51739 | L9: =Ocean_Summary!AX68 -> 123.3174 | M9: =Ocean_Summary!AY68 -> 110.72774 | N9: 110.72774 | O9: 110.72774
A10: Utility c-Si, tracking | C10: EUPVSOLL201 | D10: EUR17 | E10: NCAP_COST | F10: =PV_Summary_Fin!AF65 -> 1120 | G10: =PV_Summary_Fin!AG65 -> 830 | H10: =PV_Summary_Fin!AH65 -> 700 | I10: =PV_Summary_Fin!AI65 -> 600 | J10: =PV_Summary_Fin!AJ65 -> 510 | K10: =PV_Summary_Fin!AK65 -> 430 | L10: =PV_Summary_Fin!AL65 -> 380 | M10: =PV_Summary_Fin!AM65 -> 340 | N10: 340 | O10: 340
A11: Utility c-Si, flat | C11: EUPVSOLL101 | D11: EUR17 | E11: NCAP_COST | F11: =PV_Summary_Fin!AF66 -> 1020 | G11: =PV_Summary_Fin!AG66 -> 750 | H11: =PV_Summary_Fin!AH66 -> 640 | I11: =PV_Summary_Fin!AI66 -> 540 | J11: =PV_Summary_Fin!AJ66 -> 460 | K11: =PV_Summary_Fin!AK66 -> 390 | L11: =PV_Summary_Fin!AL66 -> 340 | M11: =PV_Summary_Fin!AM66 -> 310 | N11: 310 | O11: 310
A12: Commercial c-Si, flat | C12: EUPVSOLS201 | D12: EUR17 | E12: NCAP_COST | F12: =PV_Summary_Fin!AF67 -> 1140 | G12: =PV_Summary_Fin!AG67 -> 840 | H12: =PV_Summary_Fin!AH67 -> 720 | I12: =PV_Summary_Fin!AI67 -> 610 | J12: =PV_Summary_Fin!AJ67 -> 520 | K12: =PV_Summary_Fin!AK67 -> 440 | L12: =PV_Summary_Fin!AL67 -> 380 | M12: =PV_Summary_Fin!AM67 -> 350 | N12: 350 | O12: 350
A13: Residential c-Si, inclined | C13: EUPVSOLS101 | D13: EUR17 | E13: NCAP_COST | F13: =PV_Summary_Fin!AF69 -> 1360 | G13: =PV_Summary_Fin!AG69 -> 1000 | H13: =PV_Summary_Fin!AH69 -> 860 | I13: =PV_Summary_Fin!AI69 -> 730 | J13: =PV_Summary_Fin!AJ69 -> 610 | K13: =PV_Summary_Fin!AK69 -> 520 | L13: =PV_Summary_Fin!AL69 -> 460 | M13: =PV_Summary_Fin!AM69 -> 410 | N13: 410 | O13: 410
A14: Utility c-Si, tracking | C14: EUPVSOLL201 | D14: EUR17 | E14: NCAP_FOM | F14: ='PV SET'!$AC20*F10 -> 25.783723 | G14: ='PV SET'!$AC20*G10 -> 19.10758 | H14: ='PV SET'!$AC20*H10 -> 16.114827 | I14: ='PV SET'!$AC20*I10 -> 13.812709 | J14: ='PV SET'!$AC20*J10 -> 11.740802 | K14: ='PV SET'!$AC20*K10 -> 9.8991078 | L14: ='PV SET'!$AC20*L10 -> 8.7480488 | M14: ='PV SET'!$AC20*M10 -> 7.8272015 | N14: 7.8272015 | O14: 7.8272015
A15: Utility c-Si, flat | C15: EUPVSOLL101 | D15: EUR17 | E15: NCAP_FOM | F15: ='PV SET'!$AC21*F11 -> 17.409869 | G15: ='PV SET'!$AC21*G11 -> 12.801374 | H15: ='PV SET'!$AC21*H11 -> 10.923839 | I15: ='PV SET'!$AC21*I11 -> 9.2169895 | J15: ='PV SET'!$AC21*J11 -> 7.8515096 | K15: ='PV SET'!$AC21*K11 -> 6.6567147 | L15: ='PV SET'!$AC21*L11 -> 5.8032897 | M15: ='PV SET'!$AC21*M11 -> 5.2912347 | N15: 5.2912347 | O15: 5.2912347
A16: Commercial c-Si, flat | C16: EUPVSOLS201 | D16: EUR17 | E16: NCAP_FOM | F16: ='PV SET'!$AC22*F12 -> 28.658557 | G16: ='PV SET'!$AC22*G12 -> 21.116831 | H16: ='PV SET'!$AC22*H12 -> 18.100141 | I16: ='PV SET'!$AC22*I12 -> 15.334842 | J16: ='PV SET'!$AC22*J12 -> 13.072324 | K16: ='PV SET'!$AC22*K12 -> 11.061197 | L16: ='PV SET'!$AC22*L12 -> 9.5528523 | M16: ='PV SET'!$AC22*M12 -> 8.7986797 | N16: 8.7986797 | O16: 8.7986797
A17: Residential c-Si, inclined | C17: EUPVSOLS101 | D17: EUR17 | E17: NCAP_FOM | F17: ='PV SET'!$AC24*F13 -> 27.309599 | G17: ='PV SET'!$AC24*G13 -> 20.080587 | H17: ='PV SET'!$AC24*H13 -> 17.269305 | I17: ='PV SET'!$AC24*I13 -> 14.658829 | J17: ='PV SET'!$AC24*J13 -> 12.249158 | K17: ='PV SET'!$AC24*K13 -> 10.441905 | L17: ='PV SET'!$AC24*L13 -> 9.2370701 | M17: ='PV SET'!$AC24*M13 -> 8.2330407 | N17: 8.2330407 | O17: 8.2330407
A18: Solar CSP Parabolic Through 6-8h storage | C18: EUCSPSOL101 | D18: EUR17 | E18: NCAP_COST | F18: =STE_Summary!AF65 -> 6000 | G18: =STE_Summary!AG65 -> 4120 | H18: =STE_Summary!AH65 -> 3790 | I18: =STE_Summary!AI65 -> 3380 | J18: =STE_Summary!AJ65 -> 3080 | K18: =STE_Summary!AK65 -> 2890 | L18: =STE_Summary!AL65 -> 2770 | M18: =STE_Summary!AM65 -> 2660 | N18: 2660 | O18: 2660
A19: Solar CSP Solar Tower 12-15h storage | C19: EUCSPSOL401 | D19: EUR17 | E19: NCAP_COST | F19: =STE_Summary!AF66 -> 5280 | G19: =STE_Summary!AG66 -> 3620 | H19: =STE_Summary!AH66 -> 3330 | I19: =STE_Summary!AI66 -> 2970 | J19: =STE_Summary!AJ66 -> 2710 | K19: =STE_Summary!AK66 -> 2550 | L19: =STE_Summary!AL66 -> 2440 | M19: =STE_Summary!AM66 -> 2340 | N19: 2340 | O19: 2340
A20: Solar PV high concentration | C20: EUPVSOLHC01 | D20: EUR17 | E20: NCAP_COST | F20: =STE_Summary!AF67 -> 3800 | G20: =STE_Summary!AG67 -> 2610 | H20: =STE_Summary!AH67 -> 2400 | I20: =STE_Summary!AI67 -> 2140 | J20: =STE_Summary!AJ67 -> 1950 | K20: =STE_Summary!AK67 -> 1830 | L20: =STE_Summary!AL67 -> 1760 | M20: =STE_Summary!AM67 -> 1680 | N20: 1680 | O20: 1680
A21: Solar CSP Parabolic Through 6-8h storage | C21: EUCSPSOL101 | D21: EUR17 | E21: NCAP_FOM | F21: ='STE SET'!$X4*INS!F18 -> 101.92868 | G21: ='STE SET'!$X4*INS!G18 -> 69.991028 | H21: ='STE SET'!$X4*INS!H18 -> 64.384951 | I21: ='STE SET'!$X4*INS!I18 -> 57.419824 | J21: ='STE SET'!$X4*INS!J18 -> 52.32339 | K21: ='STE SET'!$X4*INS!K18 -> 49.095649 | L21: ='STE SET'!$X4*INS!L18 -> 47.057075 | M21: ='STE SET'!$X4*INS!M18 -> 45.188382 | N21: 45.188382 | O21: 45.188382
A22: Solar CSP Solar Tower 12-15h storage | C22: EUCSPSOL401 | D22: EUR17 | E22: NCAP_FOM | F22: ='STE SET'!$X5*INS!F19 -> 89.688954 | G22: ='STE SET'!$X5*INS!G19 -> 61.491291 | H22: ='STE SET'!$X5*INS!H19 -> 56.565193 | I22: ='STE SET'!$X5*INS!I19 -> 50.450037 | J22: ='STE SET'!$X5*INS!J19 -> 46.033535 | K22: ='STE SET'!$X5*INS!K19 -> 43.315688 | L22: ='STE SET'!$X5*INS!L19 -> 41.447168 | M22: ='STE SET'!$X5*INS!M19 -> 39.748514 | N22: 39.748514 | O22: 39.748514
A23: Solar PV high concentration | C23: EUPVSOLHC01 | D23: EUR17 | E23: NCAP_FOM | F23: =STE_Summary!AR67 -> 64.6 | G23: =STE_Summary!AS67 -> 44.322383 | H23: =STE_Summary!AT67 -> 40.785305 | I23: =STE_Summary!AU67 -> 36.385842 | J23: =STE_Summary!AV67 -> 33.176706 | K23: =STE_Summary!AW67 -> 31.142115 | L23: =STE_Summary!AX67 -> 29.835883 | M23: =STE_Summary!AY67 -> 28.586887 | N23: 28.586887 | O23: 28.586887
A24: Wind offshore both Monopile and Jacket | C24: EUWINOFH01 | D24: EUR17 | E24: NCAP_COST | F24: ='WindOffshore Summary'!G72 -> 3600 | G24: ='WindOffshore Summary'!H72 -> 2460 | H24: ='WindOffshore Summary'!I72 -> 2190 | I24: ='WindOffshore Summary'!J72 -> 1980 | J24: ='WindOffshore Summary'!K72 -> 1840 | K24: ='WindOffshore Summary'!L72 -> 1750 | L24: ='WindOffshore Summary'!M72 -> 1680 | M24: ='WindOffshore Summary'!N72 -> 1610 | N24: 1610 | O24: 1610
A25: Wind offshore 4 floating (>50m) | C25: EUWINOFV01 | D25: EUR17 | E25: NCAP_COST | F25: ='WindOffshore Summary'!G117 -> 5300 | G25: ='WindOffshore Summary'!H117 -> 3620 | H25: ='WindOffshore Summary'!I117 -> 3230 | I25: ='WindOffshore Summary'!J117 -> 2910 | J25: ='WindOffshore Summary'!K117 -> 2720 | K25: ='WindOffshore Summary'!L117 -> 2580 | L25: ='WindOffshore Summary'!M117 -> 2480 | M25: ='WindOffshore Summary'!N117 -> 2370 | N25: 2370 | O25: 2370
A26: Wind offshore both Monopile and Jacket | C26: EUWINOFH01 | D26: EUR17 | E26: NCAP_FOM | F26: ='WindOffshore Summary'!S72 -> 72 | G26: ='WindOffshore Summary'!T72 -> 49.22789 | H26: ='WindOffshore Summary'!U72 -> 43.864998 | I26: ='WindOffshore Summary'!V72 -> 39.572893 | J26: ='WindOffshore Summary'!W72 -> 36.891111 | K26: ='WindOffshore Summary'!X72 -> 35.071739 | L26: ='WindOffshore Summary'!Y72 -> 33.664998 | M26: ='WindOffshore Summary'!Z72 -> 32.189492 | N26: 32.189492 | O26: 32.189492
A27: Wind offshore 4 floating (>50m) | C27: EUWINOFV01 | D27: EUR17 | E27: NCAP_FOM | F27: ='WindOffshore Summary'!S117 -> 106 | G27: ='WindOffshore Summary'!T117 -> 72.474393 | H27: ='WindOffshore Summary'!U117 -> 64.579025 | I27: ='WindOffshore Summary'!V117 -> 58.260093 | J27: ='WindOffshore Summary'!W117 -> 54.311913 | K27: ='WindOffshore Summary'!X117 -> 51.633394 | L27: ='WindOffshore Summary'!Y117 -> 49.562359 | M27: ='WindOffshore Summary'!Z117 -> 47.390085 | N27: 47.390085 | O27: 47.390085
A28: Wind onshore CF15-20 | C28: EUWINONL01 | D28: EUR17 | E28: NCAP_COST | F28: ='WindOnshore Summary'!G72 -> 1350 | G28: ='WindOnshore Summary'!H72 -> 1220 | H28: ='WindOnshore Summary'!I72 -> 1150 | I28: ='WindOnshore Summary'!J72 -> 1080 | J28: ='WindOnshore Summary'!K72 -> 1040 | K28: ='WindOnshore Summary'!L72 -> 1000 | L28: ='WindOnshore Summary'!M72 -> 970 | M28: ='WindOnshore Summary'!N72 -> 950 | N28: 950 | O28: 950
A29: Wind onshore CF20-25 | C29: EUWINONM01 | D29: EUR17 | E29: NCAP_COST | F29: =F28 -> 1350 | G29: =G28 -> 1220 | H29: =H28 -> 1150 | I29: =I28 -> 1080 | J29: =J28 -> 1040 | K29: =K28 -> 1000 | L29: =L28 -> 970 | M29: =M28 -> 950 | N29: 950 | O29: 950
A30: Wind onshore CF25+ | C30: EUWINONH01 | D30: EUR17 | E30: NCAP_COST | F30: =F29 -> 1350 | G30: =G29 -> 1220 | H30: =H29 -> 1150 | I30: =I29 -> 1080 | J30: =J29 -> 1040 | K30: =K29 -> 1000 | L30: =L29 -> 970 | M30: =M29 -> 950 | N30: 950 | O30: 950
A31: Wind onshore CF15-20 | C31: EUWINONL01 | D31: EUR17 | E31: NCAP_FOM | F31: ='WindOnshore Summary'!S72 -> 40.5 | G31: ='WindOnshore Summary'!T72 -> 36.605774 | H31: ='WindOnshore Summary'!U72 -> 34.441134 | I31: ='WindOnshore Summary'!V72 -> 32.497625 | J31: ='WindOnshore Summary'!W72 -> 31.186177 | K31: ='WindOnshore Summary'!X72 -> 30.123419 | L31: ='WindOnshore Summary'!Y72 -> 29.199852 | M31: ='WindOnshore Summary'!Z72 -> 28.358823 | N31: 28.358823 | O31: 28.358823
A32: Wind onshore CF20-25 | C32: EUWINONM01 | D32: EUR17 | E32: NCAP_FOM | F32: =F31 -> 40.5 | G32: =G31 -> 36.605774 | H32: =H31 -> 34.441134 | I32: =I31 -> 32.497625 | J32: =J31 -> 31.186177 | K32: =K31 -> 30.123419 | L32: =L31 -> 29.199852 | M32: =M31 -> 28.358823 | N32: 28.358823 | O32: 28.358823
A33: Wind onshore CF25+ | C33: EUWINONH01 | D33: EUR17 | E33: NCAP_FOM | F33: =F32 -> 40.5 | G33: =G32 -> 36.605774 | H33: =H32 -> 34.441134 | I33: =I32 -> 32.497625 | J33: =J32 -> 31.186177 | K33: =K32 -> 30.123419 | L33: =L32 -> 29.199852 | M33: =M32 -> 28.358823 | N33: 28.358823 | O33: 28.358823
A34: Geothermal EGS with ORC | C34: EUGEOEGS01 | D34: EUR17 | E34: NCAP_COST | F34: ='Geothermal Summary'!AF35 -> 11790 | G34: ='Geothermal Summary'!AG35 -> 10550 | H34: ='Geothermal Summary'!AH35 -> 10000 | I34: ='Geothermal Summary'!AI35 -> 9250 | J34: ='Geothermal Summary'!AJ35 -> 8840 | K34: ='Geothermal Summary'!AK35 -> 8510 | L34: ='Geothermal Summary'!AL35 -> 8160 | M34: ='Geothermal Summary'!AM35 -> 7870 | N34: 7870 | O34: 7870
A35: Geothermal hydrothermal with flash power plants | C35: EUGEOF01 | D35: EUR17 | E35: NCAP_COST | F35: ='Geothermal Summary'!AF36 -> 3540 | G35: ='Geothermal Summary'!AG36 -> 3170 | H35: ='Geothermal Summary'!AH36 -> 3000 | I35: ='Geothermal Summary'!AI36 -> 2780 | J35: ='Geothermal Summary'!AJ36 -> 2650 | K35: ='Geothermal Summary'!AK36 -> 2560 | L35: ='Geothermal Summary'!AL36 -> 2450 | M35: ='Geothermal Summary'!AM36 -> 2360 | N35: 2360 | O35: 2360
A36: Geothermal hydrothermal with ORC | C36: EUGEOORC01 | D36: EUR17 | E36: NCAP_COST | F36: ='Geothermal Summary'!AF37 -> 6970 | G36: ='Geothermal Summary'!AG37 -> 6240 | H36: ='Geothermal Summary'!AH37 -> 5910 | I36: ='Geothermal Summary'!AI37 -> 5470 | J36: ='Geothermal Summary'!AJ37 -> 5230 | K36: ='Geothermal Summary'!AK37 -> 5030 | L36: ='Geothermal Summary'!AL37 -> 4830 | M36: ='Geothermal Summary'!AM37 -> 4650 | N36: 4650 | O36: 4650
A37: Geothermal EGS with ORC | C37: EUGEOEGS01 | D37: EUR17 | E37: NCAP_FOM | F37: ='Geothermal Summary'!AR35 -> 235.8 | G37: ='Geothermal Summary'!AS35 -> 211.08689 | H37: ='Geothermal Summary'!AT35 -> 200.00371 | I37: ='Geothermal Summary'!AU35 -> 185.06385 | J37: ='Geothermal Summary'!AV35 -> 176.82993 | K37: ='Geothermal Summary'!AW35 -> 170.21452 | L37: ='Geothermal Summary'!AX35 -> 163.29942 | M37: ='Geothermal Summary'!AY35 -> 157.35581 | N37: 157.35581 | O37: 157.35581
A38: Geothermal hydrothermal with flash power plants | C38: EUGEOF01 | D38: EUR17 | E38: NCAP_FOM | F38: ='Geothermal Summary'!AR36 -> 70.8 | G38: ='Geothermal Summary'!AS36 -> 63.379779 | H38: ='Geothermal Summary'!AT36 -> 60.052004 | I38: ='Geothermal Summary'!AU36 -> 55.566246 | J38: ='Geothermal Summary'!AV36 -> 53.093975 | K38: ='Geothermal Summary'!AW36 -> 51.107667 | L38: ='Geothermal Summary'!AX36 -> 49.031377 | M38: ='Geothermal Summary'!AY36 -> 47.246782 | N38: 47.246782 | O38: 47.246782 | S38: Attribute | T38: NCAP_COST | AB38: NCAP_FOM
A39: Geothermal hydrothermal with ORC | C39: EUGEOORC01 | D39: EUR17 | E39: NCAP_FOM | F39: ='Geothermal Summary'!AR37 -> 139.4 | G39: ='Geothermal Summary'!AS37 -> 124.79013 | H39: ='Geothermal Summary'!AT37 -> 118.23799 | I39: ='Geothermal Summary'!AU37 -> 109.40586 | J39: ='Geothermal Summary'!AV37 -> 104.53814 | K39: ='Geothermal Summary'!AW37 -> 100.62724 | L39: ='Geothermal Summary'!AX37 -> 96.539181 | M39: ='Geothermal Summary'!AY37 -> 93.025444 | N39: 93.025444 | O39: 93.025444 | Q39: Process | R39: Scenario | S39: Curr\Year | T39: 2013 | U39: 2015 | V39: 2020 | W39: 2025 | X39: 2030 | Y39: 2035 | Z39: 2040 | AA39: 2050 | AB39: 2010 | AC39: 2013 | AD39: 2015 | AE39: 2020 | AF39: 2030 | AG39: 2040 | AH39: 2050
A40: CCGT Combined Cycle Gas Turbine + CCS Seq post combustion | C40: EUCCGASCCSpos20 | D40: EUR17 | E40: NCAP_COST | H40: =CCUS_Summary!AH65 -> 1510 | I40: =CCUS_Summary!AI65 -> 1320 | J40: =CCUS_Summary!AJ65 -> 1240 | K40: =CCUS_Summary!AK65 -> 1190 | L40: =CCUS_Summary!AL65 -> 1170 | M40: =CCUS_Summary!AM65 -> 1150 | N40: 1150 | O40: 1150 | Q40: EUCCGASCCSpos20 [ CCGT Combined Cycle Gas Turbine + CCS Seq post combustion ] | R40: ELC_IET4 | S40: EUR13 | T40: 1500 | AC40: 37.5
A41: Supercritical pulverised coal + CCS Seq post combustion | C41: EUPCCOHCCSpos20 | D41: EUR17 | E41: NCAP_COST | H41: =CCUS_Summary!AH66 -> 2920 | I41: =CCUS_Summary!AI66 -> 2630 | J41: =CCUS_Summary!AJ66 -> 2480 | K41: =CCUS_Summary!AK66 -> 2400 | L41: =CCUS_Summary!AL66 -> 2360 | M41: =CCUS_Summary!AM66 -> 2360 | N41: 2360 | O41: 2360 | Q41: EUPCCOHCCSpos20 [ Supercritical pulverised coal + CCS Seq post combustion ] | R41: ELC_IET4 | S41: EUR13 | T41: 3000 | V41: 2700 | X41: 2550 | AC41: 75 | AE41: 67.5 | AF41: 63.75
A42: Super-critical Pulverised Coal + CCS Seq Oxyfuel | C42: EUPCCOHCCSoxy20 | D42: EUR17 | E42: NCAP_COST | H42: =CCUS_Summary!AH67 -> 2920 | I42: =CCUS_Summary!AI67 -> 2560 | J42: =CCUS_Summary!AJ67 -> 2370 | K42: =CCUS_Summary!AK67 -> 2270 | L42: =CCUS_Summary!AL67 -> 2240 | M42: =CCUS_Summary!AM67 -> 2240 | N42: 2240 | O42: 2240 | Q42: EUPCCOHCCSoxy20 [ Super-critical Pulverised Coal + CCS Seq Oxyfuel ] | R42: ELC_IET4 | S42: EUR13 | T42: 3000 | V42: 2700 | X42: 2550 | AC42: 75 | AE42: 67.5 | AF42: 63.75
A43: Integrated Gasification Combined Cycle lignite + CCS Seq pre-combustion | C43: EUIGCOLCCSpre20 | D43: EUR17 | E43: NCAP_COST | H43: =CCUS_Summary!AH68 -> 4480 | I43: =CCUS_Summary!AI68 -> 3570 | J43: =CCUS_Summary!AJ68 -> 3120 | K43: =CCUS_Summary!AK68 -> 2900 | L43: =CCUS_Summary!AL68 -> 2810 | M43: =CCUS_Summary!AM68 -> 2810 | N43: 2810 | O43: 2810 | Q43: EUIGCOLCCSpre20 [ Integrated Gasification Combined Cycle lignite + CCS Seq pre-combustion ] | R43: ELC_IET4 | S43: EUR13 | T43: 4500 | V43: 4370 | AC43: 103.5 | AE43: 100.51
A44: Integrated gasification combined cycle + CCS Seq pre combustion | C44: EUIGCOHCCSpre20 | D44: EUR17 | E44: NCAP_COST | H44: =CCUS_Summary!AH69 -> 2940 | I44: =CCUS_Summary!AI69 -> 2350 | J44: =CCUS_Summary!AJ69 -> 2050 | K44: =CCUS_Summary!AK69 -> 1900 | L44: =CCUS_Summary!AL69 -> 1850 | M44: =CCUS_Summary!AM69 -> 1850 | N44: 1850 | O44: 1850 | Q44: EUIGCOHCCSpre20 [ Integrated gasification combined cycle + CCS Seq pre combustion ] | R44: ELC_IET4 | S44: EUR13 | T44: 3100 | V44: 2885 | X44: 2825 | AC44: 93 | AE44: 86.55 | AF44: 84.75
A45: Biomass Integrated Gasification CC + CCS Seq post combustion | C45: EUIGCCWOOCCS01 | D45: EUR17 | E45: NCAP_COST | H45: =CCUS_Summary!AH70 -> 5800 | I45: =CCUS_Summary!AI70 -> 5160 | J45: =CCUS_Summary!AJ70 -> 4260 | K45: =CCUS_Summary!AK70 -> 3680 | L45: =CCUS_Summary!AL70 -> 3250 | M45: =CCUS_Summary!AM70 -> 3070 | N45: 3070 | O45: 3070 | Q45: EUIGCCWOOCCS01 | R45: ELC_IET4 | S45: EUR13 | T45: 6210 | V45: 5180 | X45: 4510 | Z45: 4210 | AA45: 3930 | AC45: 116.32 | AE45: 94.33 | AF45: 79.59 | AG45: 72.99 | AH45: 66.83
A46: CHP: Comb CYC.GAS.CCSpoc.PUB | C46: PUCCSGAS1 | D46: EUR17 | E46: NCAP_COST | H46: =H40*1.05 -> 1585.5 | I46: =I40*1.05 -> 1386 | J46: =J40*1.05 -> 1302 | K46: =K40*1.05 -> 1249.5 | L46: =L40*1.05 -> 1228.5 | M46: =M40*1.05 -> 1207.5 | N46: 1207.5 | O46: 1207.5 | Q46: PUCCSGAS1 [ CHP: Comb CYC.GAS.CCSpoc.PUB ] | R46: B-NewTechs | S46: EUR10 | U46: 1636.6 | V46: 1636.6 | X46: 1419.166 | AD46: 34.6024 | AE46: 34.6024 | AF46: 31.563
A47: CHP: Comb CYC.GAS.CCSprc.PUB | C47: PUCCSGAS2 | D47: EUR17 | E47: NCAP_COST | H47: =H46 -> 1585.5 | I47: =I46 -> 1386 | J47: =J46 -> 1302 | K47: =K46 -> 1249.5 | L47: =L46 -> 1228.5 | M47: =M46 -> 1207.5 | N47: 1207.5 | O47: 1207.5 | Q47: PUCCSGAS2 [ CHP: Comb CYC.GAS.CCSprc.PUB ] | R47: B-NewTechs | S47: EUR10 | U47: 1726.613 | V47: 1726.613 | X47: 1327.984 | AD47: 30.8616 | AE47: 30.8616 | AF47: 29.1081
A48: CHP: Comb CYC.GAS.CCSoxy.PUB | C48: PUCCSGAS3 | D48: EUR17 | E48: NCAP_COST | H48: =H47 -> 1585.5 | I48: =I47 -> 1386 | J48: =J47 -> 1302 | K48: =K47 -> 1249.5 | L48: =L47 -> 1228.5 | M48: =M47 -> 1207.5 | N48: 1207.5 | O48: 1207.5 | Q48: PUCCSGAS3 [ CHP: Comb CYC.GAS.CCSoxy.PUB ] | R48: B-NewTechs | S48: EUR10 | U48: 1827.147 | V48: 1827.147 | X48: 1346.688 | AD48: 31.9137 | AE48: 31.9137 | AF48: 30.1602
A49: CHP: Int Gasification.COH.CCSpoc.PUB | C49: PUICSCOH1 | D49: EUR17 | E49: NCAP_COST | H49: =H50 -> 3087 | I49: =I50 -> 2467.5 | J49: =J50 -> 2152.5 | K49: =K50 -> 1995 | L49: =L50 -> 1942.5 | M49: =M50 -> 1942.5 | N49: 1942.5 | O49: 1942.5 | Q49: PUICSCOH1 [ CHP: Int Gasification.COH.CCSpoc.PUB ] | R49: B-NewTechs | S49: EUR10 | U49: 3758.335 | V49: 3758.335 | X49: 3087.329 | AD49: 56.2289 | AE49: 56.2289 | AF49: 52.2543
A50: CHP: Int Gasification.COH.CCSprc.PUB | C50: PUICSCOH2 | D50: EUR17 | E50: NCAP_COST | H50: =H44*1.05 -> 3087 | I50: =I44*1.05 -> 2467.5 | J50: =J44*1.05 -> 2152.5 | K50: =K44*1.05 -> 1995 | L50: =L44*1.05 -> 1942.5 | M50: =M44*1.05 -> 1942.5 | N50: 1942.5 | O50: 1942.5 | Q50: PUICSCOH2 [ CHP: Int Gasification.COH.CCSprc.PUB ] | R50: B-NewTechs | S50: EUR10 | U50: 3538.563 | V50: 3538.563 | X50: 2826.642 | AD50: 56.2289 | AE50: 56.2289 | AF50: 52.2543
A51: CHP: Int Gasification.COH.CCSoxy.PUB | C51: PUICSCOH3 | D51: EUR17 | E51: NCAP_COST | H51: =H50 -> 3087 | I51: =I50 -> 2467.5 | J51: =J50 -> 2152.5 | K51: =K50 -> 1995 | L51: =L50 -> 1942.5 | M51: =M50 -> 1942.5 | N51: 1942.5 | O51: 1942.5 | Q51: PUICSCOH3 [ CHP: Int Gasification.COH.CCSoxy.PUB ] | R51: B-NewTechs | S51: EUR10 | U51: 3594.675 | V51: 3594.675 | X51: 2821.966 | AD51: 56.2289 | AE51: 56.2289 | AF51: 52.2543
A52: CHP: Int Gasification.COL.CCSpoc.PUB | C52: PUICSCOL1 | D52: EUR17 | E52: NCAP_COST | H52: =H53 -> 4704 | I52: =I53 -> 3748.5 | J52: =J53 -> 3276 | K52: =K53 -> 3045 | L52: =L53 -> 2950.5 | M52: =M53 -> 2950.5 | N52: 2950.5 | O52: 2950.5 | Q52: PUICSCOL1 [ CHP: Int Gasification.COL.CCSpoc.PUB ] | R52: B-NewTechs | S52: EUR10 | U52: 4134.753 | V52: 4134.753 | X52: 3395.945 | AD52: 85.8046 | AE52: 85.8046 | AF52: 77.2709
A53: CHP: Int Gasification.COL.CCSprc.PUB | C53: PUICSCOL2 | D53: EUR17 | E53: NCAP_COST | H53: =H43*1.05 -> 4704 | I53: =I43*1.05 -> 3748.5 | J53: =J43*1.05 -> 3276 | K53: =K43*1.05 -> 3045 | L53: =L43*1.05 -> 2950.5 | M53: =M43*1.05 -> 2950.5 | N53: 2950.5 | O53: 2950.5 | Q53: PUICSCOL2 [ CHP: Int Gasification.COL.CCSprc.PUB ] | R53: B-NewTechs | S53: EUR10 | U53: 3892.77 | V53: 3892.77 | X53: 3109.54 | AD53: 85.8046 | AE53: 85.8046 | AF53: 77.2709
A54: CHP: Int Gasification.COL.CCSoxy.PUB | C54: PUICSCOL3 | D54: EUR17 | E54: NCAP_COST | H54: =H53 -> 4704 | I54: =I53 -> 3748.5 | J54: =J53 -> 3276 | K54: =K53 -> 3045 | L54: =L53 -> 2950.5 | M54: =M53 -> 2950.5 | N54: 2950.5 | O54: 2950.5 | Q54: PUICSCOL3 [ CHP: Int Gasification.COL.CCSoxy.PUB ] | R54: B-NewTechs | S54: EUR10 | U54: 3954.727 | V54: 3954.727 | X54: 3103.695 | AD54: 84.7525 | AE54: 84.7525 | AF54: 77.0371
A55: CHP: Steam.Turbine.SupCr.COH.CCSpoc.PUB | C55: PUSCSCOH1 | D55: EUR17 | E55: NCAP_COST | H55: =H42*1.05 -> 3066 | I55: =I42*1.05 -> 2688 | J55: =J42*1.05 -> 2488.5 | K55: =K42*1.05 -> 2383.5 | L55: =L42*1.05 -> 2352 | M55: =M42*1.05 -> 2352 | N55: 2352 | O55: 2352 | Q55: PUSCSCOH1 [ CHP: Steam.Turbine.SupCr.COH.CCSpoc.PUB ] | R55: B-NewTechs | S55: EUR10 | U55: 3499.986 | V55: 3499.986 | X55: 2826.642 | AD55: 51.9036 | AE55: 51.9036 | AF55: 48.3966
A56: CHP: Steam.Turbine.SupCr.COH.CCSoxy.PUB | C56: PUSCSCOH3 | D56: EUR17 | E56: NCAP_COST | H56: =H41*1.05 -> 3066 | I56: =I41*1.05 -> 2761.5 | J56: =J41*1.05 -> 2604 | K56: =K41*1.05 -> 2520 | L56: =L41*1.05 -> 2478 | M56: =M41*1.05 -> 2478 | N56: 2478 | O56: 2478 | Q56: PUSCSCOH3 [ CHP: Steam.Turbine.SupCr.COH.CCSoxy.PUB ] | R56: B-NewTechs | S56: EUR10 | U56: 3648.449 | V56: 3648.449 | X56: 2756.502 | AD56: 46.8769 | AE56: 46.8769 | AF56: 45.2403
A57: CHP: Steam.Turbine.SupCr.COL.CCSpoc.PUB | C57: PUSCSCOL1 | D57: EUR17 | E57: NCAP_COST | H57: =H55+1000 -> 4066 | I57: =I55+1000 -> 3688 | J57: =J55+1000 -> 3488.5 | K57: =K55+1000 -> 3383.5 | L57: =L55+1000 -> 3352 | M57: =M55+1000 -> 3352 | N57: 3352 | O57: 3352 | Q57: PUSCSCOL1 [ CHP: Steam.Turbine.SupCr.COL.CCSpoc.PUB ] | R57: B-NewTechs | S57: EUR10 | U57: 3883.418 | V57: 3883.418 | X57: 3221.764 | AD57: 59.1514 | AE57: 59.1514 | AF57: 55.6444
A58: CHP: Steam.Turbine.SupCr.COL.CCSoxy.PUB | C58: PUSCSCOL3 | D58: EUR17 | E58: NCAP_COST | H58: =H56+1000 -> 4066 | I58: =I56+1000 -> 3761.5 | J58: =J56+1000 -> 3604 | K58: =K56+1000 -> 3520 | L58: =L56+1000 -> 3478 | M58: =M56+1000 -> 3478 | N58: 3478 | O58: 3478 | Q58: PUSCSCOL3 [ CHP: Steam.Turbine.SupCr.COL.CCSoxy.PUB ] | R58: B-NewTechs | S58: EUR10 | U58: 2625.574 | V58: 2625.574 | X58: 2459.576 | AD58: 54.1247 | AE58: 54.1247 | AF58: 52.4881
A59: CCGT Combined Cycle Gas Turbine + CCS Seq post combustion | C59: EUCCGASCCSpos20 | D59: EUR17 | E59: NCAP_FOM | H59: =CCUS_Summary!AT65 -> 37.703599 | I59: =CCUS_Summary!AU65 -> 33.02242 | J59: =CCUS_Summary!AV65 -> 30.981527 | K59: =CCUS_Summary!AW65 -> 29.857936 | L59: =CCUS_Summary!AX65 -> 29.182318 | M59: =CCUS_Summary!AY65 -> 28.812241 | N59: 28.812241 | O59: 28.812241
A60: Supercritical pulverised coal + CCS Seq post combustion | C60: EUPCCOHCCSpos20 | D60: EUR17 | E60: NCAP_FOM | H60: =CCUS_Summary!AT66 -> 59.772773 | I60: =CCUS_Summary!AU66 -> 53.97105 | J60: =CCUS_Summary!AV66 -> 50.805638 | K60: =CCUS_Summary!AW66 -> 49.098142 | L60: =CCUS_Summary!AX66 -> 48.445274 | M60: =CCUS_Summary!AY66 -> 48.445274 | N60: 48.445274 | O60: 48.445274 | Q60: EUSTWOOCCS01 | R60: ELC_IET4 | S60: EUR13 | T60: 4560 | V60: 4220 | X60: 3930 | Z60: 3660 | AA60: 3430 | AC60: 102.78 | AE60: 96.66 | AF60: 91.44 | AG60: 86.58 | AH60: 82.44
A61: Super-critical Pulverised Coal + CCS Seq Oxyfuel | C61: EUPCCOHCCSoxy20 | D61: EUR17 | E61: NCAP_FOM | H61: =CCUS_Summary!AT67 -> 67.062136 | I61: =CCUS_Summary!AU67 -> 58.948459 | J61: =CCUS_Summary!AV67 -> 54.615994 | K61: =CCUS_Summary!AW67 -> 52.308007 | L61: =CCUS_Summary!AX67 -> 51.431063 | M61: =CCUS_Summary!AY67 -> 51.431063 | N61: 51.431063 | O61: 51.431063 | Q61: EUPCCOLCCSpos20 [ Fluidised bed lignite + CCS Seq post combustion ] | R61: ELC_IET4 | S61: EUR13 | T61: 3500 | AC61: 87.5
A62: Integrated Gasification Combined Cycle lignite + CCS Seq pre-combustion | C62: EUIGCOLCCSpre20 | D62: EUR17 | E62: NCAP_FOM | H62: =CCUS_Summary!AT68 -> 98.578993 | I62: =CCUS_Summary!AU68 -> 78.596841 | J62: =CCUS_Summary!AV68 -> 68.733521 | K62: =CCUS_Summary!AW68 -> 63.713148 | L62: =CCUS_Summary!AX68 -> 61.84873 | M62: =CCUS_Summary!AY68 -> 61.84873 | N62: 61.84873 | O62: 61.84873 | Q62: EUSTIISGASCS101 [ EPLT: Steam Turbine.CO2Seq.IISGAS ] | R62: B-NewTechs | S62: EUR10 | U62: 1246.6514 | W62: 1169.6831 | Y62: 1092.7148 | AB62: 59.107088
A63: Integrated gasification combined cycle + CCS Seq pre combustion | C63: EUIGCOHCCSpre20 | D63: EUR17 | E63: NCAP_FOM | H63: =CCUS_Summary!AT69 -> 88.326966 | I63: =CCUS_Summary!AU69 -> 70.422919 | J63: =CCUS_Summary!AV69 -> 61.585366 | K63: =CCUS_Summary!AW69 -> 57.087102 | L63: =CCUS_Summary!AX69 -> 55.41658 | M63: =CCUS_Summary!AY69 -> 55.41658 | N63: 55.41658 | O63: 55.41658
A64: Biomass Integrated Gasification CC + CCS Seq post combustion | C64: EUIGCCWOOCCS01 | D64: EUR17 | E64: NCAP_FOM | H64: =CCUS_Summary!AT70 -> 133.4 | I64: =CCUS_Summary!AU70 -> 118.68568 | J64: =CCUS_Summary!AV70 -> 97.909583 | K64: =CCUS_Summary!AW70 -> 84.540033 | L64: =CCUS_Summary!AX70 -> 74.779494 | M64: =CCUS_Summary!AY70 -> 70.708367 | N64: 70.708367 | O64: 70.708367
A65: CHP: Comb CYC.GAS.CCSpoc.PUB | C65: PUCCSGAS1 | D65: EUR17 | E65: NCAP_FOM | H65: =H59*1.05 -> 39.588779 | I65: =I59*1.05 -> 34.673542 | J65: =J59*1.05 -> 32.530604 | K65: =K59*1.05 -> 31.350833 | L65: =L59*1.05 -> 30.641434 | M65: =M59*1.05 -> 30.252853 | N65: 30.252853 | O65: 30.252853
A66: CHP: Comb CYC.GAS.CCSprc.PUB | C66: PUCCSGAS2 | D66: EUR17 | E66: NCAP_FOM | H66: =H65 -> 39.588779 | I66: =I65 -> 34.673542 | J66: =J65 -> 32.530604 | K66: =K65 -> 31.350833 | L66: =L65 -> 30.641434 | M66: =M65 -> 30.252853 | N66: 30.252853 | O66: 30.252853
A67: CHP: Comb CYC.GAS.CCSoxy.PUB | C67: PUCCSGAS3 | D67: EUR17 | E67: NCAP_FOM | H67: =H66 -> 39.588779 | I67: =I66 -> 34.673542 | J67: =J66 -> 32.530604 | K67: =K66 -> 31.350833 | L67: =L66 -> 30.641434 | M67: =M66 -> 30.252853 | N67: 30.252853 | O67: 30.252853
A68: CHP: Int Gasification.COH.CCSpoc.PUB | C68: PUICSCOH1 | D68: EUR17 | E68: NCAP_FOM | H68: =H69 -> 92.743314 | I68: =I69 -> 73.944065 | J68: =J69 -> 64.664634 | K68: =K69 -> 59.941457 | L68: =L69 -> 58.187409 | M68: =M69 -> 58.187409 | N68: 58.187409 | O68: 58.187409
A69: CHP: Int Gasification.COH.CCSprc.PUB | C69: PUICSCOH2 | D69: EUR17 | E69: NCAP_FOM | H69: =H63*1.05 -> 92.743314 | I69: =I63*1.05 -> 73.944065 | J69: =J63*1.05 -> 64.664634 | K69: =K63*1.05 -> 59.941457 | L69: =L63*1.05 -> 58.187409 | M69: =M63*1.05 -> 58.187409 | N69: 58.187409 | O69: 58.187409
A70: CHP: Int Gasification.COH.CCSoxy.PUB | C70: PUICSCOH3 | D70: EUR17 | E70: NCAP_FOM | H70: =H69 -> 92.743314 | I70: =I69 -> 73.944065 | J70: =J69 -> 64.664634 | K70: =K69 -> 59.941457 | L70: =L69 -> 58.187409 | M70: =M69 -> 58.187409 | N70: 58.187409 | O70: 58.187409
A71: CHP: Int Gasification.COL.CCSpoc.PUB | C71: PUICSCOL1 | D71: EUR17 | E71: NCAP_FOM | H71: =H72 -> 103.50794 | I71: =I72 -> 82.526683 | J71: =J72 -> 72.170197 | K71: =K72 -> 66.898805 | L71: =L72 -> 64.941167 | M71: =M72 -> 64.941167 | N71: 64.941167 | O71: 64.941167
A72: CHP: Int Gasification.COL.CCSprc.PUB | C72: PUICSCOL2 | D72: EUR17 | E72: NCAP_FOM | H72: =H62*1.05 -> 103.50794 | I72: =I62*1.05 -> 82.526683 | J72: =J62*1.05 -> 72.170197 | K72: =K62*1.05 -> 66.898805 | L72: =L62*1.05 -> 64.941167 | M72: =M62*1.05 -> 64.941167 | N72: 64.941167 | O72: 64.941167
A73: CHP: Int Gasification.COL.CCSoxy.PUB | C73: PUICSCOL3 | D73: EUR17 | E73: NCAP_FOM | H73: =H72 -> 103.50794 | I73: =I72 -> 82.526683 | J73: =J72 -> 72.170197 | K73: =K72 -> 66.898805 | L73: =L72 -> 64.941167 | M73: =M72 -> 64.941167 | N73: 64.941167 | O73: 64.941167
A74: CHP: Steam.Turbine.SupCr.COH.CCSpoc.PUB | C74: PUSCSCOH1 | D74: EUR17 | E74: NCAP_FOM | H74: =H61*1.05 -> 70.415242 | I74: =I61*1.05 -> 61.895882 | J74: =J61*1.05 -> 57.346794 | K74: =K61*1.05 -> 54.923407 | L74: =L61*1.05 -> 54.002616 | M74: =M61*1.05 -> 54.002616 | N74: 54.002616 | O74: 54.002616
A75: CHP: Steam.Turbine.SupCr.COH.CCSoxy.PUB | C75: PUSCSCOH3 | D75: EUR17 | E75: NCAP_FOM | H75: =H60*1.05 -> 62.761412 | I75: =I60*1.05 -> 56.669602 | J75: =J60*1.05 -> 53.34592 | K75: =K60*1.05 -> 51.553049 | L75: =L60*1.05 -> 50.867537 | M75: =M60*1.05 -> 50.867537 | N75: 50.867537 | O75: 50.867537 | Q75: PUICBGS | R75: EUR10 | S75: B-NewTechs | T75: 1746.486 | U75: 1745.317 | W75: 1744.148 | X75: 1741.81 | Y75: 1707.909 | AB75: 34.9531 | AC75: 34.9531 | AE75: 34.87127 | AF75: 34.8362 | AG75: 34.1348
A76: CHP: Steam.Turbine.SupCr.COL.CCSpoc.PUB | C76: PUSCSCOL1 | D76: EUR17 | E76: NCAP_FOM | H76: =H74 -> 70.415242 | I76: =I74 -> 61.895882 | J76: =J74 -> 57.346794 | K76: =K74 -> 54.923407 | L76: =L74 -> 54.002616 | M76: =M74 -> 54.002616 | N76: 54.002616 | O76: 54.002616 | S76: Attribute | T76: NCAP_COST | U76: NCAP_COST | V76: NCAP_COST | W76: NCAP_COST | X76: NCAP_COST | Y76: NCAP_COST | Z76: NCAP_COST | AA76: NCAP_COST | AB76: NCAP_FOM | AC76: NCAP_FOM | AD76: NCAP_FOM | AE76: NCAP_FOM | AF76: NCAP_FOM | AG76: NCAP_FOM | AH76: NCAP_FOM | AI76: NCAP_FOM
A77: CHP: Steam.Turbine.SupCr.COL.CCSoxy.PUB | C77: PUSCSCOL3 | D77: EUR17 | E77: NCAP_FOM | H77: =H75 -> 62.761412 | I77: =I75 -> 56.669602 | J77: =J75 -> 53.34592 | K77: =K75 -> 51.553049 | L77: =L75 -> 50.867537 | M77: =M75 -> 50.867537 | N77: 50.867537 | O77: 50.867537 | Q77: Process | S77: Scenario\Year | T77: 2006 | U77: 2010 | V77: 2013 | W77: 2015 | X77: 2020 | Y77: 2030 | Z77: 2040 | AA77: 2050 | AB77: 2006 | AC77: 2010 | AD77: 2013 | AE77: 2015 | AF77: 2020 | AG77: 2030 | AH77: 2040 | AI77: 2050
A78: Fluidized Bed Boiler Biomass + steam turbine | C78: EUSTWOO01 | D78: EUR17 | E78: NCAP_COST | F78: =Biomass!AF65 -> 3600 | G78: =Biomass!AG65 -> 3220 | H78: =Biomass!AH65 -> 3080 | I78: =Biomass!AI65 -> 3020 | J78: =Biomass!AJ65 -> 2930 | K78: =Biomass!AK65 -> 2850 | L78: =Biomass!AL65 -> 2730 | M78: =Biomass!AM65 -> 2660 | N78: 2660 | O78: 2660 | Q78: EUSTWOO01 | R78: EUR13 | S78: ELC_IET4 | V78: 2960 | X78: 2620 | Y78: 2330 | Z78: 2060 | AA78: 1830 | AD78: 53.28 | AF78: 47.16 | AG78: 41.94 | AH78: 37.08 | AI78: 32.94
A79: Biomass Integrated Gasification Combined Cycle | C79: EUIGCCWOO01 | D79: EUR17 | E79: NCAP_COST | F79: =Biomass!AF66 -> 5300 | G79: =Biomass!AG66 -> 4740 | H79: =Biomass!AH66 -> 4540 | I79: =Biomass!AI66 -> 4450 | J79: =Biomass!AJ66 -> 4320 | K79: =Biomass!AK66 -> 4190 | L79: =Biomass!AL66 -> 4020 | M79: =Biomass!AM66 -> 3920 | N79: 3920 | O79: 3920 | Q79: EUIGCCWOO01 | R79: EUR13 | S79: ELC_IET4 | V79: 4810 | X79: 3810 | Y79: 3140 | Z79: 2840 | AA79: 2560 | AD79: 105.82 | AF79: 83.82 | AG79: 69.08 | AH79: 62.48 | AI79: 56.32
A80: Biomass Anaerobic Digestion | C80: EUICBGS01 | D80: EUR17 | E80: NCAP_COST | F80: =Biomass!AF67 -> 4700 | G80: =Biomass!AG67 -> 4200 | H80: =Biomass!AH67 -> 4020 | I80: =Biomass!AI67 -> 3950 | J80: =Biomass!AJ67 -> 3830 | K80: =Biomass!AK67 -> 3720 | L80: =Biomass!AL67 -> 3560 | M80: =Biomass!AM67 -> 3480 | N80: 3480 | O80: 3480 | Q80: EUICBGS01 | R80: EUR13 | S80: ELC_IET4 | V80: 3880 | X80: 3180 | Y80: 2760 | Z80: 2520 | AA80: 2300 | AD80: 159.08 | AF80: 130.38 | AG80: 113.16 | AH80: 103.32 | AI80: 94.3
A81: CHP: Anaerobic digestion.SLU.PUB | C81: PUASLU | D81: EUR17 | E81: NCAP_COST | F81: =F80*1.05 -> 4935 | G81: =G80*1.05 -> 4410 | H81: =H80*1.05 -> 4221 | I81: =I80*1.05 -> 4147.5 | J81: =J80*1.05 -> 4021.5 | K81: =K80*1.05 -> 3906 | L81: =L80*1.05 -> 3738 | M81: =M80*1.05 -> 3654 | N81: 3654 | O81: 3654 | Q81: PUASLU | R81: EUR10 | S81: B-NewTechs | T81: 3164.26 | U81: 3248.2941 | W81: 3332.3282 | X81: 3416.3622 | Y81: 3500.3963 | AB81: 153.8603 | AC81: 156.84238 | AE81: 137.97278 | AF81: 137.93858 | AG81: 127.21556
A82: CHP: Biomass.gasification.WOO.PUB | C82: PUGWOO | D82: EUR17 | E82: NCAP_COST | F82: =F79*1.05 -> 5565 | G82: =G79*1.05 -> 4977 | H82: =H79*1.05 -> 4767 | I82: =I79*1.05 -> 4672.5 | J82: =J79*1.05 -> 4536 | K82: =K79*1.05 -> 4399.5 | L82: =L79*1.05 -> 4221 | M82: =M79*1.05 -> 4116 | N82: 4116 | O82: 4116 | Q82: PUGWOO | R82: EUR10 | S82: B-NewTechs | T82: 5418.0662 | U82: 5140.093 | W82: 4862.1198 | X82: 4584.1466 | Y82: 4004.7414 | AB82: 76.749806 | AC82: 76.749806 | AE82: 76.749806 | AF82: 76.749806 | AG82: 76.749806
A83: Fluidized Bed Boiler Biomass + steam turbine | C83: EUSTWOO01 | D83: EUR17 | E83: NCAP_FOM | F83: =Biomass!AR65 -> 72 | G83: =Biomass!AS65 -> 64.368306 | H83: =Biomass!AT65 -> 61.649123 | I83: =Biomass!AU65 -> 60.434229 | J83: =Biomass!AV65 -> 58.680154 | K83: =Biomass!AW65 -> 56.934925 | L83: =Biomass!AX65 -> 54.571124 | M83: =Biomass!AY65 -> 53.26039 | N83: 53.26039 | O83: 53.26039
A84: Biomass Integrated Gasification Combined Cycle | C84: EUIGCCWOO01 | D84: EUR17 | E84: NCAP_FOM | F84: =Biomass!AR66 -> 106 | G84: =Biomass!AS66 -> 94.764451 | H84: =Biomass!AT66 -> 90.76121 | I84: =Biomass!AU66 -> 88.972615 | J84: =Biomass!AV66 -> 86.390227 | K84: =Biomass!AW66 -> 83.820862 | L84: =Biomass!AX66 -> 80.340822 | M84: =Biomass!AY66 -> 78.41113 | N84: 78.41113 | O84: 78.41113
A85: Biomass Anaerobic Digestion | C85: EUICBGS01 | D85: EUR17 | E85: NCAP_FOM | F85: =Biomass!AR67 -> 94 | G85: =Biomass!AS67 -> 84.0364 | H85: =Biomass!AT67 -> 80.486356 | I85: =Biomass!AU67 -> 78.900244 | J85: =Biomass!AV67 -> 76.610202 | K85: =Biomass!AW67 -> 74.331707 | L85: =Biomass!AX67 -> 71.245634 | M85: =Biomass!AY67 -> 69.534398 | N85: 69.534398 | O85: 69.534398
A86: CHP: Anaerobic digestion.SLU.PUB | C86: PUASLU | D86: EUR17 | E86: NCAP_FOM | F86: =F85*1.05 -> 98.7 | G86: =G85*1.05 -> 88.23822 | H86: =H85*1.05 -> 84.510673 | I86: =I85*1.05 -> 82.845256 | J86: =J85*1.05 -> 80.440712 | K86: =K85*1.05 -> 78.048293 | L86: =L85*1.05 -> 74.807916 | M86: =M85*1.05 -> 73.011118 | N86: 73.011118 | O86: 73.011118
A87: CHP: Biomass.gasification.WOO.PUB | C87: PUGWOO | D87: EUR17 | E87: NCAP_FOM | F87: =F84*1.05 -> 111.3 | G87: =G84*1.05 -> 99.502674 | H87: =H84*1.05 -> 95.29927 | I87: =I84*1.05 -> 93.421246 | J87: =J84*1.05 -> 90.709739 | K87: =K84*1.05 -> 88.011905 | L87: =L84*1.05 -> 84.357863 | M87: =M84*1.05 -> 82.331686 | N87: 82.331686 | O87: 82.331686
A88: Lake large scale cheap hydroelectricity > 10 MW | C88: EUHYDLAKELC01 | D88: EUR17 | E88: NCAP_COST | F88: =Hydro_Summary!AF65 -> 1090 | G88: =Hydro_Summary!AG65 -> 1090 | H88: =Hydro_Summary!AH65 -> 1090 | I88: =Hydro_Summary!AI65 -> 1080 | J88: =Hydro_Summary!AJ65 -> 1080 | K88: =Hydro_Summary!AK65 -> 1080 | L88: =Hydro_Summary!AL65 -> 1070 | M88: =Hydro_Summary!AM65 -> 1070 | N88: 1070 | O88: 1070
A89: Lake large scale expensive hydroelectricity > 10 MW | C89: EUHYDLAKELE01 | D89: EUR17 | E89: NCAP_COST | F89: =Hydro_Summary!AF66 -> 3500 | G89: =Hydro_Summary!AG66 -> 3500 | H89: =Hydro_Summary!AH66 -> 3480 | I89: =Hydro_Summary!AI66 -> 3470 | J89: =Hydro_Summary!AJ66 -> 3470 | K89: =Hydro_Summary!AK66 -> 3460 | L89: =Hydro_Summary!AL66 -> 3450 | M89: =Hydro_Summary!AM66 -> 3440 | N89: 3440 | O89: 3440
A90: Lake medium scale cheap hydroelectricity 1-10 MW | C90: EUHYDLAKEMC01 | D90: EUR17 | E90: NCAP_COST | F90: =Hydro_Summary!AF67 -> 1410 | G90: =Hydro_Summary!AG67 -> 1410 | H90: =Hydro_Summary!AH67 -> 1400 | I90: =Hydro_Summary!AI67 -> 1400 | J90: =Hydro_Summary!AJ67 -> 1400 | K90: =Hydro_Summary!AK67 -> 1390 | L90: =Hydro_Summary!AL67 -> 1390 | M90: =Hydro_Summary!AM67 -> 1390 | N90: 1390 | O90: 1390
A91: Lake medium scale expensive hydroelectricity 1-10 MW | C91: EUHYDLAKEME01 | D91: EUR17 | E91: NCAP_COST | F91: =Hydro_Summary!AF68 -> 4000 | G91: =Hydro_Summary!AG68 -> 4000 | H91: =Hydro_Summary!AH68 -> 3980 | I91: =Hydro_Summary!AI68 -> 3970 | J91: =Hydro_Summary!AJ68 -> 3960 | K91: =Hydro_Summary!AK68 -> 3950 | L91: =Hydro_Summary!AL68 -> 3940 | M91: =Hydro_Summary!AM68 -> 3930 | N91: 3930 | O91: 3930
A92: Lake very small cheap hydroelectricity <1 MW | C92: EUHYDLAKESC01 | D92: EUR17 | E92: NCAP_COST | F92: =Hydro_Summary!AF69 -> 1740 | G92: =Hydro_Summary!AG69 -> 1740 | H92: =Hydro_Summary!AH69 -> 1730 | I92: =Hydro_Summary!AI69 -> 1730 | J92: =Hydro_Summary!AJ69 -> 1720 | K92: =Hydro_Summary!AK69 -> 1720 | L92: =Hydro_Summary!AL69 -> 1710 | M92: =Hydro_Summary!AM69 -> 1710 | N92: 1710 | O92: 1710
A93: Lake very small expensive hydroelectricity <1 MW | C93: EUHYDLAKESE01 | D93: EUR17 | E93: NCAP_COST | F93: =Hydro_Summary!AF70 -> 5000 | G93: =Hydro_Summary!AG70 -> 5000 | H93: =Hydro_Summary!AH70 -> 4980 | I93: =Hydro_Summary!AI70 -> 4960 | J93: =Hydro_Summary!AJ70 -> 4950 | K93: =Hydro_Summary!AK70 -> 4940 | L93: =Hydro_Summary!AL70 -> 4920 | M93: =Hydro_Summary!AM70 -> 4910 | N93: 4910 | O93: 4910
A94: Run of River hydroelectricity | C94: EUHYDRUN01 | D94: EUR17 | E94: NCAP_COST | F94: =Hydro_Summary!AF71 -> 3000 | G94: =Hydro_Summary!AG71 -> 3000 | H94: =Hydro_Summary!AH71 -> 2990 | I94: =Hydro_Summary!AI71 -> 2980 | J94: =Hydro_Summary!AJ71 -> 2970 | K94: =Hydro_Summary!AK71 -> 2960 | L94: =Hydro_Summary!AL71 -> 2950 | M94: =Hydro_Summary!AM71 -> 2950 | N94: 2950 | O94: 2950
A95: Lake large scale cheap hydroelectricity > 10 MW | C95: EUHYDLAKELC01 | D95: EUR17 | E95: NCAP_FOM | F95: =Hydro_Summary!AR65 -> 5.45 | G95: =Hydro_Summary!AS65 -> 5.4450862 | H95: =Hydro_Summary!AT65 -> 5.4250265 | I95: =Hydro_Summary!AU65 -> 5.4078027 | J95: =Hydro_Summary!AV65 -> 5.3969059 | K95: =Hydro_Summary!AW65 -> 5.3815973 | L95: =Hydro_Summary!AX65 -> 5.3680715 | M95: =Hydro_Summary!AY65 -> 5.3560779 | N95: 5.3560779 | O95: 5.3560779
A96: Lake large scale expensive hydroelectricity > 10 MW | C96: EUHYDLAKELE01 | D96: EUR17 | E96: NCAP_FOM | F96: =Hydro_Summary!AR66 -> 17.5 | G96: =Hydro_Summary!AS66 -> 17.484222 | H96: =Hydro_Summary!AT66 -> 17.41981 | I96: =Hydro_Summary!AU66 -> 17.364504 | J96: =Hydro_Summary!AV66 -> 17.329514 | K96: =Hydro_Summary!AW66 -> 17.280358 | L96: =Hydro_Summary!AX66 -> 17.236927 | M96: =Hydro_Summary!AY66 -> 17.198415 | N96: 17.198415 | O96: 17.198415
A97: Lake medium scale cheap hydroelectricity 1-10 MW | C97: EUHYDLAKEMC01 | D97: EUR17 | E97: NCAP_FOM | F97: =Hydro_Summary!AR67 -> 7.05 | G97: =Hydro_Summary!AS67 -> 7.0436436 | H97: =Hydro_Summary!AT67 -> 7.0176948 | I97: =Hydro_Summary!AU67 -> 6.9954145 | J97: =Hydro_Summary!AV67 -> 6.9813186 | K97: =Hydro_Summary!AW67 -> 6.9615157 | L97: =Hydro_Summary!AX67 -> 6.9440191 | M97: =Hydro_Summary!AY67 -> 6.9285044 | N97: 6.9285044 | O97: 6.9285044
A98: Lake medium scale expensive hydroelectricity 1-10 MW | C98: EUHYDLAKEME01 | D98: EUR17 | E98: NCAP_FOM | F98: =Hydro_Summary!AR68 -> 20 | G98: =Hydro_Summary!AS68 -> 19.981968 | H98: =Hydro_Summary!AT68 -> 19.908354 | I98: =Hydro_Summary!AU68 -> 19.845148 | J98: =Hydro_Summary!AV68 -> 19.805159 | K98: =Hydro_Summary!AW68 -> 19.748981 | L98: =Hydro_Summary!AX68 -> 19.699345 | M98: =Hydro_Summary!AY68 -> 19.655332 | N98: 19.655332 | O98: 19.655332
A99: Lake very small cheap hydroelectricity <1 MW | C99: EUHYDLAKESC01 | D99: EUR17 | E99: NCAP_FOM | F99: =Hydro_Summary!AR69 -> 17.4 | G99: =Hydro_Summary!AS69 -> 17.384312 | H99: =Hydro_Summary!AT69 -> 17.320268 | I99: =Hydro_Summary!AU69 -> 17.265278 | J99: =Hydro_Summary!AV69 -> 17.230489 | K99: =Hydro_Summary!AW69 -> 17.181613 | L99: =Hydro_Summary!AX69 -> 17.13843 | M99: =Hydro_Summary!AY69 -> 17.100138 | N99: 17.100138 | O99: 17.100138
A100: Lake very small expensive hydroelectricity <1 MW | C100: EUHYDLAKESE01 | D100: EUR17 | E100: NCAP_FOM | F100: =Hydro_Summary!AR70 -> 50 | G100: =Hydro_Summary!AS70 -> 49.954919 | H100: =Hydro_Summary!AT70 -> 49.770885 | I100: =Hydro_Summary!AU70 -> 49.612869 | J100: =Hydro_Summary!AV70 -> 49.512898 | K100: =Hydro_Summary!AW70 -> 49.372452 | L100: =Hydro_Summary!AX70 -> 49.248362 | M100: =Hydro_Summary!AY70 -> 49.138329 | N100: 49.138329 | O100: 49.138329
A101: Run of River hydroelectricity | C101: EUHYDRUN01 | D101: EUR17 | E101: NCAP_FOM | F101: =Hydro_Summary!AR71 -> 15 | G101: =Hydro_Summary!AS71 -> 14.986476 | H101: =Hydro_Summary!AT71 -> 14.931265 | I101: =Hydro_Summary!AU71 -> 14.883861 | J101: =Hydro_Summary!AV71 -> 14.853869 | K101: =Hydro_Summary!AW71 -> 14.811736 | L101: =Hydro_Summary!AX71 -> 14.774509 | M101: =Hydro_Summary!AY71 -> 14.741499 | N101: 14.741499 | O101: 14.741499
...

Sheet LCEO techs
B2: LCEO Technology Group 1 | C2: LCEO CCUS | D2: DataProvided | E2: Process | F2: Process Description | G2: Technology_sector | H2: Main_Activity | I2: Fossil_RES | J2: Technology_subtype | K2: Technology_main_input | L2: Unit - capacity | M2: Unit - activity | N2: Primary Resources
B3: Advanced alternative fuels | C3: CCUS | D3: NO | E3: S_CCUS_ATM | F3: Supply convert Atmospheric CO2 to Diesel | G3: Supply and transformation | H3: Power to liquid | K3: Electricity | L3: GW | M3: PJ
B4: Advanced alternative fuels | C4: CCUS | D4: NO | E4: S_CCUS_ATM_LowAF | F4: Supply convert Atmospheric CO2 to Diesel | G4: Supply and transformation | H4: Power to liquid | K4: Electricity | L4: GW | M4: PJ
B5: Advanced alternative fuels | C5: CCUS | D5: NO | E5: S_CCUS_ATM_MeOH | F5: Supply convert Atmospheric CO2 to Methanol | G5: Supply and transformation | H5: Power to liquid | K5: Electricity | L5: GW | M5: PJ
B6: Advanced alternative fuels | C6: CCUS | D6: NO | E6: S_CCUS_ATM_MeOH_LowAF | F6: Supply convert Atmospheric CO2 to Methanol LowAF | G6: Supply and transformation | H6: Power to liquid | K6: Electricity | L6: GW | M6: PJ
B7: Advanced alternative fuels | C7: CCUS | D7: NO | E7: S_CCUS_EMIS | F7: Supply convert CCS emission to Diesel | G7: Supply and transformation | H7: Power to liquid | K7: Electricity | L7: GW | M7: PJ
B8: Advanced alternative fuels | C8: CCUS | D8: NO | E8: S_CCUS_EMIS_H2T | F8: CO2 Hydrogenation to Diesel with centralized tank | G8: Supply and transformation | H8: Power to liquid | K8: Electricity | L8: GW | M8: PJ
B9: Advanced alternative fuels | C9: CCUS | D9: NO | E9: S_CCUS_EMIS_H2T_LowAF | F9: CO2 Hydrogenation to Diesel with centralized tank | G9: Supply and transformation | H9: Power to liquid | K9: Electricity | L9: GW | M9: PJ
B10: Advanced alternative fuels | C10: CCUS | D10: NO | E10: S_CCUS_EMIS_H2U | F10: CO2 Hydrogenation to Diesel with underground storage | G10: Supply and transformation | H10: Power to liquid | K10: Electricity | L10: GW | M10: PJ
B11: Advanced alternative fuels | C11: CCUS | D11: NO | E11: S_CCUS_EMIS_H2U_LowAF | F11: CO2 Hydrogenation to Diesel with underground storage | G11: Supply and transformation | H11: Power to liquid | K11: Electricity | L11: GW | M11: PJ
B12: Advanced alternative fuels | C12: CCUS | D12: NO | E12: S_CCUS_EMIS_LowAF | F12: Supply convert CCS emission to Diesel | G12: Supply and transformation | H12: Power to liquid | K12: Electricity | L12: GW | M12: PJ
B13: Advanced alternative fuels | C13: CCUS | D13: NO | E13: S_CCUS_EMISMeOH | F13: Supply convert CCS emission to Methanol | G13: Supply and transformation | H13: Power to liquid | K13: Electricity | L13: GW | M13: PJ
B14: Advanced alternative fuels | C14: CCUS | D14: NO | E14: S_CCUS_EMISMeOH_H2 | F14: Supply convert CCS emission to Methanol supplied by H2 | G14: Supply and transformation | H14: Power to liquid | K14: Electricity | L14: GW | M14: PJ
... B36: Geothermal | C36: non-CCUS | D36: YES | E36: EUGEOORC01 | F36: Geothermal hydrothermal with ORC | G36: Power sector | H36: Electricity generation | K36: Geothermal | L36: GW | M36: PJ
B37: Geothermal | C37: non-CCUS | D37: YES | E37: HHTHGEO001 | F37: District Heating. Heat.GEO. New | G37: Buildings - Residential | H37: Heat generation | J37: District heating | K37: Coal | L37: GW | M37: PJ
B38: Geothermal | C38: non-CCUS | D38: YES | E38: R_ES-SH-DH_GEO | F38: Residential boiler for sp heat - Detached house 1945 to 1969 : Geothermal Energy | G38: Buildings - Residential | H38: Heating | K38: Geothermal | L38: 000units | M38: PJ
B39: Geothermal | C39: non-CCUS | D39: YES | E39: R_ES-SH-DH-70_GEO | F39: Residential boiler for sp heat - Detached house 1970 to 2010 : Geothermal Energy | G39: Buildings - Residential | H39: Heating | K39: Geothermal | L39: 000units | M39: PJ
B40: Geothermal | C40: non-CCUS | D40: YES | E40: R_ES-SH-FL_GEO | F40: Residential boiler for sp heat - Flat : Geothermal Energy | G40: Buildings - Residential | H40: Heating | K40: Geothermal | L40: 000units | M40: PJ
B41: Geothermal | C41: non-CCUS | D41: YES | E41: R_ES-SH-SD_GEO | F41: Residential boiler for sp heat - Semi-detached house : Geothermal Energy | G41: Buildings - Residential | H41: Heating | K41: Geothermal | L41: 000units | M41: PJ
B42: Geothermal | C42: non-CCUS | D42: YES | E42: R_ES-WH-DH_GEO01 | F42: Geo Heat Exchanger water heater - Detached | G42: Buildings - Residential | H42: Hot water | K42: Geothermal | L42: GW | M42: PJ
B43: Geothermal | C43: non-CCUS | D43: YES | E43: R_ES-WH-FL_GEO01 | F43: Geo Heat Exchanger water heater - Flat | G43: Buildings - Residential | H43: Hot water | K43: Geothermal | L43: GW | M43: PJ
B44: Geothermal | C44: non-CCUS | D44: YES | E44: R_ES-WH-SD_GEO01 | F44: Geo Heat Exchanger water heater - Semi-Detached | G44: Buildings - Residential | H44: Hot water | K44: Geothermal | L44: GW | M44: PJ
B45: H2 and fuel cells - DELIV | C45: non-CCUS | D45: YES | E45: AGRGASH2C01 | F45: Fuel Tech - H2 Delivery from centralized production to blending (COMP+USTOR+TR+BLENDING+(nocosNATGASINF))-AGR | G45: Supply and transformation | H45: Transport and distribution | J45: Fuel transport | K45: Hydrogen | L45: PJ-a | M45: PJ
B46: H2 and fuel cells - DELIV | C46: non-CCUS | D46: YES | E46: COMGASH2C01 | F46: Fuel Tech - H2 Delivery from centralized production to blending (COMP+USTOR+TR+BLENDING+(nocosNATGASINF))-COM | G46: Supply and transformation | H46: Transport and distribution | J46: Fuel transport | K46: Hydrogen | L46: PJ-a | M46: PJ
B47: H2 and fuel cells - DELIV | C47: non-CCUS | D47: YES | E47: ELCGASH2C01 | F47: Fuel Tech - H2 Delivery from centralized production to blending (COMP+USTOR+TR+BLENDING+(nocosNATGASINF))-ELC | G47: Supply and transformation | H47: Transport and distribution | J47: Fuel transport | K47: Hydrogen | L47: PJ-a | M47: PJ
B48: H2 and fuel cells - DELIV | C48: non-CCUS | D48: YES | E48: INDGASH2C01 | F48: Fuel Tech - H2 Delivery from centralized production to blending (COMP+USTOR+TR+BLENDING+(nocosNATGASINF))-IND | G48: Supply and transformation | H48: Transport and distribution | J48: Fuel transport | K48: Hydrogen | L48: PJ-a | M48: PJ
B49: H2 and fuel cells - DELIV | C49: non-CCUS | D49: YES | E49: INDGH2C01 | F49: Fuel Tech - H2 Delivery from centralized production (COMP+TR+DP - Industrial) | G49: Supply and transformation | H49: Transport and distribution | J49: Fuel transport | K49: Hydrogen | L49: PJ-a | M49: PJ
B50: H2 and fuel cells - DELIV | C50: non-CCUS | D50: YES | E50: RSDGASH2C01 | F50: Fuel Tech - H2 Delivery from centralized production to blending (COMP+USTOR+TR+BLENDING+(nocosNATGASINF))-RSD | G50: Supply and transformation | H50: Transport and distribution | J50: Fuel transport | K50: Hydrogen | L50: PJ-a | M50: PJ
B51: H2 and fuel cells - DELIV | C51: non-CCUS | D51: YES | E51: RSDGH2C01 | F51: Fuel Tech - H2 Delivery from centralized production (COMP+TR+DP - Residential) | G51: Supply and transformation | H51: Transport and distribution | J51: Fuel transport | K51: Hydrogen | L51: PJ-a | M51: PJ
B52: H2 and fuel cells - DELIV | C52: non-CCUS | D52: YES | E52: RSDGH2C02 | F52: Fuel Tech - H2 Delivery from centralized production (COMP+USTOR+TR+DP - Residential) | G52: Supply and transformation | H52: Transport and distribution | J52: Fuel transport | K52: Hydrogen | L52: PJ-a | M52: PJ
B53: H2 and fuel cells - DELIV | C53: non-CCUS | D53: YES | E53: RSDGH2D01 | F53: Fuel Tech - H2 Delivery from local production (LOCGSTORB+DP - Residential) | G53: Supply and transformation | H53: Transport and distribution | J53: Fuel transport | K53: Hydrogen | L53: PJ-a | M53: PJ
B54: H2 and fuel cells - DELIV | C54: non-CCUS | D54: YES | E54: TRAGASH2C01 | F54: Fuel Tech - H2 Delivery from centralized production to blending (COMP+USTOR+TR+BLENDING+(nocosNATGASINF))-TRA | G54: Supply and transformation | H54: Transport and distribution | J54: Fuel transport | K54: Hydrogen | L54: PJ-a | M54: PJ
B55: H2 and fuel cells - DELIV | C55: non-CCUS | D55: YES | E55: TRAGH2C01 | F55: Fuel Tech - H2 Delivery from centralized production (COMP+USTOR+TR+LIQ+LSTORB+RTS+REFLG(large)) | G55: Supply and transformation | H55: Transport and distribution | J55: Fuel transport | K55: Hydrogen | L55: PJ-a | M55: PJ
B56: H2 and fuel cells - DELIV | C56: non-CCUS | D56: YES | E56: TRAGH2C02 | F56: Fuel Tech - H2 Delivery from centralized production (COMP+TR+LIQ+LSTORB+RTS+REFLG(large)) | G56: Supply and transformation | H56: Transport and distribution | J56: Fuel transport | K56: Hydrogen | L56: PJ-a | M56: PJ
... B63: H2 and fuel cells - DELIV | C63: non-CCUS | D63: YES | E63: TRALH2D01 | F63: Fuel Tech - H2 Delivery from local production (LOCGSTORB+ONSITELIQ+REFLL (large)) | G63: Supply and transformation | H63: Transport and distribution | J63: Fuel transport | K63: Hydrogen | L63: PJ-a | M63: PJ
B64: H2 and fuel cells - PROD | C64: CCUS | D64: YES | E64: SCOAH2GCC01 | F64: H2 Production-Coal Gasification + Carbon Capture, big size, centralized | G64: Supply and transformation | H64: Hydrogen generation | K64: Coal | L64: GW | M64: PJ
B65: H2 and fuel cells - PROD | C65: CCUS | D65: YES | E65: SCOAH2GCC02 | F65: H2 Production-Coal Gasification + Carbon Capture, medium size, centralized | G65: Supply and transformation | H65: Hydrogen generation | K65: Coal | L65: GW | M65: PJ
B66: H2 and fuel cells - PROD | C66: CCUS | D66: YES | E66: SGASH2RCC01 | F66: H2 Production-Methane Steam Reforming + Carbon Capture, large size, centralized | G66: Supply and transformation | H66: Hydrogen generation | K66: Gas (possibly blended) | L66: GW | M66: PJ
B67: H2 and fuel cells - PROD | C67: CCUS | D67: YES | E67: SGASH2RCC02 | F67: H2 Production-Methane Steam Reforming + Carbon Capture, small size, centralized | G67: Supply and transformation | H67: Hydrogen generation | K67: Gas (possibly blended) | L67: GW | M67: PJ
B68: H2 and fuel cells - PROD | C68: non-CCUS | D68: YES | E68: ENUCH2EC01 | F68: H2 Production-Very High Temperature Reactor CHP, centralized | G68: Power sector | H68: Hydrogen generation | K68: Nuclear | L68: GW | M68: PJ
B69: H2 and fuel cells - PROD | C69: non-CCUS | D69: YES | E69: HHTHH2001 | F69: District Heating. Heat.Hydrogen. New | G69: Buildings - Residential | H69: Heat generation | J69: District heating | K69: Hydrogen | L69: GW | M69: PJ
B70: H2 and fuel cells - PROD | C70: non-CCUS | D70: YES | E70: SBIOH2GC01 | F70: H2 Production-Biomass Gasification, medium size, centralized | G70: Supply and transformation | H70: Hydrogen generation | J70: Gasification | K70: Other biomass | L70: GW | M70: PJ
B71: H2 and fuel cells - PROD | C71: non-CCUS | D71: YES | E71: SBIOH2GCC01 | F71: H2 Production-Biomass Gasification + Carbon Capture, medium size, centralized | G71: Supply and transformation | H71: Hydrogen generation | J71: Gasification - CCS | K71: Other biomass | L71: GW | M71: PJ
B72: H2 and fuel cells - PROD | C72: non-CCUS | D72: YES | E72: SBIOH2GD01 | F72: H2 Production-Biomass Gasification, small size, decentralized | G72: Supply and transformation | H72: Hydrogen generation | J72: Gasification | K72: Other biomass | L72: GW | M72: PJ
B73: H2 and fuel cells - PROD | C73: non-CCUS | D73: YES | E73: SBIOH2RC01 | F73: H2 Production-Biomass Steam Reforming, centralized | G73: Supply and transformation | H73: Hydrogen generation | J73: Steam reforming | K73: Other biomass | L73: GW | M73: PJ
B74: H2 and fuel cells - PROD | C74: non-CCUS | D74: YES | E74: SCOAH2GC01 | F74: H2 Production-Coal Gasification, large size, centralized | G74: Supply and transformation | H74: Hydrogen generation | K74: Coal | L74: GW | M74: PJ
B75: H2 and fuel cells - PROD | C75: non-CCUS | D75: YES | E75: SCOAH2GC02 | F75: H2 Production-Coal Gasification, medium size, centralized | G75: Supply and transformation | H75: Hydrogen generation | K75: Coal | L75: GW | M75: PJ
B76: H2 and fuel cells - PROD | C76: non-CCUS | D76: YES | E76: SELCH2EC01 | F76: H2 Production-Alkaline Electrolyser, large size, centralized | G76: Supply and transformation | H76: Hydrogen generation | J76: Electrolysers | K76: Electricity | L76: GW | M76: PJ
B77: H2 and fuel cells - PROD | C77: non-CCUS | D77: YES | E77: SELCH2EC01_LowAF | F77: H2 Production-Alkaline Electrolyser, large size, centralized - Pseudo with LowAF | G77: Supply and transformation | H77: Hydrogen generation | J77: Electrolysers | K77: Electricity | L77: GW | M77: PJ
B78: H2 and fuel cells - PROD | C78: non-CCUS | D78: YES | E78: SELCH2EC02 | F78: H2 Production-Alkaline Electrolyser, medium size, centralized | G78: Supply and transformation | H78: Hydrogen generation | J78: Electrolysers | K78: Electricity | L78: GW | M78: PJ
B79: H2 and fuel cells - PROD | C79: non-CCUS | D79: YES | E79: SELCH2EC02_LowAF | F79: H2 Production-Alkaline Electrolyser, medium size, centralized - Pseudo with LowAF | G79: Supply and transformation | H79: Hydrogen generation | J79: Electrolysers | K79: Electricity | L79: GW | M79: PJ
B80: H2 and fuel cells - PROD | C80: non-CCUS | D80: YES | E80: SELCH2ED01 | F80: H2 Production-Alkaline Electrolyser, small size, decentralized | G80: Supply and transformation | H80: Hydrogen generation | J80: Electrolysers | K80: Electricity | L80: GW | M80: PJ
B81: H2 and fuel cells - PROD | C81: non-CCUS | D81: YES | E81: SELCH2ED01_LowAF | F81: H2 Production-Alkaline Electrolyser, small size, decentralized - Pseudo with LowAF | G81: Supply and transformation | H81: Hydrogen generation | J81: Electrolysers | K81: Electricity | L81: GW | M81: PJ
B82: H2 and fuel cells - PROD | C82: non-CCUS | D82: YES | E82: SELCH2PEM01 | F82: PEM Electrolyzer - Proton Exchange Membrane - Start 2015 | G82: Supply and transformation | H82: Hydrogen generation | J82: Electrolysers | K82: Electricity | L82: GW | M82: PJ
B83: H2 and fuel cells - PROD | C83: non-CCUS | D83: YES | E83: SELCH2PEM01_LowAF | F83: PEM Electrolyzer - Proton Exchange Membrane - Pseudo with LowAF | G83: Supply and transformation | H83: Hydrogen generation | J83: Electrolysers | K83: Electricity | L83: GW | M83: PJ
B84: H2 and fuel cells - PROD | C84: non-CCUS | D84: YES | E84: SETHH2RD01 | F84: H2 Production-Ethanol Steam Reforming, decentralized | G84: Supply and transformation | H84: Hydrogen generation | J84: Steam reforming | K84: Biofuel | L84: GW | M84: PJ
B85: H2 and fuel cells - PROD | C85: non-CCUS | D85: YES | E85: SGASH2KC01 | F85: H2 Production-Kvaerner Process, centralized | G85: Supply and transformation | H85: Hydrogen generation | K85: Gas (possibly blended) | L85: GW | M85: PJ
B86: H2 and fuel cells - PROD | C86: non-CCUS | D86: YES | E86: SGASH2RC01 | F86: H2 Production-Methane Steam Reforming, large size, centralized | G86: Supply and transformation | H86: Hydrogen generation | K86: Gas (possibly blended) | L86: GW | M86: PJ
B87: H2 and fuel cells - PROD | C87: non-CCUS | D87: YES | E87: SGASH2RC02 | F87: H2 Production-Methane Steam Reforming, small size, centralized | G87: Supply and transformation | H87: Hydrogen generation | K87: Gas (possibly blended) | L87: GW | M87: PJ
B88: H2 and fuel cells - PROD | C88: non-CCUS | D88: YES | E88: SGASH2RD01 | F88: H2 Production-Methane Steam Reforming, medium size, decentralized | G88: Supply and transformation | H88: Hydrogen generation | K88: Gas (possibly blended) | L88: GW | M88: PJ
B89: H2 and fuel cells - PROD | C89: non-CCUS | D89: YES | E89: SGASH2RD02 | F89: H2 Production-Methane Steam Reforming, small size, decentralized | G89: Supply and transformation | H89: Hydrogen generation | K89: Gas (possibly blended) | L89: GW | M89: PJ
B90: H2 and fuel cells - PROD | C90: non-CCUS | D90: YES | E90: SGASSH2RC01 | F90: H2 Production-Solar Steam Reforming of Methane, centralized | G90: Supply and transformation | H90: Hydrogen generation | K90: Gas (possibly blended) | L90: GW | M90: PJ
B91: H2 and fuel cells - PROD | C91: non-CCUS | D91: YES | E91: SGASSH2RD01 | F91: H2 Production-Solar Steam Reforming of Methane, decentralized | G91: Supply and transformation | H91: Hydrogen generation | K91: Gas (possibly blended) | L91: GW | M91: PJ
B92: H2 and fuel cells - PROD | C92: non-CCUS | D92: YES | E92: SHFOH2POC01 | F92: H2 Production-Central PO of Heavy Oil (CPO3) | G92: Supply and transformation | H92: Hydrogen generation | K92: Petroleum (possibly blended) | L92: GW | M92: PJ
B93: H2 and fuel cells - related | C93: non-CCUS | D93: YES | E93: C_ES-SP-HO_GASPEM | F93: Fuel cell - PEMFC - for heat and power - Hospital | G93: Buildings - Commercial | H93: CHP | J93: Fuel Cell | K93: Gas (possibly blended) | L93: GW | M93: PJ
B94: H2 and fuel cells - related | C94: non-CCUS | D94: YES | E94: C_ES-SP-HO_GASSOFC | F94: Fuel cell - SOFC - for heat and power - Hospital | G94: Buildings - Commercial | H94: CHP | J94: Fuel Cell | K94: Gas (possibly blended) | L94: GW | M94: PJ
B95: H2 and fuel cells - related | C95: non-CCUS | D95: YES | E95: C_ES-SP-HR_GASPEM | F95: Fuel cell - PEMFC - for heat and power - Hotels & Restaurant | G95: Buildings - Commercial | H95: CHP | J95: Fuel Cell | K95: Gas (possibly blended) | L95: GW | M95: PJ
B96: H2 and fuel cells - related | C96: non-CCUS | D96: YES | E96: C_ES-SP-HR_GASSOFC | F96: Fuel cell - SOFC - for heat and power - Hotels & Restaurant | G96: Buildings - Commercial | H96: CHP | J96: Fuel Cell | K96: Gas (possibly blended) | L96: GW | M96: PJ
B97: H2 and fuel cells - related | C97: non-CCUS | D97: YES | E97: C_ES-SP-OF_GASPEM | F97: Fuel cell - PEMFC - for heat and power - Offices (Offices, Schools/Universities, Museums etc) | G97: Buildings - Commercial | H97: CHP | J97: Fuel Cell | K97: Gas (possibly blended) | L97: GW | M97: PJ
B98: H2 and fuel cells - related | C98: non-CCUS | D98: YES | E98: C_ES-SP-OF_GASSOFC | F98: Fuel cell - SOFC - for heat and power - Offices (Offices, Schools/Universities, Museums etc) | G98: Buildings - Commercial | H98: CHP | J98: Fuel Cell | K98: Gas (possibly blended) | L98: GW | M98: PJ
B99: H2 and fuel cells - related | C99: non-CCUS | D99: YES | E99: C_ES-SP-SL_GASPEM | F99: Fuel cell - PEMFC - for heat and power - Shop – Large (shopping malls) | G99: Buildings - Commercial | H99: CHP | J99: Fuel Cell | K99: Gas (possibly blended) | L99: GW | M99: PJ
B100: H2 and fuel cells - related | C100: non-CCUS | D100: YES | E100: C_ES-SP-SL_GASSOFC | F100: Fuel cell - SOFC - for heat and power - Shop – Large (shopping malls) | G100: Buildings - Commercial | H100: CHP | J100: Fuel Cell | K100: Gas (possibly blended) | L100: GW | M100: PJ
B101: H2 and fuel cells - related | C101: non-CCUS | D101: YES | E101: C_ES-SP-SR_GASPEM | F101: Fuel cell - PEMFC - for heat and power - Sport and Recreation | G101: Buildings - Commercial | H101: CHP | J101: Fuel Cell | K101: Gas (possibly blended) | L101: GW | M101: PJ
B102: H2 and fuel cells - related | C102: non-CCUS | D102: YES | E102: C_ES-SP-SR_GASSOFC | F102: Fuel cell - SOFC - for heat and power - Sport and Recreation | G102: Buildings - Commercial | H102: CHP | J102: Fuel Cell | K102: Gas (possibly blended) | L102: GW | M102: PJ
B103: H2 and fuel cells - related | C103: non-CCUS | D103: YES | E103: C_ES-SP-SS_GASPEM | F103: Fuel cell - PEMFC - for heat and power - Shop – Small (shops) | G103: Buildings - Commercial | H103: CHP | J103: Fuel Cell | K103: Gas (possibly blended) | L103: GW | M103: PJ
B104: H2 and fuel cells - related | C104: non-CCUS | D104: YES | E104: C_ES-SP-SS_GASSOFC | F104: Fuel cell - SOFC - for heat and power - Shop – Small (shops) | G104: Buildings - Commercial | H104: CHP | J104: Fuel Cell | K104: Gas (possibly blended) | L104: GW | M104: PJ
... B108: H2 and fuel cells - related | C108: non-CCUS | D108: YES | E108: R_ES-CHP-SD_GAS04 | F108: CHP fuel cells – Natural Gas fuel cell (SD) | G108: Buildings - Residential | H108: Heating | J108: Fuel Cell | K108: Gas (possibly blended) | L108: 000units | M108: PJ
B109: H2 and Fuel cells - STOR | C109: non-CCUS | D109: YES | E109: P_STH2SDT | F109: Dummy tech STH2SDT | G109: Supply and transformation | H109: Storage of hydrogen | L109: PJ-a | M109: PJ
B110: H2 and Fuel cells - STOR | C110: non-CCUS | D110: YES | E110: P_STH2SGT | F110: Dummy tech STH2SGT | G110: Supply and transformation | H110: Storage of hydrogen | L110: PJ-a | M110: PJ
B111: H2 and Fuel cells - STOR | C111: non-CCUS | D111: YES | E111: P_STH2SUG | F111: Dummy tech STH2SUG | G111: Supply and transformation | H111: Storage of hydrogen | L111: PJ-a | M111: PJ
B112: H2 and fuel cells - STOR | C112: non-CCUS | D112: YES | E112: STH2SDT | F112: Distributed Hydrogen Gas Tank Storage: DayNite/Seasonal | G112: Supply and transformation | H112: Storage of hydrogen | L112: PJ-a | M112: PJ
B113: H2 and fuel cells - STOR | C113: non-CCUS | D113: YES | E113: STH2SGT | F113: Centralised Hydrogen Gas Tank Storage: DayNite/Seasonal | G113: Supply and transformation | H113: Storage of hydrogen | L113: PJ-a | M113: PJ
B114: H2 and fuel cells - STOR | C114: non-CCUS | D114: YES | E114: STH2SUG | F114: Centralised Hydrogen Underground Storage: DayNite/Seasonal | G114: Supply and transformation | H114: Storage of hydrogen | L114: PJ-a | M114: PJ
B115: H2 and fuel cells - TRADE | C115: non-CCUS | D115: YES | E115: TB_SYNH2CU_AT_DE_01 | F115: IRE(B)-SYNH2CU Trade with DE | G115: Supply and transformation | H115: Trade | M115: PJ | N115: 1
B116: H2 and fuel cells - TRADE | C116: non-CCUS | D116: YES | E116: TB_SYNH2CU_AT_HU_01 | F116: IRE(B)-SYNH2CU Trade with HU | G116: Supply and transformation | H116: Trade | M116: PJ | N116: 1
B117: H2 and fuel cells - TRADE | C117: non-CCUS | D117: YES | E117: TB_SYNH2CU_AT_IT_01 | F117: IRE(B)-SYNH2CU Trade with IT | G117: Supply and transformation | H117: Trade | M117: PJ | N117: 1
B118: H2 and fuel cells - TRADE | C118: non-CCUS | D118: YES | E118: TB_SYNH2CU_AT_SI_01 | F118: IRE(B)-SYNH2CU Trade with SI | G118: Supply and transformation | H118: Trade | M118: PJ | N118: 1
B119: H2 and fuel cells - TRADE | C119: non-CCUS | D119: YES | E119: TB_SYNH2CU_AT_SK_01 | F119: IRE(B)-SYNH2CU Trade with SK | G119: Supply and transformation | H119: Trade | M119: PJ | N119: 1
B120: H2 and fuel cells - TRADE | C120: non-CCUS | D120: YES | E120: TB_SYNH2CU_BE_DE_01 | F120: IRE(B)-SYNH2CU Trade with DE | G120: Supply and transformation | H120: Trade | M120: PJ | N120: 1
B121: H2 and fuel cells - TRADE | C121: non-CCUS | D121: YES | E121: TB_SYNH2CU_BE_FR_01 | F121: IRE(B)-SYNH2CU Trade with FR | G121: Supply and transformation | H121: Trade | M121: PJ | N121: 1
B122: H2 and fuel cells - TRADE | C122: non-CCUS | D122: YES | E122: TB_SYNH2CU_BE_LU_01 | F122: IRE(B)-SYNH2CU Trade with LU | G122: Supply and transformation | H122: Trade | M122: PJ | N122: 1
B123: H2 and fuel cells - TRADE | C123: non-CCUS | D123: YES | E123: TB_SYNH2CU_BE_NL_01 | F123: IRE(B)-SYNH2CU Trade with NL | G123: Supply and transformation | H123: Trade | M123: PJ | N123: 1
B124: H2 and fuel cells - TRADE | C124: non-CCUS | D124: YES | E124: TB_SYNH2CU_BE_UK_01 | F124: IRE(B)-SYNH2CU Trade with UK | G124: Supply and transformation | H124: Trade | M124: PJ | N124: 1
B125: H2 and fuel cells - TRADE | C125: non-CCUS | D125: YES | E125: TB_SYNH2CU_BG_EL_01 | F125: IRE(B)-SYNH2CU Trade with EL | G125: Supply and transformation | H125: Trade | M125: PJ | N125: 1
B126: H2 and fuel cells - TRADE | C126: non-CCUS | D126: YES | E126: TB_SYNH2CU_CZ_DE_01 | F126: IRE(B)-SYNH2CU Trade with DE | G126: Supply and transformation | H126: Trade | M126: PJ | N126: 1
... B156: H2 and fuel cells - TRADE | C156: non-CCUS | D156: YES | E156: TB_SYNH2CU_SI_HU_01 | F156: IRE(B)-SYNH2CU Trade with SI | G156: Supply and transformation | H156: Trade | M156: PJ | N156: 1
B157: Heat and power from biomass | C157: CCUS | D157: YES | E157: EUIGCCWOOCCS01 | F157: Biomass Integrated Gasification CC + CCS Seq post combustion | G157: Power sector | H157: Electricity generation | K157: Biomass | L157: GW | M157: PJ
B158: Heat and power from biomass | C158: CCUS | D158: YES | E158: EUSTWOOCCS01 | F158: Fluidized Bed Biomass + CCS Seq post combustion | G158: Power sector | H158: Electricity generation | K158: Other biomass | L158: GW | M158: PJ
B159: Heat and power from biomass | C159: CCUS - related | D159: YES | E159: PUOWOO | F159: CHP: Organic.Ranking CYC.WOO.PUB | G159: Power sector | H159: CHP | K159: Other biomass | L159: GW | M159: PJ
B160: Heat and power from biomass | C160: CCUS - related | D160: YES | E160: PUSMUN | F160: CHP: Steam.Turbine.MUN.PUB | G160: Power sector | H160: CHP | K160: Other biomass | L160: GW | M160: PJ
...

Sheet Scenario names
A3: 01_ | B3: Baseline_RefL | C3: =CONCATENATE(A3,B3) -> 01_Baseline_RefL
A4: 02_ | B4: Diversified_LowL | C4: =CONCATENATE(A4,B4) -> 02_Diversified_LowL
A5: 03_ | B5: Diversified_RefL | C5: =CONCATENATE(A5,B5) -> 03_Diversified_RefL
A6: 04_ | B6: Diversified_HighL | C6: =CONCATENATE(A6,B6) -> 04_Diversified_HighL
A7: 05_ | B7: Diversified_CCS_IND_Only | C7: =CONCATENATE(A7,B7) -> 05_Diversified_CCS_IND_Only
A8: 06_ | B8: Diversified_CostCapital | C8: =CONCATENATE(A8,B8) -> 06_Diversified_CostCapital | D8: Most probable result is like 03
A9: 07_ | B9: Diversified_LowFossilPrice | C9: =CONCATENATE(A9,B9) -> 07_Diversified_LowFossilPrice | D9: Even more fossil ?
A10: 08_ | B10: Diversified_RES_EE | C10: =CONCATENATE(A10,B10) -> 08_Diversified_RES_EE
A11: 09_ | B11: PRORes_LowL | C11: =CONCATENATE(A11,B11) -> 09_PRORes_LowL
A12: 10_ | B12: PRORes_RefL | C12: =CONCATENATE(A12,B12) -> 10_PRORes_RefL
A13: 11_ | B13: PRORes_HighL | C13: =CONCATENATE(A13,B13) -> 11_PRORes_HighL
A14: 12_ | B14: PRORes_SET | C14: =CONCATENATE(A14,B14) -> 12_PRORes_SET | D14: Include Lifetime PV as well as SET-plan CSP
A15: 13_ | B15: PRORes_OffshoreDepl | C15: =CONCATENATE(A15,B15) -> 13_PRORes_OffshoreDepl | D15: Maybe already in HighL ?
A16: 14_ | B16: PRORes_HighForest | C16: =CONCATENATE(A16,B16) -> 14_PRORes_HighForest
A17: 15_ | B17: PRORes_NoCCU | C17: =CONCATENATE(A17,B17) -> 15_PRORes_NoCCU
A18: 16_ | B18: PRORes_MaxBiofuel | C18: =CONCATENATE(A18,B18) -> 16_PRORes_MaxBiofuel
A20: ?? | B20: PRORes_CSP | C20: ONLY CSP without the PV reduction | D20: entry CAPEX derived from other runs

Sheet Hydro_Summary
F1: CAPEX (Eur/kW) | R1: OPEX Eur/kW/Year | AB1: Summary | AE1: CAPEX (Eur/kW) | AP1: OPEX Eur/kW/Year | BC1: CAPEX (Eur/kW) | BN1: OPEX Eur/kW/Year | BY1: CAPEX (Eur/kW) | CI1: OPEX Eur/kW/Year
B2: Page Name | C2: Upper left cell | E2: 0 | F2: 1 | G2: 2 | H2: 3 | I2: 4 | J2: 5 | K2: 6 | L2: 7 | M2: 8 | N2: 9 | Q2: 18 | R2: 19 | S2: 20 | T2: 21 | U2: 22 | V2: 23 | W2: 24 | X2: 25 | Y2: 26 | Z2: 27 | AC2: 0 | AD2: 1 | AE2: 2 | AF2: 3 | AG2: 4 | AH2: 5 | AI2: 6 | AJ2: 7 | AK2: 8 | AL2: 9 | AM2: 10 | AR2: 15 | AS2: 16 | AT2: 17 | AU2: 18 | AV2: 19 | AW2: 20 | AX2: 21 | AY2: 22
BA3: MAX | BM3: MAX | BW3: MAX
A4: 0 | G4: 2015 | H4: 2020 | I4: 2025 | J4: 2030 | K4: 2035 | L4: 2040 | M4: 2045 | N4: 2050 | S4: 2015 | T4: 2020 | U4: 2025 | V4: 2030 | W4: 2035 | X4: 2040 | Y4: 2045 | Z4: 2050 | AF4: 2015 | AG4: 2020 | AH4: 2025 | AI4: 2030 | AJ4: 2035 | AK4: 2040 | AL4: 2045 | AM4: 2050 | AR4: 2015 | AS4: 2020 | AT4: 2025 | AU4: 2030 | AV4: 2035 | AW4: 2040 | AX4: 2045 | AY4: 2050 | BC4: 2015 | BD4: 2020 | BE4: 2025 | BF4: 2030 | BG4: 2035 | BH4: 2040 | BI4: 2045 | BJ4: 2050 | BN4: 2015 | BO4: 2020 | BP4: 2025 | BQ4: 2030 | BR4: 2035 | BS4: 2040 | BT4: 2045 | BU4: 2050 | BY4: 2015 | BZ4: 2020 | CA4: 2025 | CB4: 2030 | CC4: 2035 | CD4: 2040 | CE4: 2045 | CF4: 2050 | CG4: Reduction | CJ4: 2015 | CK4: 2020 | CL4: 2025 | CM4: 2030 | CN4: 2035 | CO4: 2040 | CP4: 2045 | CQ4: 2050
A5: 1 | B5: Hydro_large_cheap | C5: G24 | D5: Lake large scale cheap hydroelectricity > 10 MW | E5: ProRES | F5: Ref LR | G5: 1090 | H5: 1090 | I5: 1090 | J5: 1090 | K5: 1090 | L5: 1090 | M5: 1090 | N5: 1090 | P5: Lake large scale cheap hydroelectricity > 10 MW | Q5: ProRES | R5: Ref LR | S5: 5.45 | T5: 5.4432483 | U5: 5.4403565 | V5: 5.4385243 | W5: 5.4370051 | X5: 5.4358417 | Y5: 5.4344153 | Z5: 5.432744 | AB5: 5 | AC5: Lake large scale cheap hydroelectricity > 10 MW | AD5: ProRES | AE5: Ref LR | AF5: 1090 | AG5: 1090 | AH5: 1090 | AI5: 1090 | AJ5: 1090 | AK5: 1090 | AL5: 1090 | AM5: 1090 | AO5: Lake large scale cheap hydroelectricity > 10 MW | AP5: ProRES | AQ5: Ref LR | AR5: 5.45 | AS5: 5.4432483 | AT5: 5.4403565 | AU5: 5.4385243 | AV5: 5.4370051 | AW5: 5.4358417 | AX5: 5.4344153 | AY5: 5.432744 | BA5: ProRES | BC5: 5000 | BD5: 5000 | BE5: 5000 | BF5: 5000 | BG5: 5000 | BH5: 5000 | BI5: 5000 | BJ5: 5000 | BM5: ProRES | BN5: 50 | BO5: 50 | BP5: 50 | BQ5: 50 | BR5: 50 | BS5: 50 | BT5: 50 | BU5: 50 | BW5: Lake large scale cheap hydroelectricity > 10 MW | BY5: 1090 | BZ5: 1090 | CA5: 1090 | CB5: 1090 | CC5: 1090 | CD5: 1090 | CE5: 1090 | CF5: 1090 | CG5: 0 | CI5: Lake large scale cheap hydroelectricity > 10 MW | CK5: 5.45 | CL5: 5.45 | CM5: 5.45 | CN5: 5.45 | CO5: 5.45 | CP5: 5.45 | CQ5: 5.45
A6: 2 | C6: -1 | E6: Baseline | F6: Ref LR | G6: 1090 | H6: 1090 | I6: 1090 | J6: 1090 | K6: 1090 | L6: 1090 | M6: 1090 | N6: 1090 | Q6: Baseline | R6: Ref LR | S6: 5.45 | T6: 5.448274 | U6: 5.4445047 | V6: 5.4406311 | W6: 5.4367103 | X6: 5.4322844 | Y6: 5.4283872 | Z6: 5.4251266 | AB6: 20 | AC6: Lake large scale expensive hydroelectricity > 10 MW | AD6: ProRES | AE6: Ref LR | AF6: 3500 | AG6: 3500 | AH6: 3490 | AI6: 3490 | AJ6: 3490 | AK6: 3490 | AL6: 3490 | AM6: 3490 | AO6: Lake large scale expensive hydroelectricity > 10 MW | AP6: ProRES | AQ6: Ref LR | AR6: 17.5 | AS6: 17.47832 | AT6: 17.469035 | AU6: 17.463151 | AV6: 17.458273 | AW6: 17.454538 | AX6: 17.449957 | AY6: 17.444591 | BA6: Baseline | BC6: 5000 | BD6: 5000 | BE6: 5000 | BF6: 5000 | BG6: 5000 | BH6: 5000 | BI6: 5000 | BJ6: 5000 | BM6: Baseline | BN6: 50 | BO6: 50 | BP6: 50 | BQ6: 50 | BR6: 50 | BS6: 50 | BT6: 50 | BU6: 50 | BW6: Lake large scale expensive hydroelectricity > 10 MW | BY6: 3500 | BZ6: 3500 | CA6: 3500 | CB6: 3500 | CC6: 3500 | CD6: 3500 | CE6: 3500 | CF6: 3500 | CI6: Lake large scale expensive hydroelectricity > 10 MW | CK6: 17.5 | CL6: 17.5 | CM6: 17.5 | CN6: 17.5 | CO6: 17.5 | CP6: 17.5 | CQ6: 17.5
A7: 3 | E7: Diversified portfolio | F7: Ref LR | G7: 1090 | H7: 1090 | I7: 1090 | J7: 1090 | K7: 1080 | L7: 1080 | M7: 1080 | N7: 1080 | Q7: Diversified portfolio | R7: Ref LR | S7: 5.45 | T7: 5.4475549 | U7: 5.437562 | V7: 5.4289669 | W7: 5.4235221 | X7: 5.4158634 | Y7: 5.4090875 | Z7: 5.403072 | AB7: 35 | AC7: Lake medium scale cheap hydroelectricity 1-10 MW | AD7: ProRES | AE7: Ref LR | AF7: 1410 | AG7: 1410 | AH7: 1410 | AI7: 1410 | AJ7: 1410 | AK7: 1410 | AL7: 1410 | AM7: 1410 | AO7: Lake medium scale cheap hydroelectricity 1-10 MW | AP7: ProRES | AQ7: Ref LR | AR7: 7.05 | AS7: 7.0412661 | AT7: 7.0375253 | AU7: 7.0351553 | AV7: 7.0331901 | AW7: 7.0316852 | AX7: 7.02984 | AY7: 7.027678 | BA7: Diversified portfolio | BC7: 5000 | BD7: 5000 | BE7: 5000 | BF7: 5000 | BG7: 5000 | BH7: 5000 | BI7: 5000 | BJ7: 5000 | BM7: Diversified portfolio | BN7: 50 | BO7: 50 | BP7: 50 | BQ7: 50 | BR7: 50 | BS7: 50 | BT7: 50 | BU7: 50 | BW7: Lake medium scale cheap hydroelectricity 1-10 MW | BY7: 1410 | BZ7: 1410 | CA7: 1410 | CB7: 1410 | CC7: 1410 | CD7: 1410 | CE7: 1410 | CF7: 1410 | CI7: Lake medium scale cheap hydroelectricity 1-10 MW | CK7: 7.05 | CL7: 7.05 | CM7: 7.05 | CN7: 7.05 | CO7: 7.05 | CP7: 7.05 | CQ7: 7.05
AB8: 50 | AC8: Lake medium scale expensive hydroelectricity 1-10 MW | AD8: ProRES | AE8: Ref LR | AF8: 4000 | AG8: 4000 | AH8: 3990 | AI8: 3990 | AJ8: 3990 | AK8: 3990 | AL8: 3990 | AM8: 3990 | AO8: Lake medium scale expensive hydroelectricity 1-10 MW | AP8: ProRES | AQ8: Ref LR | AR8: 20 | AS8: 19.975223 | AT8: 19.964611 | AU8: 19.957887 | AV8: 19.952312 | AW8: 19.948043 | AX8: 19.942809 | AY8: 19.936675 | BW8: Lake medium scale expensive hydroelectricity 1-10 MW | BY8: 4000 | BZ8: 4000 | CA8: 4000 | CB8: 4000 | CC8: 4000 | CD8: 4000 | CE8: 4000 | CF8: 4000 | CI8: Lake medium scale expensive hydroelectricity 1-10 MW | CK8: 20 | CL8: 20 | CM8: 20 | CN8: 20 | CO8: 20 | CP8: 20 | CQ8: 20
A9: 0 | G9: 2015 | H9: 2020 | I9: 2025 | J9: 2030 | K9: 2035 | L9: 2040 | M9: 2045 | N9: 2050 | S9: 2015 | T9: 2020 | U9: 2025 | V9: 2030 | W9: 2035 | X9: 2040 | Y9: 2045 | Z9: 2050 | AB9: 65 | AC9: Lake very small cheap hydroelectricity <1 MW | AD9: ProRES | AE9: Ref LR | AF9: 1740 | AG9: 1740 | AH9: 1740 | AI9: 1740 | AJ9: 1740 | AK9: 1740 | AL9: 1740 | AM9: 1730 | AO9: Lake very small cheap hydroelectricity <1 MW | AP9: ProRES | AQ9: Ref LR | AR9: 17.4 | AS9: 17.378444 | AT9: 17.369211 | AU9: 17.363362 | AV9: 17.358512 | AW9: 17.354797 | AX9: 17.350243 | AY9: 17.344907 | BW9: Lake very small cheap hydroelectricity <1 MW | BY9: 1740 | BZ9: 1740 | CA9: 1740 | CB9: 1740 | CC9: 1740 | CD9: 1740 | CE9: 1740 | CF9: 1740 | CI9: Lake very small cheap hydroelectricity <1 MW | CK9: 17.4 | CL9: 17.4 | CM9: 17.4 | CN9: 17.4 | CO9: 17.4 | CP9: 17.4 | CQ9: 17.4
A10: 1 | B10: Hydro_large_cheap | C10: G31 | D10: Lake large scale cheap hydroelectricity > 10 MW | E10: ProRES | F10: High LR | G10: 1090 | H10: 1090 | I10: 1090 | J10: 1090 | K10: 1080 | L10: 1080 | M10: 1080 | N10: 1080 | P10: Lake large scale cheap hydroelectricity > 10 MW | Q10: ProRES | R10: High LR | S10: 5.45 | T10: 5.4364365 | U10: 5.4306323 | V10: 5.4269567 | W10: 5.4239097 | X10: 5.4215771 | Y10: 5.4187177 | Z10: 5.4153682 | AB10: 80 | AC10: Lake very small expensive hydroelectricity <1 MW | AD10: ProRES | AE10: Ref LR | AF10: 5000 | AG10: 4990 | AH10: 4990 | AI10: 4990 | AJ10: 4990 | AK10: 4990 | AL10: 4990 | AM10: 4980 | AO10: Lake very small expensive hydroelectricity <1 MW | AP10: ProRES | AQ10: Ref LR | AR10: 50 | AS10: 49.938058 | AT10: 49.911527 | AU10: 49.894718 | AV10: 49.880781 | AW10: 49.870108 | AX10: 49.857021 | AY10: 49.841688 | BA10: MIN | BM10: MIN | BW10: Lake very small expensive hydroelectricity <1 MW | BY10: 5000 | BZ10: 5000 | CA10: 5000 | CB10: 5000 | CC10: 5000 | CD10: 5000 | CE10: 5000 | CF10: 5000 | CI10: Lake very small expensive hydroelectricity <1 MW | CK10: 50 | CL10: 50 | CM10: 50 | CN10: 50 | CO10: 50 | CP10: 50 | CQ10: 50
A11: 2 | C11: -1 | E11: Baseline | F11: High LR | G11: 1090 | H11: 1090 | I11: 1090 | J11: 1090 | K11: 1080 | L11: 1080 | M11: 1080 | N11: 1080 | Q11: Baseline | R11: High LR | S11: 5.45 | T11: 5.4465311 | U11: 5.4389592 | V11: 5.4311835 | W11: 5.4233186 | X11: 5.4144475 | Y11: 5.4066421 | Z11: 5.400116 | AB11: 95 | AC11: Run of River hydroelectricity | AD11: ProRES | AE11: Ref LR | AF11: 3000 | AG11: 3000 | AH11: 2990 | AI11: 2990 | AJ11: 2990 | AK11: 2990 | AL11: 2990 | AM11: 2990 | AO11: Run of River hydroelectricity | AP11: ProRES | AQ11: Ref LR | AR11: 15 | AS11: 14.981417 | AT11: 14.973458 | AU11: 14.968416 | AV11: 14.964234 | AW11: 14.961032 | AX11: 14.957106 | AY11: 14.952506 | BC11: 2015 | BD11: 2020 | BE11: 2025 | BF11: 2030 | BG11: 2035 | BH11: 2040 | BI11: 2045 | BJ11: 2050 | BN11: 2015 | BO11: 2020 | BP11: 2025 | BQ11: 2030 | BR11: 2035 | BS11: 2040 | BT11: 2045 | BU11: 2050 | BW11: Run of River hydroelectricity | BY11: 3000 | BZ11: 3000 | CA11: 3000 | CB11: 3000 | CC11: 3000 | CD11: 3000 | CE11: 3000 | CF11: 3000 | CI11: Run of River hydroelectricity | CK11: 15 | CL11: 15 | CM11: 15 | CN11: 15 | CO11: 15 | CP11: 15 | CQ11: 15
A12: 3 | E12: Diversified portfolio | F12: High LR | G12: 1090 | H12: 1090 | I12: 1090 | J12: 1080 | K12: 1080 | L12: 1080 | M12: 1070 | N12: 1070 | Q12: Diversified portfolio | R12: High LR | S12: 5.45 | T12: 5.4450862 | U12: 5.4250265 | V12: 5.4078027 | W12: 5.3969059 | X12: 5.3815973 | Y12: 5.3680715 | Z12: 5.3560779 | AB12: 110 | BA12: ProRES | BC12: 1090 | BD12: 1090 | BE12: 1090 | BF12: 1090 | BG12: 1080 | BH12: 1080 | BI12: 1080 | BJ12: 1080 | BM12: ProRES | BN12: 5.45 | BO12: 5.4364365 | BP12: 5.4306323 | BQ12: 5.4269567 | BR12: 5.4239097 | BS12: 5.4215771 | BT12: 5.4187177 | BU12: 5.4153682
AB13: 125 | BA13: Baseline | BC13: 1090 | BD13: 1090 | BE13: 1090 | BF13: 1090 | BG13: 1080 | BH13: 1080 | BI13: 1080 | BJ13: 1080 | BM13: Baseline | BN13: 5.45 | BO13: 5.4465311 | BP13: 5.4389592 | BQ13: 5.4311835 | BR13: 5.4233186 | BS13: 5.4144475 | BT13: 5.4066421 | BU13: 5.400116
A14: 0 | G14: 2015 | H14: 2020 | I14: 2025 | J14: 2030 | K14: 2035 | L14: 2040 | M14: 2045 | N14: 2050 | S14: 2015 | T14: 2020 | U14: 2025 | V14: 2030 | W14: 2035 | X14: 2040 | Y14: 2045 | Z14: 2050 | BA14: Diversified portfolio | BC14: 1090 | BD14: 1090 | BE14: 1090 | BF14: 1080 | BG14: 1080 | BH14: 1080 | BI14: 1070 | BJ14: 1070 | BM14: Diversified portfolio | BN14: 5.45 | BO14: 5.4450862 | BP14: 5.4250265 | BQ14: 5.4078027 | BR14: 5.3969059 | BS14: 5.3815973 | BT14: 5.3680715 | BU14: 5.3560779
A15: 1 | B15: Hydro_large_cheap | C15: G38 | D15: Lake large scale cheap hydroelectricity > 10 MW | E15: ProRES | F15: Low LR | G15: 1090 | H15: 1090 | I15: 1090 | J15: 1090 | K15: 1090 | L15: 1090 | M15: 1090 | N15: 1090 | P15: Lake large scale cheap hydroelectricity > 10 MW | Q15: ProRES | R15: Low LR | S15: 5.45 | T15: 5.45 | U15: 5.45 | V15: 5.45 | W15: 5.45 | X15: 5.45 | Y15: 5.45 | Z15: 5.45
A16: 2 | C16: -1 | E16: Baseline | F16: Low LR | G16: 1090 | H16: 1090 | I16: 1090 | J16: 1090 | K16: 1090 | L16: 1090 | M16: 1090 | N16: 1090 | Q16: Baseline | R16: Low LR | S16: 5.45 | T16: 5.45 | U16: 5.45 | V16: 5.45 | W16: 5.45 | X16: 5.45 | Y16: 5.45 | Z16: 5.45 | AF16: 2015 | AG16: 2020 | AH16: 2025 | AI16: 2030 | AJ16: 2035 | AK16: 2040 | AL16: 2045 | AM16: 2050 | AR16: 2015 | AS16: 2020 | AT16: 2025 | AU16: 2030 | AV16: 2035 | AW16: 2040 | AX16: 2045 | AY16: 2050
A17: 3 | E17: Diversified portfolio | F17: Low LR | G17: 1090 | H17: 1090 | I17: 1090 | J17: 1090 | K17: 1090 | L17: 1090 | M17: 1090 | N17: 1090 | Q17: Diversified portfolio | R17: Low LR | S17: 5.45 | T17: 5.45 | U17: 5.45 | V17: 5.45 | W17: 5.45 | X17: 5.45 | Y17: 5.45 | Z17: 5.45 | AB17: 6 | AC17: Lake large scale cheap hydroelectricity > 10 MW | AD17: Baseline | AE17: Ref LR | AF17: 1090 | AG17: 1090 | AH17: 1090 | AI17: 1090 | AJ17: 1090 | AK17: 1090 | AL17: 1090 | AM17: 1090 | AO17: Lake large scale cheap hydroelectricity > 10 MW | AP17: Baseline | AQ17: Ref LR | AR17: 5.45 | AS17: 5.448274 | AT17: 5.4445047 | AU17: 5.4406311 | AV17: 5.4367103 | AW17: 5.4322844 | AX17: 5.4283872 | AY17: 5.4251266 | BC17: 2015 | BD17: 2020 | BE17: 2025 | BF17: 2030 | BG17: 2035 | BH17: 2040 | BI17: 2045 | BJ17: 2050 | BN17: 2015 | BO17: 2020 | BP17: 2025 | BQ17: 2030 | BR17: 2035 | BS17: 2040 | BT17: 2045 | BU17: 2050 | BW17: MIN
AB18: 21 | AC18: Lake large scale expensive hydroelectricity > 10 MW | AD18: Baseline | AE18: Ref LR | AF18: 3500 | AG18: 3500 | AH18: 3500 | AI18: 3490 | AJ18: 3490 | AK18: 3490 | AL18: 3490 | AM18: 3480 | AO18: Lake large scale expensive hydroelectricity > 10 MW | AP18: Baseline | AQ18: Ref LR | AR18: 17.5 | AS18: 17.494458 | AT18: 17.482354 | AU18: 17.469916 | AV18: 17.457327 | AW18: 17.443115 | AX18: 17.430601 | AY18: 17.420131 | BB18: Max | BC18: 5000 | BD18: 5000 | BE18: 5000 | BF18: 5000 | BG18: 5000 | BH18: 5000 | BI18: 5000 | BJ18: 5000 | BM18: Max | BN18: 50 | BO18: 50 | BP18: 50 | BQ18: 50 | BR18: 50 | BS18: 50 | BT18: 50 | BU18: 50 | BY18: 2015 | BZ18: 2020 | CA18: 2025 | CB18: 2030 | CC18: 2035 | CD18: 2040 | CE18: 2045 | CF18: 2050 | CG18: Reduction | CJ18: 2015 | CK18: 2020 | CL18: 2025 | CM18: 2030 | CN18: 2035 | CO18: 2040 | CP18: 2045 | CQ18: 2050
A19: 0 | G19: 2015 | H19: 2020 | I19: 2025 | J19: 2030 | K19: 2035 | L19: 2040 | M19: 2045 | N19: 2050 | S19: 2015 | T19: 2020 | U19: 2025 | V19: 2030 | W19: 2035 | X19: 2040 | Y19: 2045 | Z19: 2050 | AB19: 36 | AC19: Lake medium scale cheap hydroelectricity 1-10 MW | AD19: Baseline | AE19: Ref LR | AF19: 1410 | AG19: 1410 | AH19: 1410 | AI19: 1410 | AJ19: 1410 | AK19: 1410 | AL19: 1400 | AM19: 1400 | AO19: Lake medium scale cheap hydroelectricity 1-10 MW | AP19: Baseline | AQ19: Ref LR | AR19: 7.05 | AS19: 7.0477673 | AT19: 7.0428914 | AU19: 7.0378806 | AV19: 7.0328088 | AW19: 7.0270835 | AX19: 7.0220422 | AY19: 7.0178243 | BB19: Min | BC19: 1090 | BD19: 1090 | BE19: 1090 | BF19: 1080 | BG19: 1080 | BH19: 1080 | BI19: 1070 | BJ19: 1070 | BM19: Min | BN19: 5.45 | BO19: 5.4364365 | BP19: 5.4250265 | BQ19: 5.4078027 | BR19: 5.3969059 | BS19: 5.3815973 | BT19: 5.3680715 | BU19: 5.3560779 | BW19: Lake large scale cheap hydroelectricity > 10 MW | BY19: 1090 | BZ19: 1090 | CA19: 1090 | CB19: 1080 | CC19: 1080 | CD19: 1080 | CE19: 1070 | CF19: 1070 | CG19: 0.018348624 | CI19: Lake large scale cheap hydroelectricity > 10 MW | CK19: 5.45 | CL19: 5.4364365 | CM19: 5.4250265 | CN19: 5.4078027 | CO19: 5.3969059 | CP19: 5.3815973 | CQ19: 5.3680715
A20: 1 | B20: Hydro_large_expensive | C20: G24 | D20: Lake large scale expensive hydroelectricity > 10 MW | E20: ProRES | F20: Ref LR | G20: 3500 | H20: 3500 | I20: 3490 | J20: 3490 | K20: 3490 | L20: 3490 | M20: 3490 | N20: 3490 | P20: Lake large scale expensive hydroelectricity > 10 MW | Q20: ProRES | R20: Ref LR | S20: 17.5 | T20: 17.47832 | U20: 17.469035 | V20: 17.463151 | W20: 17.458273 | X20: 17.454538 | Y20: 17.449957 | Z20: 17.444591 | AB20: 51 | AC20: Lake medium scale expensive hydroelectricity 1-10 MW | AD20: Baseline | AE20: Ref LR | AF20: 4000 | AG20: 4000 | AH20: 4000 | AI20: 3990 | AJ20: 3990 | AK20: 3990 | AL20: 3980 | AM20: 3980 | AO20: Lake medium scale expensive hydroelectricity 1-10 MW | AP20: Baseline | AQ20: Ref LR | AR20: 20 | AS20: 19.993666 | AT20: 19.979834 | AU20: 19.965619 | AV20: 19.951231 | AW20: 19.934989 | AX20: 19.920687 | AY20: 19.908722 | BW20: Lake large scale expensive hydroelectricity > 10 MW | BY20: 3500 | BZ20: 3490 | CA20: 3480 | CB20: 3470 | CC20: 3470 | CD20: 3460 | CE20: 3450 | CF20: 3440 | CI20: Lake large scale expensive hydroelectricity > 10 MW | CK20: 17.5 | CL20: 17.456448 | CM20: 17.41981 | CN20: 17.364504 | CO20: 17.329514 | CP20: 17.280358 | CQ20: 17.236927
A21: 2 | C21: -1 | E21: Baseline | F21: Ref LR | G21: 3500 | H21: 3500 | I21: 3500 | J21: 3490 | K21: 3490 | L21: 3490 | M21: 3490 | N21: 3480 | Q21: Baseline | R21: Ref LR | S21: 17.5 | T21: 17.494458 | U21: 17.482354 | V21: 17.469916 | W21: 17.457327 | X21: 17.443115 | Y21: 17.430601 | Z21: 17.420131 | AB21: 66 | AC21: Lake very small cheap hydroelectricity <1 MW | AD21: Baseline | AE21: Ref LR | AF21: 1740 | AG21: 1740 | AH21: 1740 | AI21: 1740 | AJ21: 1740 | AK21: 1730 | AL21: 1730 | AM21: 1730 | AO21: Lake very small cheap hydroelectricity <1 MW | AP21: Baseline | AQ21: Ref LR | AR21: 17.4 | AS21: 17.39449 | AT21: 17.382455 | AU21: 17.370088 | AV21: 17.357571 | AW21: 17.34344 | AX21: 17.330998 | AY21: 17.320588 | BW21: Lake medium scale cheap hydroelectricity 1-10 MW | BY21: 1410 | BZ21: 1410 | CA21: 1400 | CB21: 1400 | CC21: 1400 | CD21: 1390 | CE21: 1390 | CF21: 1390 | CI21: Lake medium scale cheap hydroelectricity 1-10 MW | CK21: 7.05 | CL21: 7.0324546 | CM21: 7.0176948 | CN21: 6.9954145 | CO21: 6.9813186 | CP21: 6.9615157 | CQ21: 6.9440191
A22: 3 | E22: Diversified portfolio | F22: Ref LR | G22: 3500 | H22: 3500 | I22: 3490 | J22: 3490 | K22: 3480 | L22: 3480 | M22: 3470 | N22: 3470 | Q22: Diversified portfolio | R22: Ref LR | S22: 17.5 | T22: 17.492149 | U22: 17.460061 | V22: 17.432463 | W22: 17.414979 | X22: 17.390387 | Y22: 17.36863 | Z22: 17.349314 | AB22: 81 | AC22: Lake very small expensive hydroelectricity <1 MW | AD22: Baseline | AE22: Ref LR | AF22: 5000 | AG22: 5000 | AH22: 4990 | AI22: 4990 | AJ22: 4990 | AK22: 4980 | AL22: 4980 | AM22: 4980 | AO22: Lake very small expensive hydroelectricity <1 MW | AP22: Baseline | AQ22: Ref LR | AR22: 50 | AS22: 49.984166 | AT22: 49.949584 | AU22: 49.914047 | AV22: 49.878076 | AW22: 49.837472 | AX22: 49.801718 | AY22: 49.771804 | BW22: Lake medium scale expensive hydroelectricity 1-10 MW | BY22: 4000 | BZ22: 3990 | CA22: 3980 | CB22: 3970 | CC22: 3960 | CD22: 3950 | CE22: 3940 | CF22: 3930 | CI22: Lake medium scale expensive hydroelectricity 1-10 MW | CK22: 20 | CL22: 19.950226 | CM22: 19.908354 | CN22: 19.845148 | CO22: 19.805159 | CP22: 19.748981 | CQ22: 19.699345
AB23: 96 | AC23: Run of River hydroelectricity | AD23: Baseline | AE23: Ref LR | AF23: 3000 | AG23: 3000 | AH23: 3000 | AI23: 2990 | AJ23: 2990 | AK23: 2990 | AL23: 2990 | AM23: 2990 | AO23: Run of River hydroelectricity | AP23: Baseline | AQ23: Ref LR | AR23: 15 | AS23: 14.99525 | AT23: 14.984875 | AU23: 14.974214 | AV23: 14.963423 | AW23: 14.951242 | AX23: 14.940515 | AY23: 14.931541 | BW23: Lake very small cheap hydroelectricity <1 MW | BY23: 1740 | BZ23: 1740 | CA23: 1730 | CB23: 1730 | CC23: 1720 | CD23: 1720 | CE23: 1710 | CF23: 1710 | CI23: Lake very small cheap hydroelectricity <1 MW | CK23: 17.4 | CL23: 17.356696 | CM23: 17.320268 | CN23: 17.265278 | CO23: 17.230489 | CP23: 17.181613 | CQ23: 17.13843
A24: 0 | G24: 2015 | H24: 2020 | I24: 2025 | J24: 2030 | K24: 2035 | L24: 2040 | M24: 2045 | N24: 2050 | S24: 2015 | T24: 2020 | U24: 2025 | V24: 2030 | W24: 2035 | X24: 2040 | Y24: 2045 | Z24: 2050 | AB24: 111 | BW24: Lake very small expensive hydroelectricity <1 MW | BY24: 5000 | BZ24: 4990 | CA24: 4980 | CB24: 4960 | CC24: 4950 | CD24: 4940 | CE24: 4920 | CF24: 4910 | CI24: Lake very small expensive hydroelectricity <1 MW | CK24: 50 | CL24: 49.875564 | CM24: 49.770885 | CN24: 49.612869 | CO24: 49.512898 | CP24: 49.372452 | CQ24: 49.248362
A25: 1 | B25: Hydro_large_expensive | C25: G31 | D25: Lake large scale expensive hydroelectricity > 10 MW | E25: ProRES | F25: High LR | G25: 3500 | H25: 3490 | I25: 3490 | J25: 3490 | K25: 3480 | L25: 3480 | M25: 3480 | N25: 3480 | P25: Lake large scale expensive hydroelectricity > 10 MW | Q25: ProRES | R25: High LR | S25: 17.5 | T25: 17.456448 | U25: 17.43781 | V25: 17.426008 | W25: 17.416224 | X25: 17.408734 | Y25: 17.399552 | Z25: 17.388797 | AB25: 126 | BW25: Run of River hydroelectricity | BY25: 3000 | BZ25: 2990 | CA25: 2990 | CB25: 2980 | CC25: 2970 | CD25: 2960 | CE25: 2950 | CF25: 2950 | CI25: Run of River hydroelectricity | CK25: 15 | CL25: 14.962669 | CM25: 14.931265 | CN25: 14.883861 | CO25: 14.853869 | CP25: 14.811736 | CQ25: 14.774509
A26: 2 | C26: -1 | E26: Baseline | F26: High LR | G26: 3500 | H26: 3500 | I26: 3490 | J26: 3490 | K26: 3480 | L26: 3480 | M26: 3470 | N26: 3470 | Q26: Baseline | R26: High LR | S26: 17.5 | T26: 17.488861 | U26: 17.464548 | V26: 17.43958 | W26: 17.414326 | X26: 17.385841 | Y26: 17.360777 | Z26: 17.339822
A27: 3 | E27: Diversified portfolio | F27: High LR | G27: 3500 | H27: 3500 | I27: 3480 | J27: 3470 | K27: 3470 | L27: 3460 | M27: 3450 | N27: 3440 | Q27: Diversified portfolio | R27: High LR | S27: 17.5 | T27: 17.484222 | U27: 17.41981 | V27: 17.364504 | W27: 17.329514 | X27: 17.280358 | Y27: 17.236927 | Z27: 17.198415
AF28: 2015 | AG28: 2020 | AH28: 2025 | AI28: 2030 | AJ28: 2035 | AK28: 2040 | AL28: 2045 | AM28: 2050 | AR28: 2015 | AS28: 2020 | AT28: 2025 | AU28: 2030 | AV28: 2035 | AW28: 2040 | AX28: 2045 | AY28: 2050
A29: 0 | G29: 2015 | H29: 2020 | I29: 2025 | J29: 2030 | K29: 2035 | L29: 2040 | M29: 2045 | N29: 2050 | S29: 2015 | T29: 2020 | U29: 2025 | V29: 2030 | W29: 2035 | X29: 2040 | Y29: 2045 | Z29: 2050 | AB29: 7 | AC29: Lake large scale cheap hydroelectricity > 10 MW | AD29: Diversified portfolio | AE29: Ref LR | AF29: 1090 | AG29: 1090 | AH29: 1090 | AI29: 1090 | AJ29: 1080 | AK29: 1080 | AL29: 1080 | AM29: 1080 | AO29: Lake large scale cheap hydroelectricity > 10 MW | AP29: Diversified portfolio | AQ29: Ref LR | AR29: 5.45 | AS29: 5.4475549 | AT29: 5.437562 | AU29: 5.4289669 | AV29: 5.4235221 | AW29: 5.4158634 | AX29: 5.4090875 | AY29: 5.403072
A30: 1 | B30: Hydro_large_expensive | C30: G38 | D30: Lake large scale expensive hydroelectricity > 10 MW | E30: ProRES | F30: Low LR | G30: 3500 | H30: 3500 | I30: 3500 | J30: 3500 | K30: 3500 | L30: 3500 | M30: 3500 | N30: 3500 | P30: Lake large scale expensive hydroelectricity > 10 MW | Q30: ProRES | R30: Low LR | S30: 17.5 | T30: 17.5 | U30: 17.5 | V30: 17.5 | W30: 17.5 | X30: 17.5 | Y30: 17.5 | Z30: 17.5 | AB30: 22 | AC30: Lake large scale expensive hydroelectricity > 10 MW | AD30: Diversified portfolio | AE30: Ref LR | AF30: 3500 | AG30: 3500 | AH30: 3490 | AI30: 3490 | AJ30: 3480 | AK30: 3480 | AL30: 3470 | AM30: 3470 | AO30: Lake large scale expensive hydroelectricity > 10 MW | AP30: Diversified portfolio | AQ30: Ref LR | AR30: 17.5 | AS30: 17.492149 | AT30: 17.460061 | AU30: 17.432463 | AV30: 17.414979 | AW30: 17.390387 | AX30: 17.36863 | AY30: 17.349314
A31: 2 | C31: -1 | E31: Baseline | F31: Low LR | G31: 3500 | H31: 3500 | I31: 3500 | J31: 3500 | K31: 3500 | L31: 3500 | M31: 3500 | N31: 3500 | Q31: Baseline | R31: Low LR | S31: 17.5 | T31: 17.5 | U31: 17.5 | V31: 17.5 | W31: 17.5 | X31: 17.5 | Y31: 17.5 | Z31: 17.5 | AB31: 37 | AC31: Lake medium scale cheap hydroelectricity 1-10 MW | AD31: Diversified portfolio | AE31: Ref LR | AF31: 1410 | AG31: 1410 | AH31: 1410 | AI31: 1400 | AJ31: 1400 | AK31: 1400 | AL31: 1400 | AM31: 1400 | AO31: Lake medium scale cheap hydroelectricity 1-10 MW | AP31: Diversified portfolio | AQ31: Ref LR | AR31: 7.05 | AS31: 7.0468371 | AT31: 7.0339104 | AU31: 7.0227921 | AV31: 7.0157487 | AW31: 7.0058416 | AX31: 6.9970765 | AY31: 6.989295
A32: 3 | E32: Diversified portfolio | F32: Low LR | G32: 3500 | H32: 3500 | I32: 3500 | J32: 3500 | K32: 3500 | L32: 3500 | M32: 3500 | N32: 3500 | Q32: Diversified portfolio | R32: Low LR | S32: 17.5 | T32: 17.5 | U32: 17.5 | V32: 17.5 | W32: 17.5 | X32: 17.5 | Y32: 17.5 | Z32: 17.5 | AB32: 52 | AC32: Lake medium scale expensive hydroelectricity 1-10 MW | AD32: Diversified portfolio | AE32: Ref LR | AF32: 4000 | AG32: 4000 | AH32: 3990 | AI32: 3980 | AJ32: 3980 | AK32: 3970 | AL32: 3970 | AM32: 3970 | AO32: Lake medium scale expensive hydroelectricity 1-10 MW | AP32: Diversified portfolio | AQ32: Ref LR | AR32: 20 | AS32: 19.991027 | AT32: 19.954356 | AU32: 19.922814 | AV32: 19.902833 | AW32: 19.874728 | AX32: 19.849862 | AY32: 19.827787
AB33: 67 | AC33: Lake very small cheap hydroelectricity <1 MW | AD33: Diversified portfolio | AE33: Ref LR | AF33: 1740 | AG33: 1740 | AH33: 1740 | AI33: 1730 | AJ33: 1730 | AK33: 1730 | AL33: 1730 | AM33: 1730 | AO33: Lake very small cheap hydroelectricity <1 MW | AP33: Diversified portfolio | AQ33: Ref LR | AR33: 17.4 | AS33: 17.392194 | AT33: 17.36029 | AU33: 17.332849 | AV33: 17.315465 | AW33: 17.291013 | AX33: 17.26938 | AY33: 17.250175
A34: 0 | G34: 2015 | H34: 2020 | I34: 2025 | J34: 2030 | K34: 2035 | L34: 2040 | M34: 2045 | N34: 2050 | S34: 2015 | T34: 2020 | U34: 2025 | V34: 2030 | W34: 2035 | X34: 2040 | Y34: 2045 | Z34: 2050 | AB34: 82 | AC34: Lake very small expensive hydroelectricity <1 MW | AD34: Diversified portfolio | AE34: Ref LR | AF34: 5000 | AG34: 5000 | AH34: 4990 | AI34: 4980 | AJ34: 4980 | AK34: 4970 | AL34: 4960 | AM34: 4960 | AO34: Lake very small expensive hydroelectricity <1 MW | AP34: Diversified portfolio | AQ34: Ref LR | AR34: 50 | AS34: 49.977568 | AT34: 49.88589 | AU34: 49.807036 | AV34: 49.757083 | AW34: 49.68682 | AX34: 49.624656 | AY34: 49.569468
A35: 1 | B35: Hydro_medium_cheap | C35: G24 | D35: Lake medium scale cheap hydroelectricity 1-10 MW | E35: ProRES | F35: Ref LR | G35: 1410 | H35: 1410 | I35: 1410 | J35: 1410 | K35: 1410 | L35: 1410 | M35: 1410 | N35: 1410 | P35: Lake medium scale cheap hydroelectricity 1-10 MW | Q35: ProRES | R35: Ref LR | S35: 7.05 | T35: 7.0412661 | U35: 7.0375253 | V35: 7.0351553 | W35: 7.0331901 | X35: 7.0316852 | Y35: 7.02984 | Z35: 7.027678 | AB35: 97 | AC35: Run of River hydroelectricity | AD35: Diversified portfolio | AE35: Ref LR | AF35: 3000 | AG35: 3000 | AH35: 2990 | AI35: 2990 | AJ35: 2990 | AK35: 2980 | AL35: 2980 | AM35: 2970 | AO35: Run of River hydroelectricity | AP35: Diversified portfolio | AQ35: Ref LR | AR35: 15 | AS35: 14.99327 | AT35: 14.965767 | AU35: 14.942111 | AV35: 14.927125 | AW35: 14.906046 | AX35: 14.887397 | AY35: 14.87084
A36: 2 | C36: -1 | E36: Baseline | F36: Ref LR | G36: 1410 | H36: 1410 | I36: 1410 | J36: 1410 | K36: 1410 | L36: 1410 | M36: 1400 | N36: 1400 | Q36: Baseline | R36: Ref LR | S36: 7.05 | T36: 7.0477673 | U36: 7.0428914 | V36: 7.0378806 | W36: 7.0328088 | X36: 7.0270835 | Y36: 7.0220422 | Z36: 7.0178243 | AB36: 112
A37: 3 | E37: Diversified portfolio | F37: Ref LR | G37: 1410 | H37: 1410 | I37: 1410 | J37: 1400 | K37: 1400 | L37: 1400 | M37: 1400 | N37: 1400 | Q37: Diversified portfolio | R37: Ref LR | S37: 7.05 | T37: 7.0468371 | U37: 7.0339104 | V37: 7.0227921 | W37: 7.0157487 | X37: 7.0058416 | Y37: 6.9970765 | Z37: 6.989295 | AB37: 127
A39: 0 | G39: 2015 | H39: 2020 | I39: 2025 | J39: 2030 | K39: 2035 | L39: 2040 | M39: 2045 | N39: 2050 | S39: 2015 | T39: 2020 | U39: 2025 | V39: 2030 | W39: 2035 | X39: 2040 | Y39: 2045 | Z39: 2050
A40: 1 | B40: Hydro_medium_cheap | C40: G31 | D40: Lake medium scale cheap hydroelectricity 1-10 MW | E40: ProRES | F40: High LR | G40: 1410 | H40: 1410 | I40: 1400 | J40: 1400 | K40: 1400 | L40: 1400 | M40: 1400 | N40: 1400 | P40: Lake medium scale cheap hydroelectricity 1-10 MW | Q40: ProRES | R40: High LR | S40: 7.05 | T40: 7.0324546 | U40: 7.0249464 | V40: 7.0201916 | W40: 7.0162502 | X40: 7.0132327 | Y40: 7.0095339 | Z40: 7.0052011 | AF40: 2015 | AG40: 2020 | AH40: 2025 | AI40: 2030 | AJ40: 2035 | AK40: 2040 | AL40: 2045 | AM40: 2050 | AR40: 2015 | AS40: 2020 | AT40: 2025 | AU40: 2030 | AV40: 2035 | AW40: 2040 | AX40: 2045 | AY40: 2050
A41: 2 | C41: -1 | E41: Baseline | F41: High LR | G41: 1410 | H41: 1410 | I41: 1410 | J41: 1410 | K41: 1400 | L41: 1400 | M41: 1400 | N41: 1400 | Q41: Baseline | R41: High LR | S41: 7.05 | T41: 7.0455127 | U41: 7.0357179 | V41: 7.0256594 | W41: 7.0154856 | X41: 7.00401 | Y41: 6.9939132 | Z41: 6.9854711 | AB41: 10 | AC41: Lake large scale cheap hydroelectricity > 10 MW | AD41: ProRES | AE41: High LR | AF41: 1090 | AG41: 1090 | AH41: 1090 | AI41: 1090 | AJ41: 1080 | AK41: 1080 | AL41: 1080 | AM41: 1080 | AO41: Lake large scale cheap hydroelectricity > 10 MW | AP41: ProRES | AQ41: High LR | AR41: 5.45 | AS41: 5.4364365 | AT41: 5.4306323 | AU41: 5.4269567 | AV41: 5.4239097 | AW41: 5.4215771 | AX41: 5.4187177 | AY41: 5.4153682
A42: 3 | E42: Diversified portfolio | F42: High LR | G42: 1410 | H42: 1410 | I42: 1400 | J42: 1400 | K42: 1400 | L42: 1390 | M42: 1390 | N42: 1390 | Q42: Diversified portfolio | R42: High LR | S42: 7.05 | T42: 7.0436436 | U42: 7.0176948 | V42: 6.9954145 | W42: 6.9813186 | X42: 6.9615157 | Y42: 6.9440191 | Z42: 6.9285044 | AB42: 25 | AC42: Lake large scale expensive hydroelectricity > 10 MW | AD42: ProRES | AE42: High LR | AF42: 3500 | AG42: 3490 | AH42: 3490 | AI42: 3490 | AJ42: 3480 | AK42: 3480 | AL42: 3480 | AM42: 3480 | AO42: Lake large scale expensive hydroelectricity > 10 MW | AP42: ProRES | AQ42: High LR | AR42: 17.5 | AS42: 17.456448 | AT42: 17.43781 | AU42: 17.426008 | AV42: 17.416224 | AW42: 17.408734 | AX42: 17.399552 | AY42: 17.388797
AB43: 40 | AC43: Lake medium scale cheap hydroelectricity 1-10 MW | AD43: ProRES | AE43: High LR | AF43: 1410 | AG43: 1410 | AH43: 1400 | AI43: 1400 | AJ43: 1400 | AK43: 1400 | AL43: 1400 | AM43: 1400 | AO43: Lake medium scale cheap hydroelectricity 1-10 MW | AP43: ProRES | AQ43: High LR | AR43: 7.05 | AS43: 7.0324546 | AT43: 7.0249464 | AU43: 7.0201916 | AV43: 7.0162502 | AW43: 7.0132327 | AX43: 7.0095339 | AY43: 7.0052011
A44: 0 | G44: 2015 | H44: 2020 | I44: 2025 | J44: 2030 | K44: 2035 | L44: 2040 | M44: 2045 | N44: 2050 | S44: 2015 | T44: 2020 | U44: 2025 | V44: 2030 | W44: 2035 | X44: 2040 | Y44: 2045 | Z44: 2050 | AB44: 55 | AC44: Lake medium scale expensive hydroelectricity 1-10 MW | AD44: ProRES | AE44: High LR | AF44: 4000 | AG44: 3990 | AH44: 3990 | AI44: 3980 | AJ44: 3980 | AK44: 3980 | AL44: 3980 | AM44: 3970 | AO44: Lake medium scale expensive hydroelectricity 1-10 MW | AP44: ProRES | AQ44: High LR | AR44: 20 | AS44: 19.950226 | AT44: 19.928926 | AU44: 19.915437 | AV44: 19.904256 | AW44: 19.895696 | AX44: 19.885203 | AY44: 19.872911
A45: 1 | B45: Hydro_medium_cheap | C45: G38 | D45: Lake medium scale cheap hydroelectricity 1-10 MW | E45: ProRES | F45: Low LR | G45: 1410 | H45: 1410 | I45: 1410 | J45: 1410 | K45: 1410 | L45: 1410 | M45: 1410 | N45: 1410 | P45: Lake medium scale cheap hydroelectricity 1-10 MW | Q45: ProRES | R45: Low LR | S45: 7.05 | T45: 7.05 | U45: 7.05 | V45: 7.05 | W45: 7.05 | X45: 7.05 | Y45: 7.05 | Z45: 7.05 | AB45: 70 | AC45: Lake very small cheap hydroelectricity <1 MW | AD45: ProRES | AE45: High LR | AF45: 1740 | AG45: 1740 | AH45: 1730 | AI45: 1730 | AJ45: 1730 | AK45: 1730 | AL45: 1730 | AM45: 1730 | AO45: Lake very small cheap hydroelectricity <1 MW | AP45: ProRES | AQ45: High LR | AR45: 17.4 | AS45: 17.356696 | AT45: 17.338166 | AU45: 17.32643 | AV45: 17.316703 | AW45: 17.309255 | AX45: 17.300126 | AY45: 17.289433
A46: 2 | C46: -1 | E46: Baseline | F46: Low LR | G46: 1410 | H46: 1410 | I46: 1410 | J46: 1410 | K46: 1410 | L46: 1410 | M46: 1410 | N46: 1410 | Q46: Baseline | R46: Low LR | S46: 7.05 | T46: 7.05 | U46: 7.05 | V46: 7.05 | W46: 7.05 | X46: 7.05 | Y46: 7.05 | Z46: 7.05 | AB46: 85 | AC46: Lake very small expensive hydroelectricity <1 MW | AD46: ProRES | AE46: High LR | AF46: 5000 | AG46: 4990 | AH46: 4980 | AI46: 4980 | AJ46: 4980 | AK46: 4970 | AL46: 4970 | AM46: 4970 | AO46: Lake very small expensive hydroelectricity <1 MW | AP46: ProRES | AQ46: High LR | AR46: 50 | AS46: 49.875564 | AT46: 49.822315 | AU46: 49.788593 | AV46: 49.76064 | AW46: 49.739239 | AX46: 49.713006 | AY46: 49.682277
A47: 3 | E47: Diversified portfolio | F47: Low LR | G47: 1410 | H47: 1410 | I47: 1410 | J47: 1410 | K47: 1410 | L47: 1410 | M47: 1410 | N47: 1410 | Q47: Diversified portfolio | R47: Low LR | S47: 7.05 | T47: 7.05 | U47: 7.05 | V47: 7.05 | W47: 7.05 | X47: 7.05 | Y47: 7.05 | Z47: 7.05 | AB47: 100 | AC47: Run of River hydroelectricity | AD47: ProRES | AE47: High LR | AF47: 3000 | AG47: 2990 | AH47: 2990 | AI47: 2990 | AJ47: 2990 | AK47: 2980 | AL47: 2980 | AM47: 2980 | AO47: Run of River hydroelectricity | AP47: ProRES | AQ47: High LR | AR47: 15 | AS47: 14.962669 | AT47: 14.946695 | AU47: 14.936578 | AV47: 14.928192 | AW47: 14.921772 | AX47: 14.913902 | AY47: 14.904683
AB48: 115
A49: 0 | G49: 2015 | H49: 2020 | I49: 2025 | J49: 2030 | K49: 2035 | L49: 2040 | M49: 2045 | N49: 2050 | S49: 2015 | T49: 2020 | U49: 2025 | V49: 2030 | W49: 2035 | X49: 2040 | Y49: 2045 | Z49: 2050 | AB49: 130
A50: 1 | B50: Hydro_medium_expensive | C50: G24 | D50: Lake medium scale expensive hydroelectricity 1-10 MW | E50: ProRES | F50: Ref LR | G50: 4000 | H50: 4000 | I50: 3990 | J50: 3990 | K50: 3990 | L50: 3990 | M50: 3990 | N50: 3990 | P50: Lake medium scale expensive hydroelectricity 1-10 MW | Q50: ProRES | R50: Ref LR | S50: 20 | T50: 19.975223 | U50: 19.964611 | V50: 19.957887 | W50: 19.952312 | X50: 19.948043 | Y50: 19.942809 | Z50: 19.936675
A51: 2 | C51: -1 | E51: Baseline | F51: Ref LR | G51: 4000 | H51: 4000 | I51: 4000 | J51: 3990 | K51: 3990 | L51: 3990 | M51: 3980 | N51: 3980 | Q51: Baseline | R51: Ref LR | S51: 20 | T51: 19.993666 | U51: 19.979834 | V51: 19.965619 | W51: 19.951231 | X51: 19.934989 | Y51: 19.920687 | Z51: 19.908722
A52: 3 | E52: Diversified portfolio | F52: Ref LR | G52: 4000 | H52: 4000 | I52: 3990 | J52: 3980 | K52: 3980 | L52: 3970 | M52: 3970 | N52: 3970 | Q52: Diversified portfolio | R52: Ref LR | S52: 20 | T52: 19.991027 | U52: 19.954356 | V52: 19.922814 | W52: 19.902833 | X52: 19.874728 | Y52: 19.849862 | Z52: 19.827787 | AF52: 2015 | AG52: 2020 | AH52: 2025 | AI52: 2030 | AJ52: 2035 | AK52: 2040 | AL52: 2045 | AM52: 2050 | AR52: 2015 | AS52: 2020 | AT52: 2025 | AU52: 2030 | AV52: 2035 | AW52: 2040 | AX52: 2045 | AY52: 2050
AB53: 11 | AC53: Lake large scale cheap hydroelectricity > 10 MW | AD53: Baseline | AE53: High LR | AF53: 1090 | AG53: 1090 | AH53: 1090 | AI53: 1090 | AJ53: 1080 | AK53: 1080 | AL53: 1080 | AM53: 1080 | AO53: Lake large scale cheap hydroelectricity > 10 MW | AP53: Baseline | AQ53: High LR | AR53: 5.45 | AS53: 5.4465311 | AT53: 5.4389592 | AU53: 5.4311835 | AV53: 5.4233186 | AW53: 5.4144475 | AX53: 5.4066421 | AY53: 5.400116
A54: 0 | G54: 2015 | H54: 2020 | I54: 2025 | J54: 2030 | K54: 2035 | L54: 2040 | M54: 2045 | N54: 2050 | S54: 2015 | T54: 2020 | U54: 2025 | V54: 2030 | W54: 2035 | X54: 2040 | Y54: 2045 | Z54: 2050 | AB54: 26 | AC54: Lake large scale expensive hydroelectricity > 10 MW | AD54: Baseline | AE54: High LR | AF54: 3500 | AG54: 3500 | AH54: 3490 | AI54: 3490 | AJ54: 3480 | AK54: 3480 | AL54: 3470 | AM54: 3470 | AO54: Lake large scale expensive hydroelectricity > 10 MW | AP54: Baseline | AQ54: High LR | AR54: 17.5 | AS54: 17.488861 | AT54: 17.464548 | AU54: 17.43958 | AV54: 17.414326 | AW54: 17.385841 | AX54: 17.360777 | AY54: 17.339822
A55: 1 | B55: Hydro_medium_expensive | C55: G31 | D55: Lake medium scale expensive hydroelectricity 1-10 MW | E55: ProRES | F55: High LR | G55: 4000 | H55: 3990 | I55: 3990 | J55: 3980 | K55: 3980 | L55: 3980 | M55: 3980 | N55: 3970 | P55: Lake medium scale expensive hydroelectricity 1-10 MW | Q55: ProRES | R55: High LR | S55: 20 | T55: 19.950226 | U55: 19.928926 | V55: 19.915437 | W55: 19.904256 | X55: 19.895696 | Y55: 19.885203 | Z55: 19.872911 | AB55: 41 | AC55: Lake medium scale cheap hydroelectricity 1-10 MW | AD55: Baseline | AE55: High LR | AF55: 1410 | AG55: 1410 | AH55: 1410 | AI55: 1410 | AJ55: 1400 | AK55: 1400 | AL55: 1400 | AM55: 1400 | AO55: Lake medium scale cheap hydroelectricity 1-10 MW | AP55: Baseline | AQ55: High LR | AR55: 7.05 | AS55: 7.0455127 | AT55: 7.0357179 | AU55: 7.0256594 | AV55: 7.0154856 | AW55: 7.00401 | AX55: 6.9939132 | AY55: 6.9854711
A56: 2 | C56: -1 | E56: Baseline | F56: High LR | G56: 4000 | H56: 4000 | I56: 3990 | J56: 3990 | K56: 3980 | L56: 3970 | M56: 3970 | N56: 3960 | Q56: Baseline | R56: High LR | S56: 20 | T56: 19.98727 | U56: 19.959483 | V56: 19.930949 | W56: 19.902087 | X56: 19.869532 | Y56: 19.840888 | Z56: 19.816939 | AB56: 56 | AC56: Lake medium scale expensive hydroelectricity 1-10 MW | AD56: Baseline | AE56: High LR | AF56: 4000 | AG56: 4000 | AH56: 3990 | AI56: 3990 | AJ56: 3980 | AK56: 3970 | AL56: 3970 | AM56: 3960 | AO56: Lake medium scale expensive hydroelectricity 1-10 MW | AP56: Baseline | AQ56: High LR | AR56: 20 | AS56: 19.98727 | AT56: 19.959483 | AU56: 19.930949 | AV56: 19.902087 | AW56: 19.869532 | AX56: 19.840888 | AY56: 19.816939
A57: 3 | E57: Diversified portfolio | F57: High LR | G57: 4000 | H57: 4000 | I57: 3980 | J57: 3970 | K57: 3960 | L57: 3950 | M57: 3940 | N57: 3930 | Q57: Diversified portfolio | R57: High LR | S57: 20 | T57: 19.981968 | U57: 19.908354 | V57: 19.845148 | W57: 19.805159 | X57: 19.748981 | Y57: 19.699345 | Z57: 19.655332 | AB57: 71 | AC57: Lake very small cheap hydroelectricity <1 MW | AD57: Baseline | AE57: High LR | AF57: 1740 | AG57: 1740 | AH57: 1740 | AI57: 1730 | AJ57: 1730 | AK57: 1730 | AL57: 1730 | AM57: 1720 | AO57: Lake very small cheap hydroelectricity <1 MW | AP57: Baseline | AQ57: High LR | AR57: 17.4 | AS57: 17.388925 | AT57: 17.36475 | AU57: 17.339925 | AV57: 17.314815 | AW57: 17.286493 | AX57: 17.261573 | AY57: 17.240737
AB58: 86 | AC58: Lake very small expensive hydroelectricity <1 MW | AD58: Baseline | AE58: High LR | AF58: 5000 | AG58: 5000 | AH58: 4990 | AI58: 4980 | AJ58: 4980 | AK58: 4970 | AL58: 4960 | AM58: 4950 | AO58: Lake very small expensive hydroelectricity <1 MW | AP58: Baseline | AQ58: High LR | AR58: 50 | AS58: 49.968175 | AT58: 49.898708 | AU58: 49.827371 | AV58: 49.755217 | AW58: 49.67383 | AX58: 49.602221 | AY58: 49.542348
A59: 0 | G59: 2015 | H59: 2020 | I59: 2025 | J59: 2030 | K59: 2035 | L59: 2040 | M59: 2045 | N59: 2050 | S59: 2015 | T59: 2020 | U59: 2025 | V59: 2030 | W59: 2035 | X59: 2040 | Y59: 2045 | Z59: 2050 | AB59: 101 | AC59: Run of River hydroelectricity | AD59: Baseline | AE59: High LR | AF59: 3000 | AG59: 3000 | AH59: 2990 | AI59: 2990 | AJ59: 2990 | AK59: 2980 | AL59: 2980 | AM59: 2970 | AO59: Run of River hydroelectricity | AP59: Baseline | AQ59: High LR | AR59: 15 | AS59: 14.990453 | AT59: 14.969612 | AU59: 14.948211 | AV59: 14.926565 | AW59: 14.902149 | AX59: 14.880666 | AY59: 14.862704
A60: 1 | B60: Hydro_medium_expensive | C60: G38 | D60: Lake medium scale expensive hydroelectricity 1-10 MW | E60: ProRES | F60: Low LR | G60: 4000 | H60: 4000 | I60: 4000 | J60: 4000 | K60: 4000 | L60: 4000 | M60: 4000 | N60: 4000 | P60: Lake medium scale expensive hydroelectricity 1-10 MW | Q60: ProRES | R60: Low LR | S60: 20 | T60: 20 | U60: 20 | V60: 20 | W60: 20 | X60: 20 | Y60: 20 | Z60: 20 | AB60: 116
A61: 2 | C61: -1 | E61: Baseline | F61: Low LR | G61: 4000 | H61: 4000 | I61: 4000 | J61: 4000 | K61: 4000 | L61: 4000 | M61: 4000 | N61: 4000 | Q61: Baseline | R61: Low LR | S61: 20 | T61: 20 | U61: 20 | V61: 20 | W61: 20 | X61: 20 | Y61: 20 | Z61: 20 | AB61: 131
A62: 3 | E62: Diversified portfolio | F62: Low LR | G62: 4000 | H62: 4000 | I62: 4000 | J62: 4000 | K62: 4000 | L62: 4000 | M62: 4000 | N62: 4000 | Q62: Diversified portfolio | R62: Low LR | S62: 20 | T62: 20 | U62: 20 | V62: 20 | W62: 20 | X62: 20 | Y62: 20 | Z62: 20
A64: 0 | G64: 2015 | H64: 2020 | I64: 2025 | J64: 2030 | K64: 2035 | L64: 2040 | M64: 2045 | N64: 2050 | S64: 2015 | T64: 2020 | U64: 2025 | V64: 2030 | W64: 2035 | X64: 2040 | Y64: 2045 | Z64: 2050 | AF64: 2015 | AG64: 2020 | AH64: 2025 | AI64: 2030 | AJ64: 2035 | AK64: 2040 | AL64: 2045 | AM64: 2050 | AR64: 2015 | AS64: 2020 | AT64: 2025 | AU64: 2030 | AV64: 2035 | AW64: 2040 | AX64: 2045 | AY64: 2050
A65: 1 | B65: Hydro_small_cheap | C65: G24 | D65: Lake very small cheap hydroelectricity <1 MW | E65: ProRES | F65: Ref LR | G65: 1740 | H65: 1740 | I65: 1740 | J65: 1740 | K65: 1740 | L65: 1740 | M65: 1740 | N65: 1730 | P65: Lake very small cheap hydroelectricity <1 MW | Q65: ProRES | R65: Ref LR | S65: 17.4 | T65: 17.378444 | U65: 17.369211 | V65: 17.363362 | W65: 17.358512 | X65: 17.354797 | Y65: 17.350243 | Z65: 17.344907 | AB65: 12 | AC65: Lake large scale cheap hydroelectricity > 10 MW | AD65: Diversified portfolio | AE65: High LR | AF65: 1090 | AG65: 1090 | AH65: 1090 | AI65: 1080 | AJ65: 1080 | AK65: 1080 | AL65: 1070 | AM65: 1070 | AO65: Lake large scale cheap hydroelectricity > 10 MW | AP65: Diversified portfolio | AQ65: High LR | AR65: 5.45 | AS65: 5.4450862 | AT65: 5.4250265 | AU65: 5.4078027 | AV65: 5.3969059 | AW65: 5.3815973 | AX65: 5.3680715 | AY65: 5.3560779
A66: 2 | C66: -1 | E66: Baseline | F66: Ref LR | G66: 1740 | H66: 1740 | I66: 1740 | J66: 1740 | K66: 1740 | L66: 1730 | M66: 1730 | N66: 1730 | Q66: Baseline | R66: Ref LR | S66: 17.4 | T66: 17.39449 | U66: 17.382455 | V66: 17.370088 | W66: 17.357571 | X66: 17.34344 | Y66: 17.330998 | Z66: 17.320588 | AB66: 27 | AC66: Lake large scale expensive hydroelectricity > 10 MW | AD66: Diversified portfolio | AE66: High LR | AF66: 3500 | AG66: 3500 | AH66: 3480 | AI66: 3470 | AJ66: 3470 | AK66: 3460 | AL66: 3450 | AM66: 3440 | AO66: Lake large scale expensive hydroelectricity > 10 MW | AP66: Diversified portfolio | AQ66: High LR | AR66: 17.5 | AS66: 17.484222 | AT66: 17.41981 | AU66: 17.364504 | AV66: 17.329514 | AW66: 17.280358 | AX66: 17.236927 | AY66: 17.198415
A67: 3 | E67: Diversified portfolio | F67: Ref LR | G67: 1740 | H67: 1740 | I67: 1740 | J67: 1730 | K67: 1730 | L67: 1730 | M67: 1730 | N67: 1730 | Q67: Diversified portfolio | R67: Ref LR | S67: 17.4 | T67: 17.392194 | U67: 17.36029 | V67: 17.332849 | W67: 17.315465 | X67: 17.291013 | Y67: 17.26938 | Z67: 17.250175 | AB67: 42 | AC67: Lake medium scale cheap hydroelectricity 1-10 MW | AD67: Diversified portfolio | AE67: High LR | AF67: 1410 | AG67: 1410 | AH67: 1400 | AI67: 1400 | AJ67: 1400 | AK67: 1390 | AL67: 1390 | AM67: 1390 | AO67: Lake medium scale cheap hydroelectricity 1-10 MW | AP67: Diversified portfolio | AQ67: High LR | AR67: 7.05 | AS67: 7.0436436 | AT67: 7.0176948 | AU67: 6.9954145 | AV67: 6.9813186 | AW67: 6.9615157 | AX67: 6.9440191 | AY67: 6.9285044
AB68: 57 | AC68: Lake medium scale expensive hydroelectricity 1-10 MW | AD68: Diversified portfolio | AE68: High LR | AF68: 4000 | AG68: 4000 | AH68: 3980 | AI68: 3970 | AJ68: 3960 | AK68: 3950 | AL68: 3940 | AM68: 3930 | AO68: Lake medium scale expensive hydroelectricity 1-10 MW | AP68: Diversified portfolio | AQ68: High LR | AR68: 20 | AS68: 19.981968 | AT68: 19.908354 | AU68: 19.845148 | AV68: 19.805159 | AW68: 19.748981 | AX68: 19.699345 | AY68: 19.655332
A69: 0 | G69: 2015 | H69: 2020 | I69: 2025 | J69: 2030 | K69: 2035 | L69: 2040 | M69: 2045 | N69: 2050 | S69: 2015 | T69: 2020 | U69: 2025 | V69: 2030 | W69: 2035 | X69: 2040 | Y69: 2045 | Z69: 2050 | AB69: 72 | AC69: Lake very small cheap hydroelectricity <1 MW | AD69: Diversified portfolio | AE69: High LR | AF69: 1740 | AG69: 1740 | AH69: 1730 | AI69: 1730 | AJ69: 1720 | AK69: 1720 | AL69: 1710 | AM69: 1710 | AO69: Lake very small cheap hydroelectricity <1 MW | AP69: Diversified portfolio | AQ69: High LR | AR69: 17.4 | AS69: 17.384312 | AT69: 17.320268 | AU69: 17.265278 | AV69: 17.230489 | AW69: 17.181613 | AX69: 17.13843 | AY69: 17.100138
A70: 1 | B70: Hydro_small_cheap | C70: G31 | D70: Lake very small cheap hydroelectricity <1 MW | E70: ProRES | F70: High LR | G70: 1740 | H70: 1740 | I70: 1730 | J70: 1730 | K70: 1730 | L70: 1730 | M70: 1730 | N70: 1730 | P70: Lake very small cheap hydroelectricity <1 MW | Q70: ProRES | R70: High LR | S70: 17.4 | T70: 17.356696 | U70: 17.338166 | V70: 17.32643 | W70: 17.316703 | X70: 17.309255 | Y70: 17.300126 | Z70: 17.289433 | AB70: 87 | AC70: Lake very small expensive hydroelectricity <1 MW | AD70: Diversified portfolio | AE70: High LR | AF70: 5000 | AG70: 5000 | AH70: 4980 | AI70: 4960 | AJ70: 4950 | AK70: 4940 | AL70: 4920 | AM70: 4910 | AO70: Lake very small expensive hydroelectricity <1 MW | AP70: Diversified portfolio | AQ70: High LR | AR70: 50 | AS70: 49.954919 | AT70: 49.770885 | AU70: 49.612869 | AV70: 49.512898 | AW70: 49.372452 | AX70: 49.248362 | AY70: 49.138329
A71: 2 | C71: -1 | E71: Baseline | F71: High LR | G71: 1740 | H71: 1740 | I71: 1740 | J71: 1730 | K71: 1730 | L71: 1730 | M71: 1730 | N71: 1720 | Q71: Baseline | R71: High LR | S71: 17.4 | T71: 17.388925 | U71: 17.36475 | V71: 17.339925 | W71: 17.314815 | X71: 17.286493 | Y71: 17.261573 | Z71: 17.240737 | AB71: 102 | AC71: Run of River hydroelectricity | AD71: Diversified portfolio | AE71: High LR | AF71: 3000 | AG71: 3000 | AH71: 2990 | AI71: 2980 | AJ71: 2970 | AK71: 2960 | AL71: 2950 | AM71: 2950 | AO71: Run of River hydroelectricity | AP71: Diversified portfolio | AQ71: High LR | AR71: 15 | AS71: 14.986476 | AT71: 14.931265 | AU71: 14.883861 | AV71: 14.853869 | AW71: 14.811736 | AX71: 14.774509 | AY71: 14.741499
A72: 3 | E72: Diversified portfolio | F72: High LR | G72: 1740 | H72: 1740 | I72: 1730 | J72: 1730 | K72: 1720 | L72: 1720 | M72: 1710 | N72: 1710 | Q72: Diversified portfolio | R72: High LR | S72: 17.4 | T72: 17.384312 | U72: 17.320268 | V72: 17.265278 | W72: 17.230489 | X72: 17.181613 | Y72: 17.13843 | Z72: 17.100138 | AB72: 117
AB73: 132
A74: 0 | G74: 2015 | H74: 2020 | I74: 2025 | J74: 2030 | K74: 2035 | L74: 2040 | M74: 2045 | N74: 2050 | S74: 2015 | T74: 2020 | U74: 2025 | V74: 2030 | W74: 2035 | X74: 2040 | Y74: 2045 | Z74: 2050
A75: 1 | B75: Hydro_small_cheap | C75: G38 | D75: Lake very small cheap hydroelectricity <1 MW | E75: ProRES | F75: Low LR | G75: 1740 | H75: 1740 | I75: 1740 | J75: 1740 | K75: 1740 | L75: 1740 | M75: 1740 | N75: 1740 | P75: Lake very small cheap hydroelectricity <1 MW | Q75: ProRES | R75: Low LR | S75: 17.4 | T75: 17.4 | U75: 17.4 | V75: 17.4 | W75: 17.4 | X75: 17.4 | Y75: 17.4 | Z75: 17.4
A76: 2 | C76: -1 | E76: Baseline | F76: Low LR | G76: 1740 | H76: 1740 | I76: 1740 | J76: 1740 | K76: 1740 | L76: 1740 | M76: 1740 | N76: 1740 | Q76: Baseline | R76: Low LR | S76: 17.4 | T76: 17.4 | U76: 17.4 | V76: 17.4 | W76: 17.4 | X76: 17.4 | Y76: 17.4 | Z76: 17.4 | AF76: 2015 | AG76: 2020 | AH76: 2025 | AI76: 2030 | AJ76: 2035 | AK76: 2040 | AL76: 2045 | AM76: 2050 | AR76: 2015 | AS76: 2020 | AT76: 2025 | AU76: 2030 | AV76: 2035 | AW76: 2040 | AX76: 2045 | AY76: 2050
A77: 3 | E77: Diversified portfolio | F77: Low LR | G77: 1740 | H77: 1740 | I77: 1740 | J77: 1740 | K77: 1740 | L77: 1740 | M77: 1740 | N77: 1740 | Q77: Diversified portfolio | R77: Low LR | S77: 17.4 | T77: 17.4 | U77: 17.4 | V77: 17.4 | W77: 17.4 | X77: 17.4 | Y77: 17.4 | Z77: 17.4 | AB77: 15 | AC77: Lake large scale cheap hydroelectricity > 10 MW | AD77: ProRES | AE77: Low LR | AF77: 1090 | AG77: 1090 | AH77: 1090 | AI77: 1090 | AJ77: 1090 | AK77: 1090 | AL77: 1090 | AM77: 1090 | AO77: Lake large scale cheap hydroelectricity > 10 MW | AP77: ProRES | AQ77: Low LR | AR77: 5.45 | AS77: 5.45 | AT77: 5.45 | AU77: 5.45 | AV77: 5.45 | AW77: 5.45 | AX77: 5.45 | AY77: 5.45
AB78: 30 | AC78: Lake large scale expensive hydroelectricity > 10 MW | AD78: ProRES | AE78: Low LR | AF78: 3500 | AG78: 3500 | AH78: 3500 | AI78: 3500 | AJ78: 3500 | AK78: 3500 | AL78: 3500 | AM78: 3500 | AO78: Lake large scale expensive hydroelectricity > 10 MW | AP78: ProRES | AQ78: Low LR | AR78: 17.5 | AS78: 17.5 | AT78: 17.5 | AU78: 17.5 | AV78: 17.5 | AW78: 17.5 | AX78: 17.5 | AY78: 17.5
A79: 0 | G79: 2015 | H79: 2020 | I79: 2025 | J79: 2030 | K79: 2035 | L79: 2040 | M79: 2045 | N79: 2050 | S79: 2015 | T79: 2020 | U79: 2025 | V79: 2030 | W79: 2035 | X79: 2040 | Y79: 2045 | Z79: 2050 | AB79: 45 | AC79: Lake medium scale cheap hydroelectricity 1-10 MW | AD79: ProRES | AE79: Low LR | AF79: 1410 | AG79: 1410 | AH79: 1410 | AI79: 1410 | AJ79: 1410 | AK79: 1410 | AL79: 1410 | AM79: 1410 | AO79: Lake medium scale cheap hydroelectricity 1-10 MW | AP79: ProRES | AQ79: Low LR | AR79: 7.05 | AS79: 7.05 | AT79: 7.05 | AU79: 7.05 | AV79: 7.05 | AW79: 7.05 | AX79: 7.05 | AY79: 7.05
A80: 1 | B80: Hydro_small_expensive | C80: G24 | D80: Lake very small expensive hydroelectricity <1 MW | E80: ProRES | F80: Ref LR | G80: 5000 | H80: 4990 | I80: 4990 | J80: 4990 | K80: 4990 | L80: 4990 | M80: 4990 | N80: 4980 | P80: Lake very small expensive hydroelectricity <1 MW | Q80: ProRES | R80: Ref LR | S80: 50 | T80: 49.938058 | U80: 49.911527 | V80: 49.894718 | W80: 49.880781 | X80: 49.870108 | Y80: 49.857021 | Z80: 49.841688 | AB80: 60 | AC80: Lake medium scale expensive hydroelectricity 1-10 MW | AD80: ProRES | AE80: Low LR | AF80: 4000 | AG80: 4000 | AH80: 4000 | AI80: 4000 | AJ80: 4000 | AK80: 4000 | AL80: 4000 | AM80: 4000 | AO80: Lake medium scale expensive hydroelectricity 1-10 MW | AP80: ProRES | AQ80: Low LR | AR80: 20 | AS80: 20 | AT80: 20 | AU80: 20 | AV80: 20 | AW80: 20 | AX80: 20 | AY80: 20
A81: 2 | C81: -1 | E81: Baseline | F81: Ref LR | G81: 5000 | H81: 5000 | I81: 4990 | J81: 4990 | K81: 4990 | L81: 4980 | M81: 4980 | N81: 4980 | Q81: Baseline | R81: Ref LR | S81: 50 | T81: 49.984166 | U81: 49.949584 | V81: 49.914047 | W81: 49.878076 | X81: 49.837472 | Y81: 49.801718 | Z81: 49.771804 | AB81: 75 | AC81: Lake very small cheap hydroelectricity <1 MW | AD81: ProRES | AE81: Low LR | AF81: 1740 | AG81: 1740 | AH81: 1740 | AI81: 1740 | AJ81: 1740 | AK81: 1740 | AL81: 1740 | AM81: 1740 | AO81: Lake very small cheap hydroelectricity <1 MW | AP81: ProRES | AQ81: Low LR | AR81: 17.4 | AS81: 17.4 | AT81: 17.4 | AU81: 17.4 | AV81: 17.4 | AW81: 17.4 | AX81: 17.4 | AY81: 17.4
A82: 3 | E82: Diversified portfolio | F82: Ref LR | G82: 5000 | H82: 5000 | I82: 4990 | J82: 4980 | K82: 4980 | L82: 4970 | M82: 4960 | N82: 4960 | Q82: Diversified portfolio | R82: Ref LR | S82: 50 | T82: 49.977568 | U82: 49.88589 | V82: 49.807036 | W82: 49.757083 | X82: 49.68682 | Y82: 49.624656 | Z82: 49.569468 | AB82: 90 | AC82: Lake very small expensive hydroelectricity <1 MW | AD82: ProRES | AE82: Low LR | AF82: 5000 | AG82: 5000 | AH82: 5000 | AI82: 5000 | AJ82: 5000 | AK82: 5000 | AL82: 5000 | AM82: 5000 | AO82: Lake very small expensive hydroelectricity <1 MW | AP82: ProRES | AQ82: Low LR | AR82: 50 | AS82: 50 | AT82: 50 | AU82: 50 | AV82: 50 | AW82: 50 | AX82: 50 | AY82: 50
AB83: 105 | AC83: Run of River hydroelectricity | AD83: ProRES | AE83: Low LR | AF83: 3000 | AG83: 3000 | AH83: 3000 | AI83: 3000 | AJ83: 3000 | AK83: 3000 | AL83: 3000 | AM83: 3000 | AO83: Run of River hydroelectricity | AP83: ProRES | AQ83: Low LR | AR83: 15 | AS83: 15 | AT83: 15 | AU83: 15 | AV83: 15 | AW83: 15 | AX83: 15 | AY83: 15
A84: 0 | G84: 2015 | H84: 2020 | I84: 2025 | J84: 2030 | K84: 2035 | L84: 2040 | M84: 2045 | N84: 2050 | S84: 2015 | T84: 2020 | U84: 2025 | V84: 2030 | W84: 2035 | X84: 2040 | Y84: 2045 | Z84: 2050 | AB84: 120
A85: 1 | B85: Hydro_small_expensive | C85: G31 | D85: Lake very small expensive hydroelectricity <1 MW | E85: ProRES | F85: High LR | G85: 5000 | H85: 4990 | I85: 4980 | J85: 4980 | K85: 4980 | L85: 4970 | M85: 4970 | N85: 4970 | P85: Lake very small expensive hydroelectricity <1 MW | Q85: ProRES | R85: High LR | S85: 50 | T85: 49.875564 | U85: 49.822315 | V85: 49.788593 | W85: 49.76064 | X85: 49.739239 | Y85: 49.713006 | Z85: 49.682277 | AB85: 135
A86: 2 | C86: -1 | E86: Baseline | F86: High LR | G86: 5000 | H86: 5000 | I86: 4990 | J86: 4980 | K86: 4980 | L86: 4970 | M86: 4960 | N86: 4950 | Q86: Baseline | R86: High LR | S86: 50 | T86: 49.968175 | U86: 49.898708 | V86: 49.827371 | W86: 49.755217 | X86: 49.67383 | Y86: 49.602221 | Z86: 49.542348
A87: 3 | E87: Diversified portfolio | F87: High LR | G87: 5000 | H87: 5000 | I87: 4980 | J87: 4960 | K87: 4950 | L87: 4940 | M87: 4920 | N87: 4910 | Q87: Diversified portfolio | R87: High LR | S87: 50 | T87: 49.954919 | U87: 49.770885 | V87: 49.612869 | W87: 49.512898 | X87: 49.372452 | Y87: 49.248362 | Z87: 49.138329
AF88: 2015 | AG88: 2020 | AH88: 2025 | AI88: 2030 | AJ88: 2035 | AK88: 2040 | AL88: 2045 | AM88: 2050 | AR88: 2015 | AS88: 2020 | AT88: 2025 | AU88: 2030 | AV88: 2035 | AW88: 2040 | AX88: 2045 | AY88: 2050
A89: 0 | G89: 2015 | H89: 2020 | I89: 2025 | J89: 2030 | K89: 2035 | L89: 2040 | M89: 2045 | N89: 2050 | S89: 2015 | T89: 2020 | U89: 2025 | V89: 2030 | W89: 2035 | X89: 2040 | Y89: 2045 | Z89: 2050 | AB89: 16 | AC89: Lake large scale cheap hydroelectricity > 10 MW | AD89: Baseline | AE89: Low LR | AF89: 1090 | AG89: 1090 | AH89: 1090 | AI89: 1090 | AJ89: 1090 | AK89: 1090 | AL89: 1090 | AM89: 1090 | AO89: Lake large scale cheap hydroelectricity > 10 MW | AP89: Baseline | AQ89: Low LR | AR89: 5.45 | AS89: 5.45 | AT89: 5.45 | AU89: 5.45 | AV89: 5.45 | AW89: 5.45 | AX89: 5.45 | AY89: 5.45
A90: 1 | B90: Hydro_small_expensive | C90: G38 | D90: Lake very small expensive hydroelectricity <1 MW | E90: ProRES | F90: Low LR | G90: 5000 | H90: 5000 | I90: 5000 | J90: 5000 | K90: 5000 | L90: 5000 | M90: 5000 | N90: 5000 | P90: Lake very small expensive hydroelectricity <1 MW | Q90: ProRES | R90: Low LR | S90: 50 | T90: 50 | U90: 50 | V90: 50 | W90: 50 | X90: 50 | Y90: 50 | Z90: 50 | AB90: 31 | AC90: Lake large scale expensive hydroelectricity > 10 MW | AD90: Baseline | AE90: Low LR | AF90: 3500 | AG90: 3500 | AH90: 3500 | AI90: 3500 | AJ90: 3500 | AK90: 3500 | AL90: 3500 | AM90: 3500 | AO90: Lake large scale expensive hydroelectricity > 10 MW | AP90: Baseline | AQ90: Low LR | AR90: 17.5 | AS90: 17.5 | AT90: 17.5 | AU90: 17.5 | AV90: 17.5 | AW90: 17.5 | AX90: 17.5 | AY90: 17.5
A91: 2 | C91: -1 | E91: Baseline | F91: Low LR | G91: 5000 | H91: 5000 | I91: 5000 | J91: 5000 | K91: 5000 | L91: 5000 | M91: 5000 | N91: 5000 | Q91: Baseline | R91: Low LR | S91: 50 | T91: 50 | U91: 50 | V91: 50 | W91: 50 | X91: 50 | Y91: 50 | Z91: 50 | AB91: 46 | AC91: Lake medium scale cheap hydroelectricity 1-10 MW | AD91: Baseline | AE91: Low LR | AF91: 1410 | AG91: 1410 | AH91: 1410 | AI91: 1410 | AJ91: 1410 | AK91: 1410 | AL91: 1410 | AM91: 1410 | AO91: Lake medium scale cheap hydroelectricity 1-10 MW | AP91: Baseline | AQ91: Low LR | AR91: 7.05 | AS91: 7.05 | AT91: 7.05 | AU91: 7.05 | AV91: 7.05 | AW91: 7.05 | AX91: 7.05 | AY91: 7.05
A92: 3 | E92: Diversified portfolio | F92: Low LR | G92: 5000 | H92: 5000 | I92: 5000 | J92: 5000 | K92: 5000 | L92: 5000 | M92: 5000 | N92: 5000 | Q92: Diversified portfolio | R92: Low LR | S92: 50 | T92: 50 | U92: 50 | V92: 50 | W92: 50 | X92: 50 | Y92: 50 | Z92: 50 | AB92: 61 | AC92: Lake medium scale expensive hydroelectricity 1-10 MW | AD92: Baseline | AE92: Low LR | AF92: 4000 | AG92: 4000 | AH92: 4000 | AI92: 4000 | AJ92: 4000 | AK92: 4000 | AL92: 4000 | AM92: 4000 | AO92: Lake medium scale expensive hydroelectricity 1-10 MW | AP92: Baseline | AQ92: Low LR | AR92: 20 | AS92: 20 | AT92: 20 | AU92: 20 | AV92: 20 | AW92: 20 | AX92: 20 | AY92: 20
AB93: 76 | AC93: Lake very small cheap hydroelectricity <1 MW | AD93: Baseline | AE93: Low LR | AF93: 1740 | AG93: 1740 | AH93: 1740 | AI93: 1740 | AJ93: 1740 | AK93: 1740 | AL93: 1740 | AM93: 1740 | AO93: Lake very small cheap hydroelectricity <1 MW | AP93: Baseline | AQ93: Low LR | AR93: 17.4 | AS93: 17.4 | AT93: 17.4 | AU93: 17.4 | AV93: 17.4 | AW93: 17.4 | AX93: 17.4 | AY93: 17.4
A94: 0 | G94: 2015 | H94: 2020 | I94: 2025 | J94: 2030 | K94: 2035 | L94: 2040 | M94: 2045 | N94: 2050 | S94: 2015 | T94: 2020 | U94: 2025 | V94: 2030 | W94: 2035 | X94: 2040 | Y94: 2045 | Z94: 2050 | AB94: 91 | AC94: Lake very small expensive hydroelectricity <1 MW | AD94: Baseline | AE94: Low LR | AF94: 5000 | AG94: 5000 | AH94: 5000 | AI94: 5000 | AJ94: 5000 | AK94: 5000 | AL94: 5000 | AM94: 5000 | AO94: Lake very small expensive hydroelectricity <1 MW | AP94: Baseline | AQ94: Low LR | AR94: 50 | AS94: 50 | AT94: 50 | AU94: 50 | AV94: 50 | AW94: 50 | AX94: 50 | AY94: 50
A95: 1 | B95: Hydro_RoR | C95: G24 | D95: Run of River hydroelectricity | E95: ProRES | F95: Ref LR | G95: 3000 | H95: 3000 | I95: 2990 | J95: 2990 | K95: 2990 | L95: 2990 | M95: 2990 | N95: 2990 | P95: Run of River hydroelectricity | Q95: ProRES | R95: Ref LR | S95: 15 | T95: 14.981417 | U95: 14.973458 | V95: 14.968416 | W95: 14.964234 | X95: 14.961032 | Y95: 14.957106 | Z95: 14.952506 | AB95: 106 | AC95: Run of River hydroelectricity | AD95: Baseline | AE95: Low LR | AF95: 3000 | AG95: 3000 | AH95: 3000 | AI95: 3000 | AJ95: 3000 | AK95: 3000 | AL95: 3000 | AM95: 3000 | AO95: Run of River hydroelectricity | AP95: Baseline | AQ95: Low LR | AR95: 15 | AS95: 15 | AT95: 15 | AU95: 15 | AV95: 15 | AW95: 15 | AX95: 15 | AY95: 15
A96: 2 | C96: -1 | E96: Baseline | F96: Ref LR | G96: 3000 | H96: 3000 | I96: 3000 | J96: 2990 | K96: 2990 | L96: 2990 | M96: 2990 | N96: 2990 | Q96: Baseline | R96: Ref LR | S96: 15 | T96: 14.99525 | U96: 14.984875 | V96: 14.974214 | W96: 14.963423 | X96: 14.951242 | Y96: 14.940515 | Z96: 14.931541 | AB96: 121
A97: 3 | E97: Diversified portfolio | F97: Ref LR | G97: 3000 | H97: 3000 | I97: 2990 | J97: 2990 | K97: 2990 | L97: 2980 | M97: 2980 | N97: 2970 | Q97: Diversified portfolio | R97: Ref LR | S97: 15 | T97: 14.99327 | U97: 14.965767 | V97: 14.942111 | W97: 14.927125 | X97: 14.906046 | Y97: 14.887397 | Z97: 14.87084 | AB97: 136
A99: 0 | G99: 2015 | H99: 2020 | I99: 2025 | J99: 2030 | K99: 2035 | L99: 2040 | M99: 2045 | N99: 2050 | S99: 2015 | T99: 2020 | U99: 2025 | V99: 2030 | W99: 2035 | X99: 2040 | Y99: 2045 | Z99: 2050
A100: 1 | B100: Hydro_RoR | C100: G31 | D100: Run of River hydroelectricity | E100: ProRES | F100: High LR | G100: 3000 | H100: 2990 | I100: 2990 | J100: 2990 | K100: 2990 | L100: 2980 | M100: 2980 | N100: 2980 | P100: Run of River hydroelectricity | Q100: ProRES | R100: High LR | S100: 15 | T100: 14.962669 | U100: 14.946695 | V100: 14.936578 | W100: 14.928192 | X100: 14.921772 | Y100: 14.913902 | Z100: 14.904683 | AF100: 2015 | AG100: 2020 | AH100: 2025 | AI100: 2030 | AJ100: 2035 | AK100: 2040 | AL100: 2045 | AM100: 2050 | AR100: 2015 | AS100: 2020 | AT100: 2025 | AU100: 2030 | AV100: 2035 | AW100: 2040 | AX100: 2045 | AY100: 2050
A101: 2 | C101: -1 | E101: Baseline | F101: High LR | G101: 3000 | H101: 3000 | I101: 2990 | J101: 2990 | K101: 2990 | L101: 2980 | M101: 2980 | N101: 2970 | Q101: Baseline | R101: High LR | S101: 15 | T101: 14.990453 | U101: 14.969612 | V101: 14.948211 | W101: 14.926565 | X101: 14.902149 | Y101: 14.880666 | Z101: 14.862704 | AB101: 17 | AC101: Lake large scale cheap hydroelectricity > 10 MW | AD101: Diversified portfolio | AE101: Low LR | AF101: 1090 | AG101: 1090 | AH101: 1090 | AI101: 1090 | AJ101: 1090 | AK101: 1090 | AL101: 1090 | AM101: 1090 | AO101: Lake large scale cheap hydroelectricity > 10 MW | AP101: Diversified portfolio | AQ101: Low LR | AR101: 5.45 | AS101: 5.45 | AT101: 5.45 | AU101: 5.45 | AV101: 5.45 | AW101: 5.45 | AX101: 5.45 | AY101: 5.45
A102: 3 | E102: Diversified portfolio | F102: High LR | G102: 3000 | H102: 3000 | I102: 2990 | J102: 2980 | K102: 2970 | L102: 2960 | M102: 2950 | N102: 2950 | Q102: Diversified portfolio | R102: High LR | S102: 15 | T102: 14.986476 | U102: 14.931265 | V102: 14.883861 | W102: 14.853869 | X102: 14.811736 | Y102: 14.774509 | Z102: 14.741499 | AB102: 32 | AC102: Lake large scale expensive hydroelectricity > 10 MW | AD102: Diversified portfolio | AE102: Low LR | AF102: 3500 | AG102: 3500 | AH102: 3500 | AI102: 3500 | AJ102: 3500 | AK102: 3500 | AL102: 3500 | AM102: 3500 | AO102: Lake large scale expensive hydroelectricity > 10 MW | AP102: Diversified portfolio | AQ102: Low LR | AR102: 17.5 | AS102: 17.5 | AT102: 17.5 | AU102: 17.5 | AV102: 17.5 | AW102: 17.5 | AX102: 17.5 | AY102: 17.5
AB103: 47 | AC103: Lake medium scale cheap hydroelectricity 1-10 MW | AD103: Diversified portfolio | AE103: Low LR | AF103: 1410 | AG103: 1410 | AH103: 1410 | AI103: 1410 | AJ103: 1410 | AK103: 1410 | AL103: 1410 | AM103: 1410 | AO103: Lake medium scale cheap hydroelectricity 1-10 MW | AP103: Diversified portfolio | AQ103: Low LR | AR103: 7.05 | AS103: 7.05 | AT103: 7.05 | AU103: 7.05 | AV103: 7.05 | AW103: 7.05 | AX103: 7.05 | AY103: 7.05
...

Sheet Biomass
F1: CAPEX (Eur/kW) | R1: OPEX Eur/kW/Year | AB1: Summary | AE1: CAPEX (Eur/kW) | AP1: OPEX Eur/kW/Year | BC1: CAPEX (Eur/kW) | BN1: OPEX Eur/kW/Year | BY1: CAPEX (Eur/kW) | CI1: OPEX Eur/kW/Year
B2: Page Name | C2: Upper left cell | E2: 0 | F2: 1 | G2: 2 | H2: 3 | I2: 4 | J2: 5 | K2: 6 | L2: 7 | M2: 8 | N2: 9 | Q2: 18 | R2: 19 | S2: 20 | T2: 21 | U2: 22 | V2: 23 | W2: 24 | X2: 25 | Y2: 26 | Z2: 27 | AC2: 0 | AD2: 1 | AE2: 2 | AF2: 3 | AG2: 4 | AH2: 5 | AI2: 6 | AJ2: 7 | AK2: 8 | AL2: 9 | AM2: 10 | AR2: 15 | AS2: 16 | AT2: 17 | AU2: 18 | AV2: 19 | AW2: 20 | AX2: 21 | AY2: 22
BA3: MAX | BM3: MAX | BW3: MAX
A4: 0 | G4: 2015 | H4: 2020 | I4: 2025 | J4: 2030 | K4: 2035 | L4: 2040 | M4: 2045 | N4: 2050 | S4: 2015 | T4: 2020 | U4: 2025 | V4: 2030 | W4: 2035 | X4: 2040 | Y4: 2045 | Z4: 2050 | AF4: 2015 | AG4: 2020 | AH4: 2025 | AI4: 2030 | AJ4: 2035 | AK4: 2040 | AL4: 2045 | AM4: 2050 | AR4: 2015 | AS4: 2020 | AT4: 2025 | AU4: 2030 | AV4: 2035 | AW4: 2040 | AX4: 2045 | AY4: 2050 | BC4: 2015 | BD4: 2020 | BE4: 2025 | BF4: 2030 | BG4: 2035 | BH4: 2040 | BI4: 2045 | BJ4: 2050 | BN4: 2015 | BO4: 2020 | BP4: 2025 | BQ4: 2030 | BR4: 2035 | BS4: 2040 | BT4: 2045 | BU4: 2050 | BY4: 2015 | BZ4: 2020 | CA4: 2025 | CB4: 2030 | CC4: 2035 | CD4: 2040 | CE4: 2045 | CF4: 2050 | CG4: Reduction | CJ4: 2015 | CK4: 2020 | CL4: 2025 | CM4: 2030 | CN4: 2035 | CO4: 2040 | CP4: 2045 | CQ4: 2050
A5: 1 | B5: Subcritical | C5: G24 | D5: BiomassSubcirical | E5: ProRES | F5: Ref LR | G5: 3600 | H5: 3380 | I5: 3270 | J5: 3190 | K5: 3140 | L5: 3100 | M5: 3030 | N5: 2980 | P5: BiomassSubcirical | Q5: ProRES | R5: Ref LR | S5: 72 | T5: 67.680518 | U5: 65.309715 | V5: 63.785692 | W5: 62.820864 | X5: 61.939563 | Y5: 60.644861 | Z5: 59.685434 | AB5: 5 | AC5: BiomassSubcirical | AD5: ProRES | AE5: Ref LR | AF5: 3600 | AG5: 3380 | AH5: 3270 | AI5: 3190 | AJ5: 3140 | AK5: 3100 | AL5: 3030 | AM5: 2980 | AO5: BiomassSubcirical | AP5: ProRES | AQ5: Ref LR | AR5: 72 | AS5: 67.680518 | AT5: 65.309715 | AU5: 63.785692 | AV5: 62.820864 | AW5: 61.939563 | AX5: 60.644861 | AY5: 59.685434 | BA5: ProRES | BC5: 5300 | BD5: 5170 | BE5: 5100 | BF5: 5050 | BG5: 5020 | BH5: 4990 | BI5: 4950 | BJ5: 4920 | BM5: ProRES | BN5: 124 | BO5: 121.01493 | BP5: 119.32724 | BQ5: 118.22265 | BR5: 117.51506 | BS5: 116.86295 | BT5: 115.89467 | BU5: 115.16903 | BW5: BiomassSubcirical | BY5: 3600 | BZ5: 3520 | CA5: 3490 | CB5: 3480 | CC5: 3470 | CD5: 3450 | CE5: 3420 | CF5: 3400 | CG5: 0.055555556 | CI5: BiomassSubcirical | CK5: 72 | CL5: 70.395234 | CM5: 69.841764 | CN5: 69.62294 | CO5: 69.376489 | CP5: 69.018004 | CQ5: 68.382494
A6: 2 | C6: -1 | E6: Baseline | F6: Ref LR | G6: 3600 | H6: 3400 | I6: 3330 | J6: 3310 | K6: 3280 | L6: 3230 | M6: 3160 | N6: 3120 | Q6: Baseline | R6: Ref LR | S6: 72 | T6: 67.995206 | U6: 66.64609 | V6: 66.11721 | W6: 65.524614 | X6: 64.668392 | Y6: 63.167257 | Z6: 62.337865 | AB6: 20 | AC6: BiomassGasified | AD6: ProRES | AE6: Ref LR | AF6: 5300 | AG6: 4980 | AH6: 4810 | AI6: 4700 | AJ6: 4620 | AK6: 4560 | AL6: 4460 | AM6: 4390 | AO6: BiomassGasified | AP6: ProRES | AQ6: Ref LR | AR6: 106 | AS6: 99.640762 | AT6: 96.150414 | AU6: 93.906714 | AV6: 92.486272 | AW6: 91.188801 | AX6: 89.282712 | AY6: 87.870222 | BA6: Baseline | BC6: 5300 | BD6: 5180 | BE6: 5140 | BF6: 5130 | BG6: 5110 | BH6: 5080 | BI6: 5030 | BJ6: 5010 | BM6: Baseline | BN6: 124 | BO6: 121.23624 | BP6: 120.28304 | BQ6: 119.90617 | BR6: 119.48173 | BS6: 118.86434 | BT6: 117.76985 | BU6: 117.15836 | BW6: BiomassGasified | BY6: 5300 | BZ6: 5180 | CA6: 5140 | CB6: 5130 | CC6: 5110 | CD6: 5080 | CE6: 5030 | CF6: 5010 | CI6: BiomassGasified | CK6: 106 | CL6: 103.63743 | CM6: 102.8226 | CN6: 102.50044 | CO6: 102.13761 | CP6: 101.60984 | CQ6: 100.67423
A7: 3 | E7: Diversified portfolio | F7: Ref LR | G7: 3600 | H7: 3330 | I7: 3230 | J7: 3180 | K7: 3120 | L7: 3050 | M7: 2960 | N7: 2910 | Q7: Diversified portfolio | R7: Ref LR | S7: 72 | T7: 66.517987 | U7: 64.519341 | V7: 63.618051 | W7: 62.307324 | X7: 60.991755 | Y7: 59.19087 | Z7: 58.182434 | AB7: 35 | AC7: BiomassORC | AD7: ProRES | AE7: Ref LR | AF7: 4700 | AG7: 4420 | AH7: 4260 | AI7: 4160 | AJ7: 4100 | AK7: 4040 | AL7: 3960 | AM7: 3900 | AO7: BiomassORC | AP7: ProRES | AQ7: Ref LR | AR7: 94 | AS7: 88.360676 | AT7: 85.265461 | AU7: 83.275765 | AV7: 82.016128 | AW7: 80.865541 | AX7: 79.175235 | AY7: 77.92265 | BA7: Diversified portfolio | BC7: 5300 | BD7: 5140 | BE7: 5080 | BF7: 5050 | BG7: 5010 | BH7: 4960 | BI7: 4910 | BJ7: 4870 | BM7: Diversified portfolio | BN7: 124 | BO7: 120.19192 | BP7: 118.75636 | BQ7: 118.10017 | BR7: 117.13575 | BS7: 116.15533 | BT7: 114.79221 | BU7: 114.0179 | BW7: BiomassORC | BY7: 4700 | BZ7: 4600 | CA7: 4560 | CB7: 4540 | CC7: 4530 | CD7: 4510 | CE7: 4460 | CF7: 4440 | CI7: BiomassORC | CK7: 94 | CL7: 91.904889 | CM7: 91.182303 | CN7: 90.896616 | CO7: 90.574861 | CP7: 90.106838 | CQ7: 89.277146
AB8: 50 | AC8: BiomassDigest | AD8: ProRES | AE8: Ref LR | AF8: 3100 | AG8: 2910 | AH8: 2810 | AI8: 2750 | AJ8: 2700 | AK8: 2670 | AL8: 2610 | AM8: 2570 | AO8: BiomassDigest | AP8: ProRES | AQ8: Ref LR | AR8: 124 | AS8: 116.56089 | AT8: 112.47784 | AU8: 109.85314 | AV8: 108.19149 | AW8: 106.67369 | AX8: 104.44393 | AY8: 102.79158 | BW8: BiomassDigest | BY8: 3100 | BZ8: 3030 | CA8: 3010 | CB8: 3000 | CC8: 2990 | CD8: 2970 | CE8: 2940 | CF8: 2930 | CI8: BiomassDigest | CK8: 124 | CL8: 121.23624 | CM8: 120.28304 | CN8: 119.90617 | CO8: 119.48173 | CP8: 118.86434 | CQ8: 117.76985
A9: 0 | G9: 2015 | H9: 2020 | I9: 2025 | J9: 2030 | K9: 2035 | L9: 2040 | M9: 2045 | N9: 2050 | S9: 2015 | T9: 2020 | U9: 2025 | V9: 2030 | W9: 2035 | X9: 2040 | Y9: 2045 | Z9: 2050 | AB9: 65 | BW9: 0 | BY9: 2015 | BZ9: 2020 | CA9: 2025 | CB9: 2030 | CC9: 2035 | CD9: 2040 | CE9: 2045 | CF9: 2050 | CI9: 0 | CK9: 2015 | CL9: 2020 | CM9: 2025 | CN9: 2030 | CO9: 2035 | CP9: 2040 | CQ9: 2045
A10: 1 | B10: Subcritical | C10: G31 | D10: BiomassSubcirical | E10: ProRES | F10: High LR | G10: 3600 | H10: 3300 | I10: 3140 | J10: 3030 | K10: 2970 | L10: 2910 | M10: 2820 | N10: 2760 | P10: BiomassSubcirical | Q10: ProRES | R10: High LR | S10: 72 | T10: 65.965672 | U10: 62.720322 | V10: 60.659665 | W10: 59.365592 | X10: 58.19073 | Y10: 56.477319 | Z10: 55.217347 | AB10: 80 | BA10: MIN | BM10: MIN | BW10: 0 | BY10: 2015 | BZ10: 2020 | CA10: 2025 | CB10: 2030 | CC10: 2035 | CD10: 2040 | CE10: 2045 | CF10: 2050 | CI10: 0 | CK10: 2015 | CL10: 2020 | CM10: 2025 | CN10: 2030 | CO10: 2035 | CP10: 2040 | CQ10: 2045
A11: 2 | C11: -1 | E11: Baseline | F11: High LR | G11: 3600 | H11: 3320 | I11: 3230 | J11: 3190 | K11: 3150 | L11: 3090 | M11: 2990 | N11: 2940 | Q11: Baseline | R11: High LR | S11: 72 | T11: 66.400036 | U11: 64.543763 | V11: 63.820292 | W11: 63.012509 | X11: 61.850719 | Y11: 59.829248 | Z11: 58.720853 | AB11: 95 | BC11: 2015 | BD11: 2020 | BE11: 2025 | BF11: 2030 | BG11: 2035 | BH11: 2040 | BI11: 2045 | BJ11: 2050 | BN11: 2015 | BO11: 2020 | BP11: 2025 | BQ11: 2030 | BR11: 2035 | BS11: 2040 | BT11: 2045 | BU11: 2050 | BW11: 0 | BY11: 2015 | BZ11: 2020 | CA11: 2025 | CB11: 2030 | CC11: 2035 | CD11: 2040 | CE11: 2045 | CF11: 2050 | CI11: 0 | CK11: 2015 | CL11: 2020 | CM11: 2025 | CN11: 2030 | CO11: 2035 | CP11: 2040 | CQ11: 2045
A12: 3 | E12: Diversified portfolio | F12: High LR | G12: 3600 | H12: 3220 | I12: 3080 | J12: 3020 | K12: 2930 | L12: 2850 | M12: 2730 | N12: 2660 | Q12: Diversified portfolio | R12: High LR | S12: 72 | T12: 64.368306 | U12: 61.649123 | V12: 60.434229 | W12: 58.680154 | X12: 56.934925 | Y12: 54.571124 | Z12: 53.26039 | AB12: 110 | BA12: ProRES | BC12: 3100 | BD12: 2840 | BE12: 2700 | BF12: 2610 | BG12: 2560 | BH12: 2510 | BI12: 2430 | BJ12: 2380 | BM12: ProRES | BN12: 72 | BO12: 65.965672 | BP12: 62.720322 | BQ12: 60.659665 | BR12: 59.365592 | BS12: 58.19073 | BT12: 56.477319 | BU12: 55.217347
AB13: 125 | BA13: Baseline | BC13: 3100 | BD13: 2860 | BE13: 2780 | BF13: 2750 | BG13: 2710 | BH13: 2660 | BI13: 2580 | BJ13: 2530 | BM13: Baseline | BN13: 72 | BO13: 66.400036 | BP13: 64.543763 | BQ13: 63.820292 | BR13: 63.012509 | BS13: 61.850719 | BT13: 59.829248 | BU13: 58.720853
A14: 0 | G14: 2015 | H14: 2020 | I14: 2025 | J14: 2030 | K14: 2035 | L14: 2040 | M14: 2045 | N14: 2050 | S14: 2015 | T14: 2020 | U14: 2025 | V14: 2030 | W14: 2035 | X14: 2040 | Y14: 2045 | Z14: 2050 | BA14: Diversified portfolio | BC14: 3100 | BD14: 2770 | BE14: 2650 | BF14: 2600 | BG14: 2530 | BH14: 2450 | BI14: 2350 | BJ14: 2290 | BM14: Diversified portfolio | BN14: 72 | BO14: 64.368306 | BP14: 61.649123 | BQ14: 60.434229 | BR14: 58.680154 | BS14: 56.934925 | BT14: 54.571124 | BU14: 53.26039
A15: 1 | B15: Subcritical | C15: G38 | D15: BiomassSubcirical | E15: ProRES | F15: Low LR | G15: 3600 | H15: 3510 | I15: 3460 | J15: 3430 | K15: 3410 | L15: 3390 | M15: 3360 | N15: 3340 | P15: BiomassSubcirical | Q15: ProRES | R15: Low LR | S15: 72 | T15: 70.266734 | U15: 69.286783 | V15: 68.645408 | W15: 68.234552 | X15: 67.855908 | Y15: 67.293681 | Z15: 66.872338
A16: 2 | C16: -1 | E16: Baseline | F16: Low LR | G16: 3600 | H16: 3520 | I16: 3490 | J16: 3480 | K16: 3470 | L16: 3450 | M16: 3420 | N16: 3400 | Q16: Baseline | R16: Low LR | S16: 72 | T16: 70.395234 | U16: 69.841764 | V16: 69.62294 | W16: 69.376489 | X16: 69.018004 | Y16: 68.382494 | Z16: 68.027437 | AF16: 2015 | AG16: 2020 | AH16: 2025 | AI16: 2030 | AJ16: 2035 | AK16: 2040 | AL16: 2045 | AM16: 2050 | AR16: 2015 | AS16: 2020 | AT16: 2025 | AU16: 2030 | AV16: 2035 | AW16: 2040 | AX16: 2045 | AY16: 2050
A17: 3 | E17: Diversified portfolio | F17: Low LR | G17: 3600 | H17: 3490 | I17: 3450 | J17: 3430 | K17: 3400 | L17: 3370 | M17: 3330 | N17: 3310 | Q17: Diversified portfolio | R17: Low LR | S17: 72 | T17: 69.788858 | U17: 68.955305 | V17: 68.574292 | W17: 68.014308 | X17: 67.445028 | Y17: 66.653539 | Z17: 66.203943 | AB17: 6 | AC17: BiomassSubcirical | AD17: Baseline | AE17: Ref LR | AF17: 3600 | AG17: 3400 | AH17: 3330 | AI17: 3310 | AJ17: 3280 | AK17: 3230 | AL17: 3160 | AM17: 3120 | AO17: BiomassSubcirical | AP17: Baseline | AQ17: Ref LR | AR17: 72 | AS17: 67.995206 | AT17: 66.64609 | AU17: 66.11721 | AV17: 65.524614 | AW17: 64.668392 | AX17: 63.167257 | AY17: 62.337865 | BC17: 2015 | BD17: 2020 | BE17: 2025 | BF17: 2030 | BG17: 2035 | BH17: 2040 | BI17: 2045 | BJ17: 2050 | BN17: 2015 | BO17: 2020 | BP17: 2025 | BQ17: 2030 | BR17: 2035 | BS17: 2040 | BT17: 2045 | BU17: 2050 | BW17: MIN
AB18: 21 | AC18: BiomassGasified | AD18: Baseline | AE18: Ref LR | AF18: 5300 | AG18: 5010 | AH18: 4910 | AI18: 4870 | AJ18: 4820 | AK18: 4760 | AL18: 4650 | AM18: 4590 | AO18: BiomassGasified | AP18: Baseline | AQ18: Ref LR | AR18: 106 | AS18: 100.10405 | AT18: 98.117855 | AU18: 97.339226 | AV18: 96.466792 | AW18: 95.206244 | AX18: 92.996239 | AY18: 91.77519 | BB18: Max | BC18: 5300 | BD18: 5180 | BE18: 5140 | BF18: 5130 | BG18: 5110 | BH18: 5080 | BI18: 5030 | BJ18: 5010 | BM18: Max | BN18: 124 | BO18: 121.23624 | BP18: 120.28304 | BQ18: 119.90617 | BR18: 119.48173 | BS18: 118.86434 | BT18: 117.76985 | BU18: 117.15836 | BY18: 2015 | BZ18: 2020 | CA18: 2025 | CB18: 2030 | CC18: 2035 | CD18: 2040 | CE18: 2045 | CF18: 2050 | CG18: Reduction | CJ18: 2015 | CK18: 2020 | CL18: 2025 | CM18: 2030 | CN18: 2035 | CO18: 2040 | CP18: 2045 | CQ18: 2050
A19: 0 | G19: 2015 | H19: 2020 | I19: 2025 | J19: 2030 | K19: 2035 | L19: 2040 | M19: 2045 | N19: 2050 | S19: 2015 | T19: 2020 | U19: 2025 | V19: 2030 | W19: 2035 | X19: 2040 | Y19: 2045 | Z19: 2050 | AB19: 36 | AC19: BiomassORC | AD19: Baseline | AE19: Ref LR | AF19: 4700 | AG19: 4440 | AH19: 4350 | AI19: 4320 | AJ19: 4280 | AK19: 4220 | AL19: 4120 | AM19: 4070 | AO19: BiomassORC | AP19: Baseline | AQ19: Ref LR | AR19: 94 | AS19: 88.771519 | AT19: 87.010173 | AU19: 86.319691 | AV19: 85.546024 | AW19: 84.428178 | AX19: 82.468363 | AY19: 81.385546 | BB19: Min | BC19: 3100 | BD19: 2770 | BE19: 2650 | BF19: 2600 | BG19: 2530 | BH19: 2450 | BI19: 2350 | BJ19: 2290 | BM19: Min | BN19: 72 | BO19: 64.368306 | BP19: 61.649123 | BQ19: 60.434229 | BR19: 58.680154 | BS19: 56.934925 | BT19: 54.571124 | BU19: 53.26039 | BW19: BiomassSubcirical | BY19: 3600 | BZ19: 3220 | CA19: 3080 | CB19: 3020 | CC19: 2930 | CD19: 2850 | CE19: 2730 | CF19: 2660 | CG19: 0.26111111 | CI19: BiomassSubcirical | CK19: 72 | CL19: 64.368306 | CM19: 61.649123 | CN19: 60.434229 | CO19: 58.680154 | CP19: 56.934925 | CQ19: 54.571124
A20: 1 | B20: Gasified | C20: G24 | D20: BiomassGasified | E20: ProRES | F20: Ref LR | G20: 5300 | H20: 4980 | I20: 4810 | J20: 4700 | K20: 4620 | L20: 4560 | M20: 4460 | N20: 4390 | P20: BiomassGasified | Q20: ProRES | R20: Ref LR | S20: 106 | T20: 99.640762 | U20: 96.150414 | V20: 93.906714 | W20: 92.486272 | X20: 91.188801 | Y20: 89.282712 | Z20: 87.870222 | AB20: 51 | AC20: BiomassDigest | AD20: Baseline | AE20: Ref LR | AF20: 3100 | AG20: 2930 | AH20: 2870 | AI20: 2850 | AJ20: 2820 | AK20: 2780 | AL20: 2720 | AM20: 2680 | AO20: BiomassDigest | AP20: Baseline | AQ20: Ref LR | AR20: 124 | AS20: 117.10285 | AT20: 114.77938 | AU20: 113.86853 | AV20: 112.84795 | AW20: 111.37334 | AX20: 108.78805 | AY20: 107.35966 | BW20: BiomassGasified | BY20: 5300 | BZ20: 4740 | CA20: 4540 | CB20: 4450 | CC20: 4320 | CD20: 4190 | CE20: 4020 | CF20: 3920 | CI20: BiomassGasified | CK20: 106 | CL20: 94.764451 | CM20: 90.76121 | CN20: 88.972615 | CO20: 86.390227 | CP20: 83.820862 | CQ20: 80.340822
A21: 2 | C21: -1 | E21: Baseline | F21: Ref LR | G21: 5300 | H21: 5010 | I21: 4910 | J21: 4870 | K21: 4820 | L21: 4760 | M21: 4650 | N21: 4590 | Q21: Baseline | R21: Ref LR | S21: 106 | T21: 100.10405 | U21: 98.117855 | V21: 97.339226 | W21: 96.466792 | X21: 95.206244 | Y21: 92.996239 | Z21: 91.77519 | AB21: 66 | BW21: BiomassORC | BY21: 4700 | BZ21: 4200 | CA21: 4020 | CB21: 3950 | CC21: 3830 | CD21: 3720 | CE21: 3560 | CF21: 3480 | CI21: BiomassORC | CK21: 94 | CL21: 84.0364 | CM21: 80.486356 | CN21: 78.900244 | CO21: 76.610202 | CP21: 74.331707 | CQ21: 71.245634
A22: 3 | E22: Diversified portfolio | F22: Ref LR | G22: 5300 | H22: 4900 | I22: 4750 | J22: 4680 | K22: 4590 | L22: 4490 | M22: 4360 | N22: 4280 | Q22: Diversified portfolio | R22: Ref LR | S22: 106 | T22: 97.929258 | U22: 94.986807 | V22: 93.659908 | W22: 91.730227 | X22: 89.793417 | Y22: 87.142114 | Z22: 85.657472 | AB22: 81 | BW22: BiomassDigest | BY22: 3100 | BZ22: 2770 | CA22: 2650 | CB22: 2600 | CC22: 2530 | CD22: 2450 | CE22: 2350 | CF22: 2290 | CI22: BiomassDigest | CK22: 124 | CL22: 110.85653 | CM22: 106.17349 | CN22: 104.08117 | CO22: 101.06027 | CP22: 98.054593 | CQ22: 93.983603
AB23: 96 | BW23: 0 | BY23: 0 | BZ23: 0 | CA23: 0 | CB23: 0 | CC23: 0 | CD23: 0 | CE23: 0 | CF23: 0 | CI23: 0 | CK23: 0 | CL23: 0 | CM23: 0 | CN23: 0 | CO23: 0 | CP23: 0 | CQ23: 0
A24: 0 | G24: 2015 | H24: 2020 | I24: 2025 | J24: 2030 | K24: 2035 | L24: 2040 | M24: 2045 | N24: 2050 | S24: 2015 | T24: 2020 | U24: 2025 | V24: 2030 | W24: 2035 | X24: 2040 | Y24: 2045 | Z24: 2050 | AB24: 111 | BW24: 0 | BY24: 0 | BZ24: 0 | CA24: 0 | CB24: 0 | CC24: 0 | CD24: 0 | CE24: 0 | CF24: 0 | CI24: 0 | CK24: 0 | CL24: 0 | CM24: 0 | CN24: 0 | CO24: 0 | CP24: 0 | CQ24: 0
A25: 1 | B25: Gasified | C25: G31 | D25: BiomassGasified | E25: ProRES | F25: High LR | G25: 5300 | H25: 4860 | I25: 4620 | J25: 4470 | K25: 4370 | L25: 4280 | M25: 4160 | N25: 4060 | P25: BiomassGasified | Q25: ProRES | R25: High LR | S25: 106 | T25: 97.116128 | U25: 92.338252 | V25: 89.304506 | W25: 87.399343 | X25: 85.669685 | Y25: 83.147165 | Z25: 81.292206 | AB25: 126 | BW25: 0 | BY25: 0 | BZ25: 0 | CA25: 0 | CB25: 0 | CC25: 0 | CD25: 0 | CE25: 0 | CF25: 0 | CI25: 0 | CK25: 0 | CL25: 0 | CM25: 0 | CN25: 0 | CO25: 0 | CP25: 0 | CQ25: 0
A26: 2 | C26: -1 | E26: Baseline | F26: High LR | G26: 5300 | H26: 4890 | I26: 4750 | J26: 4700 | K26: 4640 | L26: 4550 | M26: 4400 | N26: 4320 | Q26: Baseline | R26: High LR | S26: 106 | T26: 97.755608 | U26: 95.022762 | V26: 93.957652 | W26: 92.768416 | X26: 91.058004 | Y26: 88.081948 | Z26: 86.450145
A27: 3 | E27: Diversified portfolio | F27: High LR | G27: 5300 | H27: 4740 | I27: 4540 | J27: 4450 | K27: 4320 | L27: 4190 | M27: 4020 | N27: 3920 | Q27: Diversified portfolio | R27: High LR | S27: 106 | T27: 94.764451 | U27: 90.76121 | V27: 88.972615 | W27: 86.390227 | X27: 83.820862 | Y27: 80.340822 | Z27: 78.41113
AF28: 2015 | AG28: 2020 | AH28: 2025 | AI28: 2030 | AJ28: 2035 | AK28: 2040 | AL28: 2045 | AM28: 2050 | AR28: 2015 | AS28: 2020 | AT28: 2025 | AU28: 2030 | AV28: 2035 | AW28: 2040 | AX28: 2045 | AY28: 2050
A29: 0 | G29: 2015 | H29: 2020 | I29: 2025 | J29: 2030 | K29: 2035 | L29: 2040 | M29: 2045 | N29: 2050 | S29: 2015 | T29: 2020 | U29: 2025 | V29: 2030 | W29: 2035 | X29: 2040 | Y29: 2045 | Z29: 2050 | AB29: 7 | AC29: BiomassSubcirical | AD29: Diversified portfolio | AE29: Ref LR | AF29: 3600 | AG29: 3330 | AH29: 3230 | AI29: 3180 | AJ29: 3120 | AK29: 3050 | AL29: 2960 | AM29: 2910 | AO29: BiomassSubcirical | AP29: Diversified portfolio | AQ29: Ref LR | AR29: 72 | AS29: 66.517987 | AT29: 64.519341 | AU29: 63.618051 | AV29: 62.307324 | AW29: 60.991755 | AX29: 59.19087 | AY29: 58.182434
A30: 1 | B30: Gasified | C30: G38 | D30: BiomassGasified | E30: ProRES | F30: Low LR | G30: 5300 | H30: 5170 | I30: 5100 | J30: 5050 | K30: 5020 | L30: 4990 | M30: 4950 | N30: 4920 | P30: BiomassGasified | Q30: ProRES | R30: Low LR | S30: 106 | T30: 103.44825 | U30: 102.00554 | V30: 101.06129 | W30: 100.45642 | X30: 99.898976 | Y30: 99.071253 | Z30: 98.450942 | AB30: 22 | AC30: BiomassGasified | AD30: Diversified portfolio | AE30: Ref LR | AF30: 5300 | AG30: 4900 | AH30: 4750 | AI30: 4680 | AJ30: 4590 | AK30: 4490 | AL30: 4360 | AM30: 4280 | AO30: BiomassGasified | AP30: Diversified portfolio | AQ30: Ref LR | AR30: 106 | AS30: 97.929258 | AT30: 94.986807 | AU30: 93.659908 | AV30: 91.730227 | AW30: 89.793417 | AX30: 87.142114 | AY30: 85.657472
A31: 2 | C31: -1 | E31: Baseline | F31: Low LR | G31: 5300 | H31: 5180 | I31: 5140 | J31: 5130 | K31: 5110 | L31: 5080 | M31: 5030 | N31: 5010 | Q31: Baseline | R31: Low LR | S31: 106 | T31: 103.63743 | U31: 102.8226 | V31: 102.50044 | W31: 102.13761 | X31: 101.60984 | Y31: 100.67423 | Z31: 100.1515 | AB31: 37 | AC31: BiomassORC | AD31: Diversified portfolio | AE31: Ref LR | AF31: 4700 | AG31: 4340 | AH31: 4210 | AI31: 4150 | AJ31: 4070 | AK31: 3980 | AL31: 3860 | AM31: 3800 | AO31: BiomassORC | AP31: Diversified portfolio | AQ31: Ref LR | AR31: 94 | AS31: 86.842927 | AT31: 84.233583 | AU31: 83.0569 | AV31: 81.345673 | AW31: 79.628124 | AX31: 77.276969 | AY31: 75.9604
A32: 3 | E32: Diversified portfolio | F32: Low LR | G32: 5300 | H32: 5140 | I32: 5080 | J32: 5050 | K32: 5010 | L32: 4960 | M32: 4910 | N32: 4870 | Q32: Diversified portfolio | R32: Low LR | S32: 106 | T32: 102.74471 | U32: 101.51753 | V32: 100.9566 | W32: 100.13218 | X32: 99.29407 | Y32: 98.128822 | Z32: 97.466916 | AB32: 52 | AC32: BiomassDigest | AD32: Diversified portfolio | AE32: Ref LR | AF32: 3100 | AG32: 2860 | AH32: 2780 | AI32: 2740 | AJ32: 2680 | AK32: 2630 | AL32: 2550 | AM32: 2510 | AO32: BiomassDigest | AP32: Diversified portfolio | AQ32: Ref LR | AR32: 124 | AS32: 114.55875 | AT32: 111.11664 | AU32: 109.56442 | AV32: 107.30706 | AW32: 105.04136 | AX32: 101.93983 | AY32: 100.20308
AB33: 67
A34: 0 | G34: 2015 | H34: 2020 | I34: 2025 | J34: 2030 | K34: 2035 | L34: 2040 | M34: 2045 | N34: 2050 | S34: 2015 | T34: 2020 | U34: 2025 | V34: 2030 | W34: 2035 | X34: 2040 | Y34: 2045 | Z34: 2050 | AB34: 82
A35: 1 | B35: ORC | C35: G24 | D35: BiomassORC | E35: ProRES | F35: Ref LR | G35: 4700 | H35: 4420 | I35: 4260 | J35: 4160 | K35: 4100 | L35: 4040 | M35: 3960 | N35: 3900 | P35: BiomassORC | Q35: ProRES | R35: Ref LR | S35: 94 | T35: 88.360676 | U35: 85.265461 | V35: 83.275765 | W35: 82.016128 | X35: 80.865541 | Y35: 79.175235 | Z35: 77.92265 | AB35: 97
A36: 2 | C36: -1 | E36: Baseline | F36: Ref LR | G36: 4700 | H36: 4440 | I36: 4350 | J36: 4320 | K36: 4280 | L36: 4220 | M36: 4120 | N36: 4070 | Q36: Baseline | R36: Ref LR | S36: 94 | T36: 88.771519 | U36: 87.010173 | V36: 86.319691 | W36: 85.546024 | X36: 84.428178 | Y36: 82.468363 | Z36: 81.385546 | AB36: 112
A37: 3 | E37: Diversified portfolio | F37: Ref LR | G37: 4700 | H37: 4340 | I37: 4210 | J37: 4150 | K37: 4070 | L37: 3980 | M37: 3860 | N37: 3800 | Q37: Diversified portfolio | R37: Ref LR | S37: 94 | T37: 86.842927 | U37: 84.233583 | V37: 83.0569 | W37: 81.345673 | X37: 79.628124 | Y37: 77.276969 | Z37: 75.9604 | AB37: 127
A39: 0 | G39: 2015 | H39: 2020 | I39: 2025 | J39: 2030 | K39: 2035 | L39: 2040 | M39: 2045 | N39: 2050 | S39: 2015 | T39: 2020 | U39: 2025 | V39: 2030 | W39: 2035 | X39: 2040 | Y39: 2045 | Z39: 2050
A40: 1 | B40: ORC | C40: G31 | D40: BiomassORC | E40: ProRES | F40: High LR | G40: 4700 | H40: 4310 | I40: 4090 | J40: 3960 | K40: 3880 | L40: 3800 | M40: 3690 | N40: 3600 | P40: BiomassORC | Q40: ProRES | R40: High LR | S40: 94 | T40: 86.12185 | U40: 81.884865 | V40: 79.194562 | W40: 77.505078 | X40: 75.97123 | Y40: 73.734278 | Z40: 72.089315 | AF40: 2015 | AG40: 2020 | AH40: 2025 | AI40: 2030 | AJ40: 2035 | AK40: 2040 | AL40: 2045 | AM40: 2050 | AR40: 2015 | AS40: 2020 | AT40: 2025 | AU40: 2030 | AV40: 2035 | AW40: 2040 | AX40: 2045 | AY40: 2050
A41: 2 | C41: -1 | E41: Baseline | F41: High LR | G41: 4700 | H41: 4330 | I41: 4210 | J41: 4170 | K41: 4110 | L41: 4040 | M41: 3910 | N41: 3830 | Q41: Baseline | R41: High LR | S41: 94 | T41: 86.688936 | U41: 84.265468 | V41: 83.320937 | W41: 82.266331 | X41: 80.74955 | Y41: 78.110407 | Z41: 76.663336 | AB41: 10 | AC41: BiomassSubcirical | AD41: ProRES | AE41: High LR | AF41: 3600 | AG41: 3300 | AH41: 3140 | AI41: 3030 | AJ41: 2970 | AK41: 2910 | AL41: 2820 | AM41: 2760 | AO41: BiomassSubcirical | AP41: ProRES | AQ41: High LR | AR41: 72 | AS41: 65.965672 | AT41: 62.720322 | AU41: 60.659665 | AV41: 59.365592 | AW41: 58.19073 | AX41: 56.477319 | AY41: 55.217347
A42: 3 | E42: Diversified portfolio | F42: High LR | G42: 4700 | H42: 4200 | I42: 4020 | J42: 3950 | K42: 3830 | L42: 3720 | M42: 3560 | N42: 3480 | Q42: Diversified portfolio | R42: High LR | S42: 94 | T42: 84.0364 | U42: 80.486356 | V42: 78.900244 | W42: 76.610202 | X42: 74.331707 | Y42: 71.245634 | Z42: 69.534398 | AB42: 25 | AC42: BiomassGasified | AD42: ProRES | AE42: High LR | AF42: 5300 | AG42: 4860 | AH42: 4620 | AI42: 4470 | AJ42: 4370 | AK42: 4280 | AL42: 4160 | AM42: 4060 | AO42: BiomassGasified | AP42: ProRES | AQ42: High LR | AR42: 106 | AS42: 97.116128 | AT42: 92.338252 | AU42: 89.304506 | AV42: 87.399343 | AW42: 85.669685 | AX42: 83.147165 | AY42: 81.292206
AB43: 40 | AC43: BiomassORC | AD43: ProRES | AE43: High LR | AF43: 4700 | AG43: 4310 | AH43: 4090 | AI43: 3960 | AJ43: 3880 | AK43: 3800 | AL43: 3690 | AM43: 3600 | AO43: BiomassORC | AP43: ProRES | AQ43: High LR | AR43: 94 | AS43: 86.12185 | AT43: 81.884865 | AU43: 79.194562 | AV43: 77.505078 | AW43: 75.97123 | AX43: 73.734278 | AY43: 72.089315
A44: 0 | G44: 2015 | H44: 2020 | I44: 2025 | J44: 2030 | K44: 2035 | L44: 2040 | M44: 2045 | N44: 2050 | S44: 2015 | T44: 2020 | U44: 2025 | V44: 2030 | W44: 2035 | X44: 2040 | Y44: 2045 | Z44: 2050 | AB44: 55 | AC44: BiomassDigest | AD44: ProRES | AE44: High LR | AF44: 3100 | AG44: 2840 | AH44: 2700 | AI44: 2610 | AJ44: 2560 | AK44: 2510 | AL44: 2430 | AM44: 2380 | AO44: BiomassDigest | AP44: ProRES | AQ44: High LR | AR44: 124 | AS44: 113.60755 | AT44: 108.01833 | AU44: 104.46942 | AV44: 102.24074 | AW44: 100.21737 | AX44: 97.266494 | AY44: 95.096543
A45: 1 | B45: ORC | C45: G38 | D45: BiomassORC | E45: ProRES | F45: Low LR | G45: 4700 | H45: 4590 | I45: 4520 | J45: 4480 | K45: 4450 | L45: 4430 | M45: 4390 | N45: 4370 | P45: BiomassORC | Q45: ProRES | R45: Low LR | S45: 94 | T45: 91.737125 | U45: 90.457745 | V45: 89.620394 | W45: 89.083998 | X45: 88.589658 | Y45: 87.855639 | Z45: 87.305552 | AB45: 70
A46: 2 | C46: -1 | E46: Baseline | F46: Low LR | G46: 4700 | H46: 4600 | I46: 4560 | J46: 4540 | K46: 4530 | L46: 4510 | M46: 4460 | N46: 4440 | Q46: Baseline | R46: Low LR | S46: 94 | T46: 91.904889 | U46: 91.182303 | V46: 90.896616 | W46: 90.574861 | X46: 90.106838 | Y46: 89.277146 | Z46: 88.813598 | AB46: 85
A47: 3 | E47: Diversified portfolio | F47: Low LR | G47: 4700 | H47: 4560 | I47: 4500 | J47: 4480 | K47: 4440 | L47: 4400 | M47: 4350 | N47: 4320 | Q47: Diversified portfolio | R47: Low LR | S47: 94 | T47: 91.113231 | U47: 90.024982 | V47: 89.527548 | W47: 88.796458 | X47: 88.053231 | Y47: 87.019899 | Z47: 86.432925 | AB47: 100
AB48: 115
A49: 0 | G49: 2015 | H49: 2020 | I49: 2025 | J49: 2030 | K49: 2035 | L49: 2040 | M49: 2045 | N49: 2050 | S49: 2015 | T49: 2020 | U49: 2025 | V49: 2030 | W49: 2035 | X49: 2040 | Y49: 2045 | Z49: 2050 | AB49: 130
A50: 1 | B50: Anaerobic | C50: G24 | D50: BiomassDigest | E50: ProRES | F50: Ref LR | G50: 3100 | H50: 2910 | I50: 2810 | J50: 2750 | K50: 2700 | L50: 2670 | M50: 2610 | N50: 2570 | P50: BiomassDigest | Q50: ProRES | R50: Ref LR | S50: 124 | T50: 116.56089 | U50: 112.47784 | V50: 109.85314 | W50: 108.19149 | X50: 106.67369 | Y50: 104.44393 | Z50: 102.79158
A51: 2 | C51: -1 | E51: Baseline | F51: Ref LR | G51: 3100 | H51: 2930 | I51: 2870 | J51: 2850 | K51: 2820 | L51: 2780 | M51: 2720 | N51: 2680 | Q51: Baseline | R51: Ref LR | S51: 124 | T51: 117.10285 | U51: 114.77938 | V51: 113.86853 | W51: 112.84795 | X51: 111.37334 | Y51: 108.78805 | Z51: 107.35966
A52: 3 | E52: Diversified portfolio | F52: Ref LR | G52: 3100 | H52: 2860 | I52: 2780 | J52: 2740 | K52: 2680 | L52: 2630 | M52: 2550 | N52: 2510 | Q52: Diversified portfolio | R52: Ref LR | S52: 124 | T52: 114.55875 | U52: 111.11664 | V52: 109.56442 | W52: 107.30706 | X52: 105.04136 | Y52: 101.93983 | Z52: 100.20308 | AF52: 2015 | AG52: 2020 | AH52: 2025 | AI52: 2030 | AJ52: 2035 | AK52: 2040 | AL52: 2045 | AM52: 2050 | AR52: 2015 | AS52: 2020 | AT52: 2025 | AU52: 2030 | AV52: 2035 | AW52: 2040 | AX52: 2045 | AY52: 2050
AB53: 11 | AC53: BiomassSubcirical | AD53: Baseline | AE53: High LR | AF53: 3600 | AG53: 3320 | AH53: 3230 | AI53: 3190 | AJ53: 3150 | AK53: 3090 | AL53: 2990 | AM53: 2940 | AO53: BiomassSubcirical | AP53: Baseline | AQ53: High LR | AR53: 72 | AS53: 66.400036 | AT53: 64.543763 | AU53: 63.820292 | AV53: 63.012509 | AW53: 61.850719 | AX53: 59.829248 | AY53: 58.720853
A54: 0 | G54: 2015 | H54: 2020 | I54: 2025 | J54: 2030 | K54: 2035 | L54: 2040 | M54: 2045 | N54: 2050 | S54: 2015 | T54: 2020 | U54: 2025 | V54: 2030 | W54: 2035 | X54: 2040 | Y54: 2045 | Z54: 2050 | AB54: 26 | AC54: BiomassGasified | AD54: Baseline | AE54: High LR | AF54: 5300 | AG54: 4890 | AH54: 4750 | AI54: 4700 | AJ54: 4640 | AK54: 4550 | AL54: 4400 | AM54: 4320 | AO54: BiomassGasified | AP54: Baseline | AQ54: High LR | AR54: 106 | AS54: 97.755608 | AT54: 95.022762 | AU54: 93.957652 | AV54: 92.768416 | AW54: 91.058004 | AX54: 88.081948 | AY54: 86.450145
A55: 1 | B55: Anaerobic | C55: G31 | D55: BiomassDigest | E55: ProRES | F55: High LR | G55: 3100 | H55: 2840 | I55: 2700 | J55: 2610 | K55: 2560 | L55: 2510 | M55: 2430 | N55: 2380 | P55: BiomassDigest | Q55: ProRES | R55: High LR | S55: 124 | T55: 113.60755 | U55: 108.01833 | V55: 104.46942 | W55: 102.24074 | X55: 100.21737 | Y55: 97.266494 | Z55: 95.096543 | AB55: 41 | AC55: BiomassORC | AD55: Baseline | AE55: High LR | AF55: 4700 | AG55: 4330 | AH55: 4210 | AI55: 4170 | AJ55: 4110 | AK55: 4040 | AL55: 3910 | AM55: 3830 | AO55: BiomassORC | AP55: Baseline | AQ55: High LR | AR55: 94 | AS55: 86.688936 | AT55: 84.265468 | AU55: 83.320937 | AV55: 82.266331 | AW55: 80.74955 | AX55: 78.110407 | AY55: 76.663336
A56: 2 | C56: -1 | E56: Baseline | F56: High LR | G56: 3100 | H56: 2860 | I56: 2780 | J56: 2750 | K56: 2710 | L56: 2660 | M56: 2580 | N56: 2530 | Q56: Baseline | R56: High LR | S56: 124 | T56: 114.35562 | U56: 111.1587 | V56: 109.91272 | W56: 108.52154 | X56: 106.52068 | Y56: 103.03926 | Z56: 101.13036 | AB56: 56 | AC56: BiomassDigest | AD56: Baseline | AE56: High LR | AF56: 3100 | AG56: 2860 | AH56: 2780 | AI56: 2750 | AJ56: 2710 | AK56: 2660 | AL56: 2580 | AM56: 2530 | AO56: BiomassDigest | AP56: Baseline | AQ56: High LR | AR56: 124 | AS56: 114.35562 | AT56: 111.1587 | AU56: 109.91272 | AV56: 108.52154 | AW56: 106.52068 | AX56: 103.03926 | AY56: 101.13036
A57: 3 | E57: Diversified portfolio | F57: High LR | G57: 3100 | H57: 2770 | I57: 2650 | J57: 2600 | K57: 2530 | L57: 2450 | M57: 2350 | N57: 2290 | Q57: Diversified portfolio | R57: High LR | S57: 124 | T57: 110.85653 | U57: 106.17349 | V57: 104.08117 | W57: 101.06027 | X57: 98.054593 | Y57: 93.983603 | Z57: 91.726227 | AB57: 71
AB58: 86
A59: 0 | G59: 2015 | H59: 2020 | I59: 2025 | J59: 2030 | K59: 2035 | L59: 2040 | M59: 2045 | N59: 2050 | S59: 2015 | T59: 2020 | U59: 2025 | V59: 2030 | W59: 2035 | X59: 2040 | Y59: 2045 | Z59: 2050 | AB59: 101
A60: 1 | B60: Anaerobic | C60: G38 | D60: BiomassDigest | E60: ProRES | F60: Low LR | G60: 3100 | H60: 3030 | I60: 2980 | J60: 2960 | K60: 2940 | L60: 2920 | M60: 2900 | N60: 2880 | P60: BiomassDigest | Q60: ProRES | R60: Low LR | S60: 124 | T60: 121.01493 | U60: 119.32724 | V60: 118.22265 | W60: 117.51506 | X60: 116.86295 | Y60: 115.89467 | Z60: 115.16903 | AB60: 116
A61: 2 | C61: -1 | E61: Baseline | F61: Low LR | G61: 3100 | H61: 3030 | I61: 3010 | J61: 3000 | K61: 2990 | L61: 2970 | M61: 2940 | N61: 2930 | Q61: Baseline | R61: Low LR | S61: 124 | T61: 121.23624 | U61: 120.28304 | V61: 119.90617 | W61: 119.48173 | X61: 118.86434 | Y61: 117.76985 | Z61: 117.15836 | AB61: 131
A62: 3 | E62: Diversified portfolio | F62: Low LR | G62: 3100 | H62: 3000 | I62: 2970 | J62: 2950 | K62: 2930 | L62: 2900 | M62: 2870 | N62: 2850 | Q62: Diversified portfolio | R62: Low LR | S62: 124 | T62: 120.19192 | U62: 118.75636 | V62: 118.10017 | W62: 117.13575 | X62: 116.15533 | Y62: 114.79221 | Z62: 114.0179
AF64: 2015 | AG64: 2020 | AH64: 2025 | AI64: 2030 | AJ64: 2035 | AK64: 2040 | AL64: 2045 | AM64: 2050 | AR64: 2015 | AS64: 2020 | AT64: 2025 | AU64: 2030 | AV64: 2035 | AW64: 2040 | AX64: 2045 | AY64: 2050
AB65: 12 | AC65: BiomassSubcirical | AD65: Diversified portfolio | AE65: High LR | AF65: 3600 | AG65: 3220 | AH65: 3080 | AI65: 3020 | AJ65: 2930 | AK65: 2850 | AL65: 2730 | AM65: 2660 | AO65: BiomassSubcirical | AP65: Diversified portfolio | AQ65: High LR | AR65: 72 | AS65: 64.368306 | AT65: 61.649123 | AU65: 60.434229 | AV65: 58.680154 | AW65: 56.934925 | AX65: 54.571124 | AY65: 53.26039
AB66: 27 | AC66: BiomassGasified | AD66: Diversified portfolio | AE66: High LR | AF66: 5300 | AG66: 4740 | AH66: 4540 | AI66: 4450 | AJ66: 4320 | AK66: 4190 | AL66: 4020 | AM66: 3920 | AO66: BiomassGasified | AP66: Diversified portfolio | AQ66: High LR | AR66: 106 | AS66: 94.764451 | AT66: 90.76121 | AU66: 88.972615 | AV66: 86.390227 | AW66: 83.820862 | AX66: 80.340822 | AY66: 78.41113
AB67: 42 | AC67: BiomassORC | AD67: Diversified portfolio | AE67: High LR | AF67: 4700 | AG67: 4200 | AH67: 4020 | AI67: 3950 | AJ67: 3830 | AK67: 3720 | AL67: 3560 | AM67: 3480 | AO67: BiomassORC | AP67: Diversified portfolio | AQ67: High LR | AR67: 94 | AS67: 84.0364 | AT67: 80.486356 | AU67: 78.900244 | AV67: 76.610202 | AW67: 74.331707 | AX67: 71.245634 | AY67: 69.534398
AB68: 57 | AC68: BiomassDigest | AD68: Diversified portfolio | AE68: High LR | AF68: 3100 | AG68: 2770 | AH68: 2650 | AI68: 2600 | AJ68: 2530 | AK68: 2450 | AL68: 2350 | AM68: 2290 | AO68: BiomassDigest | AP68: Diversified portfolio | AQ68: High LR | AR68: 124 | AS68: 110.85653 | AT68: 106.17349 | AU68: 104.08117 | AV68: 101.06027 | AW68: 98.054593 | AX68: 93.983603 | AY68: 91.726227
AB69: 72
AB70: 87
AB71: 102
AB72: 117
AB73: 132
AF76: 2015 | AG76: 2020 | AH76: 2025 | AI76: 2030 | AJ76: 2035 | AK76: 2040 | AL76: 2045 | AM76: 2050 | AR76: 2015 | AS76: 2020 | AT76: 2025 | AU76: 2030 | AV76: 2035 | AW76: 2040 | AX76: 2045 | AY76: 2050
AB77: 15 | AC77: BiomassSubcirical | AD77: ProRES | AE77: Low LR | AF77: 3600 | AG77: 3510 | AH77: 3460 | AI77: 3430 | AJ77: 3410 | AK77: 3390 | AL77: 3360 | AM77: 3340 | AO77: BiomassSubcirical | AP77: ProRES | AQ77: Low LR | AR77: 72 | AS77: 70.266734 | AT77: 69.286783 | AU77: 68.645408 | AV77: 68.234552 | AW77: 67.855908 | AX77: 67.293681 | AY77: 66.872338
AB78: 30 | AC78: BiomassGasified | AD78: ProRES | AE78: Low LR | AF78: 5300 | AG78: 5170 | AH78: 5100 | AI78: 5050 | AJ78: 5020 | AK78: 4990 | AL78: 4950 | AM78: 4920 | AO78: BiomassGasified | AP78: ProRES | AQ78: Low LR | AR78: 106 | AS78: 103.44825 | AT78: 102.00554 | AU78: 101.06129 | AV78: 100.45642 | AW78: 99.898976 | AX78: 99.071253 | AY78: 98.450942
AB79: 45 | AC79: BiomassORC | AD79: ProRES | AE79: Low LR | AF79: 4700 | AG79: 4590 | AH79: 4520 | AI79: 4480 | AJ79: 4450 | AK79: 4430 | AL79: 4390 | AM79: 4370 | AO79: BiomassORC | AP79: ProRES | AQ79: Low LR | AR79: 94 | AS79: 91.737125 | AT79: 90.457745 | AU79: 89.620394 | AV79: 89.083998 | AW79: 88.589658 | AX79: 87.855639 | AY79: 87.305552
AB80: 60 | AC80: BiomassDigest | AD80: ProRES | AE80: Low LR | AF80: 3100 | AG80: 3030 | AH80: 2980 | AI80: 2960 | AJ80: 2940 | AK80: 2920 | AL80: 2900 | AM80: 2880 | AO80: BiomassDigest | AP80: ProRES | AQ80: Low LR | AR80: 124 | AS80: 121.01493 | AT80: 119.32724 | AU80: 118.22265 | AV80: 117.51506 | AW80: 116.86295 | AX80: 115.89467 | AY80: 115.16903
AB81: 75
AB82: 90
AB83: 105
AB84: 120
AB85: 135
AF88: 2015 | AG88: 2020 | AH88: 2025 | AI88: 2030 | AJ88: 2035 | AK88: 2040 | AL88: 2045 | AM88: 2050 | AR88: 2015 | AS88: 2020 | AT88: 2025 | AU88: 2030 | AV88: 2035 | AW88: 2040 | AX88: 2045 | AY88: 2050
AB89: 16 | AC89: BiomassSubcirical | AD89: Baseline | AE89: Low LR | AF89: 3600 | AG89: 3520 | AH89: 3490 | AI89: 3480 | AJ89: 3470 | AK89: 3450 | AL89: 3420 | AM89: 3400 | AO89: BiomassSubcirical | AP89: Baseline | AQ89: Low LR | AR89: 72 | AS89: 70.395234 | AT89: 69.841764 | AU89: 69.62294 | AV89: 69.376489 | AW89: 69.018004 | AX89: 68.382494 | AY89: 68.027437
AB90: 31 | AC90: BiomassGasified | AD90: Baseline | AE90: Low LR | AF90: 5300 | AG90: 5180 | AH90: 5140 | AI90: 5130 | AJ90: 5110 | AK90: 5080 | AL90: 5030 | AM90: 5010 | AO90: BiomassGasified | AP90: Baseline | AQ90: Low LR | AR90: 106 | AS90: 103.63743 | AT90: 102.8226 | AU90: 102.50044 | AV90: 102.13761 | AW90: 101.60984 | AX90: 100.67423 | AY90: 100.1515
AB91: 46 | AC91: BiomassORC | AD91: Baseline | AE91: Low LR | AF91: 4700 | AG91: 4600 | AH91: 4560 | AI91: 4540 | AJ91: 4530 | AK91: 4510 | AL91: 4460 | AM91: 4440 | AO91: BiomassORC | AP91: Baseline | AQ91: Low LR | AR91: 94 | AS91: 91.904889 | AT91: 91.182303 | AU91: 90.896616 | AV91: 90.574861 | AW91: 90.106838 | AX91: 89.277146 | AY91: 88.813598
AB92: 61 | AC92: BiomassDigest | AD92: Baseline | AE92: Low LR | AF92: 3100 | AG92: 3030 | AH92: 3010 | AI92: 3000 | AJ92: 2990 | AK92: 2970 | AL92: 2940 | AM92: 2930 | AO92: BiomassDigest | AP92: Baseline | AQ92: Low LR | AR92: 124 | AS92: 121.23624 | AT92: 120.28304 | AU92: 119.90617 | AV92: 119.48173 | AW92: 118.86434 | AX92: 117.76985 | AY92: 117.15836
AB93: 76
AB94: 91
AB95: 106
AB96: 121
AB97: 136
AF100: 2015 | AG100: 2020 | AH100: 2025 | AI100: 2030 | AJ100: 2035 | AK100: 2040 | AL100: 2045 | AM100: 2050 | AR100: 2015 | AS100: 2020 | AT100: 2025 | AU100: 2030 | AV100: 2035 | AW100: 2040 | AX100: 2045 | AY100: 2050
AB101: 17 | AC101: BiomassSubcirical | AD101: Diversified portfolio | AE101: Low LR | AF101: 3600 | AG101: 3490 | AH101: 3450 | AI101: 3430 | AJ101: 3400 | AK101: 3370 | AL101: 3330 | AM101: 3310 | AO101: BiomassSubcirical | AP101: Diversified portfolio | AQ101: Low LR | AR101: 72 | AS101: 69.788858 | AT101: 68.955305 | AU101: 68.574292 | AV101: 68.014308 | AW101: 67.445028 | AX101: 66.653539 | AY101: 66.203943
AB102: 32 | AC102: BiomassGasified | AD102: Diversified portfolio | AE102: Low LR | AF102: 5300 | AG102: 5140 | AH102: 5080 | AI102: 5050 | AJ102: 5010 | AK102: 4960 | AL102: 4910 | AM102: 4870 | AO102: BiomassGasified | AP102: Diversified portfolio | AQ102: Low LR | AR102: 106 | AS102: 102.74471 | AT102: 101.51753 | AU102: 100.9566 | AV102: 100.13218 | AW102: 99.29407 | AX102: 98.128822 | AY102: 97.466916
AB103: 47 | AC103: BiomassORC | AD103: Diversified portfolio | AE103: Low LR | AF103: 4700 | AG103: 4560 | AH103: 4500 | AI103: 4480 | AJ103: 4440 | AK103: 4400 | AL103: 4350 | AM103: 4320 | AO103: BiomassORC | AP103: Diversified portfolio | AQ103: Low LR | AR103: 94 | AS103: 91.113231 | AT103: 90.024982 | AU103: 89.527548 | AV103: 88.796458 | AW103: 88.053231 | AX103: 87.019899 | AY103: 86.432925
AB104: 62 | AC104: BiomassDigest | AD104: Diversified portfolio | AE104: Low LR | AF104: 3100 | AG104: 3000 | AH104: 2970 | AI104: 2950 | AJ104: 2930 | AK104: 2900 | AL104: 2870 | AM104: 2850 | AO104: BiomassDigest | AP104: Diversified portfolio | AQ104: Low LR | AR104: 124 | AS104: 120.19192 | AT104: 118.75636 | AU104: 118.10017 | AV104: 117.13575 | AW104: 116.15533 | AX104: 114.79221 | AY104: 114.0179
AB105: 77
AB106: 92
AB107: 107
AB108: 122
...

Sheet CCUS_Summary
F1: CAPEX (Eur/kW) | R1: OPEX Eur/kW/Year | AB1: Summary | AE1: CAPEX (Eur/kW) | AP1: OPEX Eur/kW/Year | BC1: CAPEX (Eur/kW) | BN1: OPEX Eur/kW/Year | BY1: CAPEX (Eur/kW) | CI1: OPEX Eur/kW/Year
B2: Page Name | C2: Upper left cell | E2: 0 | F2: 1 | G2: 2 | H2: 3 | I2: 4 | J2: 5 | K2: 6 | L2: 7 | M2: 8 | N2: 9 | Q2: 18 | R2: 19 | S2: 20 | T2: 21 | U2: 22 | V2: 23 | W2: 24 | X2: 25 | Y2: 26 | Z2: 27 | AC2: 0 | AD2: 1 | AE2: 2 | AF2: 3 | AG2: 4 | AH2: 5 | AI2: 6 | AJ2: 7 | AK2: 8 | AL2: 9 | AM2: 10 | AR2: 15 | AS2: 16 | AT2: 17 | AU2: 18 | AV2: 19 | AW2: 20 | AX2: 21 | AY2: 22
BA3: MAX | BM3: MAX | BW3: MAX
A4: 0 | G4: 2015 | H4: 2020 | I4: 2025 | J4: 2030 | K4: 2035 | L4: 2040 | M4: 2045 | N4: 2050 | S4: 2015 | T4: 2020 | U4: 2025 | V4: 2030 | W4: 2035 | X4: 2040 | Y4: 2045 | Z4: 2050 | AF4: 2015 | AG4: 2020 | AH4: 2025 | AI4: 2030 | AJ4: 2035 | AK4: 2040 | AL4: 2045 | AM4: 2050 | AR4: 2015 | AS4: 2020 | AT4: 2025 | AU4: 2030 | AV4: 2035 | AW4: 2040 | AX4: 2045 | AY4: 2050 | BC4: 2015 | BD4: 2020 | BE4: 2025 | BF4: 2030 | BG4: 2035 | BH4: 2040 | BI4: 2045 | BJ4: 2050 | BN4: 2015 | BO4: 2020 | BP4: 2025 | BQ4: 2030 | BR4: 2035 | BS4: 2040 | BT4: 2045 | BU4: 2050 | BY4: 2015 | BZ4: 2020 | CA4: 2025 | CB4: 2030 | CC4: 2035 | CD4: 2040 | CE4: 2045 | CF4: 2050 | CG4: Reduction | CJ4: 2015 | CK4: 2020 | CL4: 2025 | CM4: 2030 | CN4: 2035 | CO4: 2040 | CP4: 2045 | CQ4: 2050
A5: 1 | B5: CCUS_Gas | C5: G24 | D5: CCGT Advanced + CCS post combustion | E5: ProRES | F5: Ref LR | G5: #N/A | H5: #N/A | I5: #N/A | J5: #N/A | K5: #N/A | L5: #N/A | M5: #N/A | N5: #N/A | P5: CCGT Advanced + CCS post combustion | Q5: ProRES | R5: Ref LR | S5: #N/A | T5: #N/A | U5: #N/A | V5: #N/A | W5: #N/A | X5: #N/A | Y5: #N/A | Z5: #N/A | AB5: 5 | AC5: CCGT Advanced + CCS post combustion | AD5: ProRES | AE5: Ref LR | AF5: #N/A | AG5: #N/A | AH5: #N/A | AI5: #N/A | AJ5: #N/A | AK5: #N/A | AL5: #N/A | AM5: #N/A | AO5: CCGT Advanced + CCS post combustion | AP5: ProRES | AQ5: Ref LR | AR5: #N/A | AS5: #N/A | AT5: #N/A | AU5: #N/A | AV5: #N/A | AW5: #N/A | AX5: #N/A | AY5: #N/A | BA5: ProRES | BC5: #N/A | BD5: #N/A | BE5: #N/A | BF5: #N/A | BG5: #N/A | BH5: #N/A | BI5: #N/A | BJ5: #N/A | BM5: ProRES | BN5: #N/A | BO5: #N/A | BP5: #N/A | BQ5: #N/A | BR5: #N/A | BS5: #N/A | BT5: #N/A | BU5: #N/A | BW5: CCGT Advanced + CCS post combustion | BY5: #N/A | BZ5: #N/A | CA5: #N/A | CB5: #N/A | CC5: #N/A | CD5: #N/A | CE5: #N/A | CF5: #N/A | CG5: #N/A | CI5: CCGT Advanced + CCS post combustion | CK5: #N/A | CL5: #N/A | CM5: #N/A | CN5: #N/A | CO5: #N/A | CP5: #N/A | CQ5: #N/A
A6: 2 | C6: -1 | E6: Baseline | F6: Ref LR | G6: #N/A | H6: #N/A | I6: 1510 | J6: 1510 | K6: 1510 | L6: 1510 | M6: 1510 | N6: 1510 | Q6: Baseline | R6: Ref LR | S6: #N/A | T6: #N/A | U6: 37.7 | V6: 37.7 | W6: 37.7 | X6: 37.7 | Y6: 37.7 | Z6: 37.7 | AB6: 20 | AC6: SC PC + CCS post combustion | AD6: ProRES | AE6: Ref LR | AF6: #N/A | AG6: #N/A | AH6: #N/A | AI6: #N/A | AJ6: #N/A | AK6: #N/A | AL6: #N/A | AM6: #N/A | AO6: SC PC + CCS post combustion | AP6: ProRES | AQ6: Ref LR | AR6: #N/A | AS6: #N/A | AT6: #N/A | AU6: #N/A | AV6: #N/A | AW6: #N/A | AX6: #N/A | AY6: #N/A | BA6: Baseline | BC6: #N/A | BD6: #N/A | BE6: #REF! | BF6: #REF! | BG6: #REF! | BH6: #REF! | BI6: #REF! | BJ6: #REF! | BM6: Baseline | BN6: #N/A | BO6: #N/A | BP6: #REF! | BQ6: #REF! | BR6: #REF! | BS6: #REF! | BT6: #REF! | BU6: #REF! | BW6: SC PC + CCS post combustion | BY6: #N/A | BZ6: #N/A | CA6: #N/A | CB6: #N/A | CC6: #N/A | CD6: #N/A | CE6: #N/A | CF6: #N/A | CI6: SC PC + CCS post combustion | CK6: #N/A | CL6: #N/A | CM6: #N/A | CN6: #N/A | CO6: #N/A | CP6: #N/A | CQ6: #N/A
A7: 3 | E7: Diversified portfolio | F7: Ref LR | G7: #N/A | H7: #N/A | I7: 1510 | J7: 1390 | K7: 1340 | L7: 1310 | M7: 1290 | N7: 1280 | Q7: Diversified portfolio | R7: Ref LR | S7: #N/A | T7: #N/A | U7: 37.703599 | V7: 34.789666 | W7: 33.468773 | X7: 32.726969 | Y7: 32.275633 | Z7: 32.026667 | AB7: 35 | AC7: SC PC + CCS Oxyfuel | AD7: ProRES | AE7: LR_Oxy_Ref | AF7: #N/A | AG7: #N/A | AH7: #N/A | AI7: #N/A | AJ7: #N/A | AK7: #N/A | AL7: #N/A | AM7: #N/A | AO7: SC PC + CCS Oxyfuel | AP7: ProRES | AQ7: LR_Oxy_Ref | AR7: #N/A | AS7: #N/A | AT7: #N/A | AU7: #N/A | AV7: #N/A | AW7: #N/A | AX7: #N/A | AY7: #N/A | BA7: Diversified portfolio | BC7: #N/A | BD7: #N/A | BE7: #REF! | BF7: #REF! | BG7: #REF! | BH7: #REF! | BI7: #REF! | BJ7: #REF! | BM7: Diversified portfolio | BN7: #N/A | BO7: #N/A | BP7: #REF! | BQ7: #REF! | BR7: #REF! | BS7: #REF! | BT7: #REF! | BU7: #REF! | BW7: SC PC + CCS Oxyfuel | BY7: #N/A | BZ7: #N/A | CA7: #N/A | CB7: #N/A | CC7: #N/A | CD7: #N/A | CE7: #N/A | CF7: #N/A | CI7: SC PC + CCS Oxyfuel | CK7: #N/A | CL7: #N/A | CM7: #N/A | CN7: #N/A | CO7: #N/A | CP7: #N/A | CQ7: #N/A
AB8: 50 | AC8: IGCC lignite + CCS pre combustion | AD8: ProRES | AE8: LR_IGCC_Ref | AF8: #N/A | AG8: #N/A | AH8: #N/A | AI8: #N/A | AJ8: #N/A | AK8: #N/A | AL8: #N/A | AM8: #N/A | AO8: IGCC lignite + CCS pre combustion | AP8: ProRES | AQ8: LR_IGCC_Ref | AR8: #N/A | AS8: #N/A | AT8: #N/A | AU8: #N/A | AV8: #N/A | AW8: #N/A | AX8: #N/A | AY8: #N/A | BW8: IGCC lignite + CCS pre combustion | BY8: #N/A | BZ8: #N/A | CA8: #N/A | CB8: #N/A | CC8: #N/A | CD8: #N/A | CE8: #N/A | CF8: #N/A | CI8: IGCC lignite + CCS pre combustion | CK8: #N/A | CL8: #N/A | CM8: #N/A | CN8: #N/A | CO8: #N/A | CP8: #N/A | CQ8: #N/A
A9: 0 | G9: 2015 | H9: 2020 | I9: 2025 | J9: 2030 | K9: 2035 | L9: 2040 | M9: 2045 | N9: 2050 | S9: 2015 | T9: 2020 | U9: 2025 | V9: 2030 | W9: 2035 | X9: 2040 | Y9: 2045 | Z9: 2050 | AB9: 65 | AC9: IGCC + CCS pre combustion | AD9: ProRES | AE9: LR_IGCC_Ref | AF9: #N/A | AG9: #N/A | AH9: #N/A | AI9: #N/A | AJ9: #N/A | AK9: #N/A | AL9: #N/A | AM9: #N/A | AO9: IGCC + CCS pre combustion | AP9: ProRES | AQ9: LR_IGCC_Ref | AR9: #N/A | AS9: #N/A | AT9: #N/A | AU9: #N/A | AV9: #N/A | AW9: #N/A | AX9: #N/A | AY9: #N/A | BW9: IGCC + CCS pre combustion | BY9: #N/A | BZ9: #N/A | CA9: #N/A | CB9: #N/A | CC9: #N/A | CD9: #N/A | CE9: #N/A | CF9: #N/A | CI9: IGCC + CCS pre combustion | CK9: #N/A | CL9: #N/A | CM9: #N/A | CN9: #N/A | CO9: #N/A | CP9: #N/A | CQ9: #N/A
A10: 1 | B10: CCUS_Gas | C10: G31 | D10: CCGT Advanced + CCS post combustion | E10: ProRES | F10: High LR | G10: #N/A | H10: #N/A | I10: #N/A | J10: #N/A | K10: #N/A | L10: #N/A | M10: #N/A | N10: #N/A | P10: CCGT Advanced + CCS post combustion | Q10: ProRES | R10: High LR | S10: #N/A | T10: #N/A | U10: #N/A | V10: #N/A | W10: #N/A | X10: #N/A | Y10: #N/A | Z10: #N/A | AB10: 80 | AC10: IGCC biomass with CCS pre combustion | AD10: ProRES | AE10: LR_IGCC_B_Ref | AF10: #N/A | AG10: #N/A | AH10: #N/A | AI10: #N/A | AJ10: #N/A | AK10: #N/A | AL10: #N/A | AM10: #N/A | AO10: IGCC biomass with CCS pre combustion | AP10: ProRES | AQ10: LR_IGCC_B_Ref | AR10: #N/A | AS10: #N/A | AT10: #N/A | AU10: #N/A | AV10: #N/A | AW10: #N/A | AX10: #N/A | AY10: #N/A | BA10: MIN | BM10: MIN | BW10: IGCC biomass with CCS pre combustion | BY10: #N/A | BZ10: #N/A | CA10: #N/A | CB10: #N/A | CC10: #N/A | CD10: #N/A | CE10: #N/A | CF10: #N/A | CI10: IGCC biomass with CCS pre combustion | CK10: #N/A | CL10: #N/A | CM10: #N/A | CN10: #N/A | CO10: #N/A | CP10: #N/A | CQ10: #N/A
A11: 2 | C11: -1 | E11: Baseline | F11: High LR | G11: #N/A | H11: #N/A | I11: 1510 | J11: 1510 | K11: 1510 | L11: 1510 | M11: 1510 | N11: 1510 | Q11: Baseline | R11: High LR | S11: #N/A | T11: #N/A | U11: 37.7 | V11: 37.7 | W11: 37.7 | X11: 37.7 | Y11: 37.7 | Z11: 37.7 | AB11: 95 | AC11: #REF! | AD11: #REF! | AE11: #REF! | AF11: #REF! | AG11: #REF! | AH11: #REF! | AI11: #REF! | AJ11: #REF! | AK11: #REF! | AL11: #REF! | AM11: #REF! | AO11: #REF! | AP11: #REF! | AQ11: #REF! | AR11: #REF! | AS11: #REF! | AT11: #REF! | AU11: #REF! | AV11: #REF! | AW11: #REF! | AX11: #REF! | AY11: #REF! | BC11: 2015 | BD11: 2020 | BE11: 2025 | BF11: 2030 | BG11: 2035 | BH11: 2040 | BI11: 2045 | BJ11: 2050 | BN11: 2015 | BO11: 2020 | BP11: 2025 | BQ11: 2030 | BR11: 2035 | BS11: 2040 | BT11: 2045 | BU11: 2050 | BW11: #REF! | BY11: #REF! | BZ11: #REF! | CA11: #REF! | CB11: #REF! | CC11: #REF! | CD11: #REF! | CE11: #REF! | CF11: #REF! | CI11: #REF! | CK11: #REF! | CL11: #REF! | CM11: #REF! | CN11: #REF! | CO11: #REF! | CP11: #REF! | CQ11: #REF!
A12: 3 | E12: Diversified portfolio | F12: High LR | G12: #N/A | H12: #N/A | I12: 1510 | J12: 1320 | K12: 1240 | L12: 1190 | M12: 1170 | N12: 1150 | Q12: Diversified portfolio | R12: High LR | S12: #N/A | T12: #N/A | U12: 37.703599 | V12: 33.02242 | W12: 30.981527 | X12: 29.857936 | Y12: 29.182318 | Z12: 28.812241 | AB12: 110 | AC12: #REF! | AD12: #REF! | AE12: #REF! | AF12: #REF! | AG12: #REF! | AH12: #REF! | AI12: #REF! | AJ12: #REF! | AK12: #REF! | AL12: #REF! | AM12: #REF! | AO12: #REF! | AP12: #REF! | AQ12: #REF! | AR12: #REF! | AS12: #REF! | AT12: #REF! | AU12: #REF! | AV12: #REF! | AW12: #REF! | AX12: #REF! | AY12: #REF! | BA12: ProRES | BC12: #N/A | BD12: #N/A | BE12: #N/A | BF12: #N/A | BG12: #N/A | BH12: #N/A | BI12: #N/A | BJ12: #N/A | BM12: ProRES | BN12: #N/A | BO12: #N/A | BP12: #N/A | BQ12: #N/A | BR12: #N/A | BS12: #N/A | BT12: #N/A | BU12: #N/A | BW12: #REF! | BY12: #REF! | BZ12: #REF! | CA12: #REF! | CB12: #REF! | CC12: #REF! | CD12: #REF! | CE12: #REF! | CF12: #REF! | CI12: #REF! | CK12: #REF! | CL12: #REF! | CM12: #REF! | CN12: #REF! | CO12: #REF! | CP12: #REF! | CQ12: #REF!
BA13: Baseline | BC13: #N/A | BD13: #N/A | BE13: #REF! | BF13: #REF! | BG13: #REF! | BH13: #REF! | BI13: #REF! | BJ13: #REF! | BM13: Baseline | BN13: #N/A | BO13: #N/A | BP13: #REF! | BQ13: #REF! | BR13: #REF! | BS13: #REF! | BT13: #REF! | BU13: #REF!
A14: 0 | G14: 2015 | H14: 2020 | I14: 2025 | J14: 2030 | K14: 2035 | L14: 2040 | M14: 2045 | N14: 2050 | S14: 2015 | T14: 2020 | U14: 2025 | V14: 2030 | W14: 2035 | X14: 2040 | Y14: 2045 | Z14: 2050 | BA14: Diversified portfolio | BC14: #N/A | BD14: #N/A | BE14: #REF! | BF14: #REF! | BG14: #REF! | BH14: #REF! | BI14: #REF! | BJ14: #REF! | BM14: Diversified portfolio | BN14: #N/A | BO14: #N/A | BP14: #REF! | BQ14: #REF! | BR14: #REF! | BS14: #REF! | BT14: #REF! | BU14: #REF!
A15: 1 | B15: CCUS_Gas | C15: G38 | D15: CCGT Advanced + CCS post combustion | E15: ProRES | F15: Low LR | G15: #N/A | H15: #N/A | I15: #N/A | J15: #N/A | K15: #N/A | L15: #N/A | M15: #N/A | N15: #N/A | P15: CCGT Advanced + CCS post combustion | Q15: ProRES | R15: Low LR | S15: #N/A | T15: #N/A | U15: #N/A | V15: #N/A | W15: #N/A | X15: #N/A | Y15: #N/A | Z15: #N/A
A16: 2 | C16: -1 | E16: Baseline | F16: Low LR | G16: #N/A | H16: #N/A | I16: 1510 | J16: 1510 | K16: 1510 | L16: 1510 | M16: 1510 | N16: 1510 | Q16: Baseline | R16: Low LR | S16: #N/A | T16: #N/A | U16: 37.7 | V16: 37.7 | W16: 37.7 | X16: 37.7 | Y16: 37.7 | Z16: 37.7 | AF16: 2015 | AG16: 2020 | AH16: 2025 | AI16: 2030 | AJ16: 2035 | AK16: 2040 | AL16: 2045 | AM16: 2050 | AR16: 2015 | AS16: 2020 | AT16: 2025 | AU16: 2030 | AV16: 2035 | AW16: 2040 | AX16: 2045 | AY16: 2050
A17: 3 | E17: Diversified portfolio | F17: Low LR | G17: #N/A | H17: #N/A | I17: 1510 | J17: 1440 | K17: 1410 | L17: 1400 | M17: 1390 | N17: 1380 | Q17: Diversified portfolio | R17: Low LR | S17: #N/A | T17: #N/A | U17: 37.703599 | V17: 36.093175 | W17: 35.342896 | X17: 34.915602 | Y17: 34.653455 | Z17: 34.508131 | AB17: 6 | AC17: CCGT Advanced + CCS post combustion | AD17: Baseline | AE17: Ref LR | AF17: #N/A | AG17: #N/A | AH17: 1510 | AI17: 1510 | AJ17: 1510 | AK17: 1510 | AL17: 1510 | AM17: 1510 | AO17: CCGT Advanced + CCS post combustion | AP17: Baseline | AQ17: Ref LR | AR17: #N/A | AS17: #N/A | AT17: 37.703599 | AU17: 37.703599 | AV17: 37.703599 | AW17: 37.703599 | AX17: 37.703599 | AY17: 37.703599 | BC17: 2015 | BD17: 2020 | BE17: 2025 | BF17: 2030 | BG17: 2035 | BH17: 2040 | BI17: 2045 | BJ17: 2050 | BN17: 2015 | BO17: 2020 | BP17: 2025 | BQ17: 2030 | BR17: 2035 | BS17: 2040 | BT17: 2045 | BU17: 2050 | BW17: MIN
AB18: 21 | AC18: SC PC + CCS post combustion | AD18: Baseline | AE18: Ref LR | AF18: #N/A | AG18: #N/A | AH18: 2920 | AI18: 2760 | AJ18: 2710 | AK18: 2680 | AL18: 2640 | AM18: 2580 | AO18: SC PC + CCS post combustion | AP18: Baseline | AQ18: Ref LR | AR18: #N/A | AS18: #N/A | AT18: 59.772773 | AU18: 56.568396 | AV18: 55.507783 | AW18: 54.853883 | AX18: 54.03645 | AY18: 52.939925 | BB18: Max | BC18: #N/A | BD18: #N/A | BE18: #N/A | BF18: #N/A | BG18: #N/A | BH18: #N/A | BI18: #N/A | BJ18: #N/A | BM18: Max | BN18: #N/A | BO18: #N/A | BP18: #N/A | BQ18: #N/A | BR18: #N/A | BS18: #N/A | BT18: #N/A | BU18: #N/A | BY18: 2015 | BZ18: 2020 | CA18: 2025 | CB18: 2030 | CC18: 2035 | CD18: 2040 | CE18: 2045 | CF18: 2050 | CG18: Reduction | CJ18: 2015 | CK18: 2020 | CL18: 2025 | CM18: 2030 | CN18: 2035 | CO18: 2040 | CP18: 2045 | CQ18: 2050
A19: 0 | G19: 2015 | H19: 2020 | I19: 2025 | J19: 2030 | K19: 2035 | L19: 2040 | M19: 2045 | N19: 2050 | S19: 2015 | T19: 2020 | U19: 2025 | V19: 2030 | W19: 2035 | X19: 2040 | Y19: 2045 | Z19: 2050 | AB19: 36 | AC19: SC PC + CCS Oxyfuel | AD19: Baseline | AE19: LR_Oxy_Ref | AF19: #N/A | AG19: #N/A | AH19: 2920 | AI19: 2710 | AJ19: 2640 | AK19: 2600 | AL19: 2550 | AM19: 2480 | AO19: SC PC + CCS Oxyfuel | AP19: Baseline | AQ19: LR_Oxy_Ref | AR19: #N/A | AS19: #N/A | AT19: 67.062136 | AU19: 62.295563 | AV19: 60.737639 | AW19: 59.782124 | AX19: 58.593053 | AY19: 57.007542 | BB19: Min | BC19: #N/A | BD19: #N/A | BE19: #N/A | BF19: #N/A | BG19: #N/A | BH19: #N/A | BI19: #N/A | BJ19: #N/A | BM19: Min | BN19: #N/A | BO19: #N/A | BP19: #N/A | BQ19: #N/A | BR19: #N/A | BS19: #N/A | BT19: #N/A | BU19: #N/A | BW19: CCGT Advanced + CCS post combustion | BY19: #N/A | BZ19: #N/A | CA19: #N/A | CB19: #N/A | CC19: #N/A | CD19: #N/A | CE19: #N/A | CF19: #N/A | CG19: #N/A | CI19: CCGT Advanced + CCS post combustion | CK19: #N/A | CL19: #N/A | CM19: #N/A | CN19: #N/A | CO19: #N/A | CP19: #N/A | CQ19: #N/A
A20: 1 | B20: CCUS_Coal_PC | C20: G24 | D20: SC PC + CCS post combustion | E20: ProRES | F20: Ref LR | G20: #N/A | H20: #N/A | I20: #N/A | J20: #N/A | K20: #N/A | L20: #N/A | M20: #N/A | N20: #N/A | P20: SC PC + CCS post combustion | Q20: ProRES | R20: Ref LR | S20: #N/A | T20: #N/A | U20: #N/A | V20: #N/A | W20: #N/A | X20: #N/A | Y20: #N/A | Z20: #N/A | AB20: 51 | AC20: IGCC lignite + CCS pre combustion | AD20: Baseline | AE20: LR_IGCC_Ref | AF20: #N/A | AG20: #N/A | AH20: 4480 | AI20: 3920 | AJ20: 3750 | AK20: 3640 | AL20: 3510 | AM20: 3340 | AO20: IGCC lignite + CCS pre combustion | AP20: Baseline | AQ20: LR_IGCC_Ref | AR20: #N/A | AS20: #N/A | AT20: 98.578993 | AU20: 86.288208 | AV20: 82.430018 | AW20: 80.10273 | AX20: 77.248206 | AY20: 73.514067 | BW20: SC PC + CCS post combustion | BY20: #N/A | BZ20: #N/A | CA20: #N/A | CB20: #N/A | CC20: #N/A | CD20: #N/A | CE20: #N/A | CF20: #N/A | CI20: SC PC + CCS post combustion | CK20: #N/A | CL20: #N/A | CM20: #N/A | CN20: #N/A | CO20: #N/A | CP20: #N/A | CQ20: #N/A
A21: 2 | C21: -1 | E21: Baseline | F21: Ref LR | G21: #N/A | H21: #N/A | I21: 2920 | J21: 2760 | K21: 2710 | L21: 2680 | M21: 2640 | N21: 2580 | Q21: Baseline | R21: Ref LR | S21: #N/A | T21: #N/A | U21: 59.772773 | V21: 56.568396 | W21: 55.507783 | X21: 54.853883 | Y21: 54.03645 | Z21: 52.939925 | AB21: 66 | AC21: IGCC + CCS pre combustion | AD21: Baseline | AE21: LR_IGCC_Ref | AF21: #N/A | AG21: #N/A | AH21: 2940 | AI21: 2580 | AJ21: 2460 | AK21: 2390 | AL21: 2310 | AM21: 2200 | AO21: IGCC + CCS pre combustion | AP21: Baseline | AQ21: LR_IGCC_Ref | AR21: #N/A | AS21: #N/A | AT21: 88.326966 | AU21: 77.314398 | AV21: 73.857453 | AW21: 71.772198 | AX21: 69.21454 | AY21: 65.868744 | BW21: SC PC + CCS Oxyfuel | BY21: #N/A | BZ21: #N/A | CA21: #N/A | CB21: #N/A | CC21: #N/A | CD21: #N/A | CE21: #N/A | CF21: #N/A | CI21: SC PC + CCS Oxyfuel | CK21: #N/A | CL21: #N/A | CM21: #N/A | CN21: #N/A | CO21: #N/A | CP21: #N/A | CQ21: #N/A
A22: 3 | E22: Diversified portfolio | F22: Ref LR | G22: #N/A | H22: #N/A | I22: 2920 | J22: 2740 | K22: 2650 | L22: 2590 | M22: 2570 | N22: 2570 | Q22: Diversified portfolio | R22: Ref LR | S22: #N/A | T22: #N/A | U22: 59.772773 | V22: 56.245515 | W22: 54.256404 | X22: 53.162637 | Y22: 52.740379 | Z22: 52.740379 | AB22: 81 | AC22: IGCC biomass with CCS pre combustion | AD22: Baseline | AE22: LR_IGCC_B_Ref | AF22: #N/A | AG22: #N/A | AH22: 5800 | AI22: 5800 | AJ22: 5800 | AK22: 5800 | AL22: 5800 | AM22: 5800 | AO22: IGCC biomass with CCS pre combustion | AP22: Baseline | AQ22: LR_IGCC_B_Ref | AR22: #N/A | AS22: #N/A | AT22: 133.4 | AU22: 133.4 | AV22: 133.4 | AW22: 133.4 | AX22: 133.4 | AY22: 133.4 | BW22: IGCC lignite + CCS pre combustion | BY22: #N/A | BZ22: #N/A | CA22: #N/A | CB22: #N/A | CC22: #N/A | CD22: #N/A | CE22: #N/A | CF22: #N/A | CI22: IGCC lignite + CCS pre combustion | CK22: #N/A | CL22: #N/A | CM22: #N/A | CN22: #N/A | CO22: #N/A | CP22: #N/A | CQ22: #N/A
AB23: 96 | AC23: #REF! | AD23: #REF! | AE23: #REF! | AF23: #REF! | AG23: #REF! | AH23: #REF! | AI23: #REF! | AJ23: #REF! | AK23: #REF! | AL23: #REF! | AM23: #REF! | AO23: #REF! | AP23: #REF! | AQ23: #REF! | AR23: #REF! | AS23: #REF! | AT23: #REF! | AU23: #REF! | AV23: #REF! | AW23: #REF! | AX23: #REF! | AY23: #REF! | BW23: IGCC + CCS pre combustion | BY23: #N/A | BZ23: #N/A | CA23: #N/A | CB23: #N/A | CC23: #N/A | CD23: #N/A | CE23: #N/A | CF23: #N/A | CI23: IGCC + CCS pre combustion | CK23: #N/A | CL23: #N/A | CM23: #N/A | CN23: #N/A | CO23: #N/A | CP23: #N/A | CQ23: #N/A
A24: 0 | G24: 2015 | H24: 2020 | I24: 2025 | J24: 2030 | K24: 2035 | L24: 2040 | M24: 2045 | N24: 2050 | S24: 2015 | T24: 2020 | U24: 2025 | V24: 2030 | W24: 2035 | X24: 2040 | Y24: 2045 | Z24: 2050 | AB24: 111 | AC24: #REF! | AD24: #REF! | AE24: #REF! | AF24: #REF! | AG24: #REF! | AH24: #REF! | AI24: #REF! | AJ24: #REF! | AK24: #REF! | AL24: #REF! | AM24: #REF! | AO24: #REF! | AP24: #REF! | AQ24: #REF! | AR24: #REF! | AS24: #REF! | AT24: #REF! | AU24: #REF! | AV24: #REF! | AW24: #REF! | AX24: #REF! | AY24: #REF! | BW24: IGCC biomass with CCS pre combustion | BY24: #N/A | BZ24: #N/A | CA24: #N/A | CB24: #N/A | CC24: #N/A | CD24: #N/A | CE24: #N/A | CF24: #N/A | CI24: IGCC biomass with CCS pre combustion | CK24: #N/A | CL24: #N/A | CM24: #N/A | CN24: #N/A | CO24: #N/A | CP24: #N/A | CQ24: #N/A
A25: 1 | B25: CCUS_Coal_PC | C25: G31 | D25: SC PC + CCS post combustion | E25: ProRES | F25: High LR | G25: #N/A | H25: #N/A | I25: #N/A | J25: #N/A | K25: #N/A | L25: #N/A | M25: #N/A | N25: #N/A | P25: SC PC + CCS post combustion | Q25: ProRES | R25: High LR | S25: #N/A | T25: #N/A | U25: #N/A | V25: #N/A | W25: #N/A | X25: #N/A | Y25: #N/A | Z25: #N/A | AB25: 126 | BW25: #REF! | BY25: #REF! | BZ25: #REF! | CA25: #REF! | CB25: #REF! | CC25: #REF! | CD25: #REF! | CE25: #REF! | CF25: #REF! | CI25: #REF! | CK25: #REF! | CL25: #REF! | CM25: #REF! | CN25: #REF! | CO25: #REF! | CP25: #REF! | CQ25: #REF!
A26: 2 | C26: -1 | E26: Baseline | F26: High LR | G26: #N/A | H26: #N/A | I26: 2920 | J26: 2660 | K26: 2580 | L26: 2520 | M26: 2460 | N26: 2380 | Q26: Baseline | R26: High LR | S26: #N/A | T26: #N/A | U26: 59.772773 | V26: 54.49215 | W26: 52.788026 | X26: 51.748315 | Y26: 50.460369 | Z26: 48.753358 | BW26: #REF! | BY26: #REF! | BZ26: #REF! | CA26: #REF! | CB26: #REF! | CC26: #REF! | CD26: #REF! | CE26: #REF! | CF26: #REF! | CI26: #REF! | CK26: #REF! | CL26: #REF! | CM26: #REF! | CN26: #REF! | CO26: #REF! | CP26: #REF! | CQ26: #REF!
A27: 3 | E27: Diversified portfolio | F27: High LR | G27: #N/A | H27: #N/A | I27: 2920 | J27: 2630 | K27: 2480 | L27: 2400 | M27: 2360 | N27: 2360 | Q27: Diversified portfolio | R27: High LR | S27: #N/A | T27: #N/A | U27: 59.772773 | V27: 53.97105 | W27: 50.805638 | X27: 49.098142 | Y27: 48.445274 | Z27: 48.445274
AF28: 2015 | AG28: 2020 | AH28: 2025 | AI28: 2030 | AJ28: 2035 | AK28: 2040 | AL28: 2045 | AM28: 2050 | AR28: 2015 | AS28: 2020 | AT28: 2025 | AU28: 2030 | AV28: 2035 | AW28: 2040 | AX28: 2045 | AY28: 2050
A29: 0 | G29: 2015 | H29: 2020 | I29: 2025 | J29: 2030 | K29: 2035 | L29: 2040 | M29: 2045 | N29: 2050 | S29: 2015 | T29: 2020 | U29: 2025 | V29: 2030 | W29: 2035 | X29: 2040 | Y29: 2045 | Z29: 2050 | AB29: 7 | AC29: CCGT Advanced + CCS post combustion | AD29: Diversified portfolio | AE29: Ref LR | AF29: #N/A | AG29: #N/A | AH29: 1510 | AI29: 1390 | AJ29: 1340 | AK29: 1310 | AL29: 1290 | AM29: 1280 | AO29: CCGT Advanced + CCS post combustion | AP29: Diversified portfolio | AQ29: Ref LR | AR29: #N/A | AS29: #N/A | AT29: 37.703599 | AU29: 34.789666 | AV29: 33.468773 | AW29: 32.726969 | AX29: 32.275633 | AY29: 32.026667
A30: 1 | B30: CCUS_Coal_PC | C30: G38 | D30: SC PC + CCS post combustion | E30: ProRES | F30: Low LR | G30: #N/A | H30: #N/A | I30: #N/A | J30: #N/A | K30: #N/A | L30: #N/A | M30: #N/A | N30: #N/A | P30: SC PC + CCS post combustion | Q30: ProRES | R30: Low LR | S30: #N/A | T30: #N/A | U30: #N/A | V30: #N/A | W30: #N/A | X30: #N/A | Y30: #N/A | Z30: #N/A | AB30: 22 | AC30: SC PC + CCS post combustion | AD30: Diversified portfolio | AE30: Ref LR | AF30: #N/A | AG30: #N/A | AH30: 2920 | AI30: 2740 | AJ30: 2650 | AK30: 2590 | AL30: 2570 | AM30: 2570 | AO30: SC PC + CCS post combustion | AP30: Diversified portfolio | AQ30: Ref LR | AR30: #N/A | AS30: #N/A | AT30: 59.772773 | AU30: 56.245515 | AV30: 54.256404 | AW30: 53.162637 | AX30: 52.740379 | AY30: 52.740379
A31: 2 | C31: -1 | E31: Baseline | F31: Low LR | G31: #N/A | H31: #N/A | I31: 2920 | J31: 2830 | K31: 2810 | L31: 2790 | M31: 2770 | N31: 2740 | Q31: Baseline | R31: Low LR | S31: #N/A | T31: #N/A | U31: 59.772773 | V31: 58.080753 | W31: 57.510653 | X31: 57.156568 | Y31: 56.711074 | Z31: 56.108378 | AB31: 37 | AC31: SC PC + CCS Oxyfuel | AD31: Diversified portfolio | AE31: LR_Oxy_Ref | AF31: #N/A | AG31: #N/A | AH31: 2920 | AI31: 2690 | AJ31: 2560 | AK31: 2490 | AL31: 2470 | AM31: 2470 | AO31: SC PC + CCS Oxyfuel | AP31: Diversified portfolio | AQ31: LR_Oxy_Ref | AR31: #N/A | AS31: #N/A | AT31: 67.062136 | AU31: 61.820232 | AV31: 58.912413 | AW31: 57.328681 | AX31: 56.720196 | AY31: 56.720196
A32: 3 | E32: Diversified portfolio | F32: Low LR | G32: #N/A | H32: #N/A | I32: 2920 | J32: 2820 | K32: 2770 | L32: 2740 | M32: 2730 | N32: 2730 | Q32: Diversified portfolio | R32: Low LR | S32: #N/A | T32: #N/A | U32: 59.772773 | V32: 57.907745 | W32: 56.831262 | X32: 56.23127 | Y32: 55.998058 | Z32: 55.998058 | AB32: 52 | AC32: IGCC lignite + CCS pre combustion | AD32: Diversified portfolio | AE32: LR_IGCC_Ref | AF32: #N/A | AG32: #N/A | AH32: 4480 | AI32: 3870 | AJ32: 3550 | AK32: 3380 | AL32: 3310 | AM32: 3310 | AO32: IGCC lignite + CCS pre combustion | AP32: Diversified portfolio | AQ32: LR_IGCC_Ref | AR32: #N/A | AS32: #N/A | AT32: 98.578993 | AU32: 85.102707 | AV32: 78.010331 | AW32: 74.263731 | AX32: 72.846169 | AY32: 72.846169
AB33: 67 | AC33: IGCC + CCS pre combustion | AD33: Diversified portfolio | AE33: LR_IGCC_Ref | AF33: #N/A | AG33: #N/A | AH33: 2940 | AI33: 2540 | AJ33: 2330 | AK33: 2220 | AL33: 2180 | AM33: 2180 | AO33: IGCC + CCS pre combustion | AP33: Diversified portfolio | AQ33: LR_IGCC_Ref | AR33: #N/A | AS33: #N/A | AT33: 88.326966 | AU33: 76.252187 | AV33: 69.897405 | AW33: 66.540444 | AX33: 65.270306 | AY33: 65.270306
A34: 0 | G34: 2015 | H34: 2020 | I34: 2025 | J34: 2030 | K34: 2035 | L34: 2040 | M34: 2045 | N34: 2050 | S34: 2015 | T34: 2020 | U34: 2025 | V34: 2030 | W34: 2035 | X34: 2040 | Y34: 2045 | Z34: 2050 | AB34: 82 | AC34: IGCC biomass with CCS pre combustion | AD34: Diversified portfolio | AE34: LR_IGCC_B_Ref | AF34: #N/A | AG34: #N/A | AH34: 5800 | AI34: 5380 | AJ34: 4750 | AK34: 4310 | AL34: 3980 | AM34: 3840 | AO34: IGCC biomass with CCS pre combustion | AP34: Diversified portfolio | AQ34: LR_IGCC_B_Ref | AR34: #N/A | AS34: #N/A | AT34: 133.4 | AU34: 123.65677 | AV34: 109.14027 | AW34: 99.221915 | AX34: 91.628975 | AY34: 88.36012
A35: 1 | B35: CCUS_Coal_Oxy | C35: G24 | D35: SC PC + CCS Oxyfuel | E35: ProRES | F35: LR_Oxy_Ref | G35: #N/A | H35: #N/A | I35: #N/A | J35: #N/A | K35: #N/A | L35: #N/A | M35: #N/A | N35: #N/A | P35: SC PC + CCS Oxyfuel | Q35: ProRES | R35: LR_Oxy_Ref | S35: #N/A | T35: #N/A | U35: #N/A | V35: #N/A | W35: #N/A | X35: #N/A | Y35: #N/A | Z35: #N/A | AB35: 97 | AC35: #REF! | AD35: #REF! | AE35: #REF! | AF35: #REF! | AG35: #REF! | AH35: #REF! | AI35: #REF! | AJ35: #REF! | AK35: #REF! | AL35: #REF! | AM35: #REF! | AO35: #REF! | AP35: #REF! | AQ35: #REF! | AR35: #REF! | AS35: #REF! | AT35: #REF! | AU35: #REF! | AV35: #REF! | AW35: #REF! | AX35: #REF! | AY35: #REF!
A36: 2 | C36: -1 | E36: Baseline | F36: LR_Oxy_Ref | G36: #N/A | H36: #N/A | I36: 2920 | J36: 2710 | K36: 2640 | L36: 2600 | M36: 2550 | N36: 2480 | Q36: Baseline | R36: LR_Oxy_Ref | S36: #N/A | T36: #N/A | U36: 67.062136 | V36: 62.295563 | W36: 60.737639 | X36: 59.782124 | Y36: 58.593053 | Z36: 57.007542 | AB36: 112 | AC36: #REF! | AD36: #REF! | AE36: #REF! | AF36: #REF! | AG36: #REF! | AH36: #REF! | AI36: #REF! | AJ36: #REF! | AK36: #REF! | AL36: #REF! | AM36: #REF! | AO36: #REF! | AP36: #REF! | AQ36: #REF! | AR36: #REF! | AS36: #REF! | AT36: #REF! | AU36: #REF! | AV36: #REF! | AW36: #REF! | AX36: #REF! | AY36: #REF!
A37: 3 | E37: Diversified portfolio | F37: LR_Oxy_Ref | G37: #N/A | H37: #N/A | I37: 2920 | J37: 2690 | K37: 2560 | L37: 2490 | M37: 2470 | N37: 2470 | Q37: Diversified portfolio | R37: LR_Oxy_Ref | S37: #N/A | T37: #N/A | U37: 67.062136 | V37: 61.820232 | W37: 58.912413 | X37: 57.328681 | Y37: 56.720196 | Z37: 56.720196 | AB37: 127
A39: 0 | G39: 2015 | H39: 2020 | I39: 2025 | J39: 2030 | K39: 2035 | L39: 2040 | M39: 2045 | N39: 2050 | S39: 2015 | T39: 2020 | U39: 2025 | V39: 2030 | W39: 2035 | X39: 2040 | Y39: 2045 | Z39: 2050
A40: 1 | B40: CCUS_Coal_Oxy | C40: G31 | D40: SC PC + CCS Oxyfuel | E40: ProRES | F40: LR_Oxy_High | G40: #N/A | H40: #N/A | I40: #N/A | J40: #N/A | K40: #N/A | L40: #N/A | M40: #N/A | N40: #N/A | P40: SC PC + CCS Oxyfuel | Q40: ProRES | R40: LR_Oxy_High | S40: #N/A | T40: #N/A | U40: #N/A | V40: #N/A | W40: #N/A | X40: #N/A | Y40: #N/A | Z40: #N/A | AF40: 2015 | AG40: 2020 | AH40: 2025 | AI40: 2030 | AJ40: 2035 | AK40: 2040 | AL40: 2045 | AM40: 2050 | AR40: 2015 | AS40: 2020 | AT40: 2025 | AU40: 2030 | AV40: 2035 | AW40: 2040 | AX40: 2045 | AY40: 2050
A41: 2 | C41: -1 | E41: Baseline | F41: LR_Oxy_High | G41: #N/A | H41: #N/A | I41: 2920 | J41: 2590 | K41: 2490 | L41: 2430 | M41: 2350 | N41: 2250 | Q41: Baseline | R41: LR_Oxy_High | S41: #N/A | T41: #N/A | U41: 67.062136 | V41: 59.668219 | W41: 57.321224 | X41: 55.899004 | Y41: 54.147632 | Z41: 51.844502 | AB41: 10 | AC41: CCGT Advanced + CCS post combustion | AD41: ProRES | AE41: High LR | AF41: #N/A | AG41: #N/A | AH41: #N/A | AI41: #N/A | AJ41: #N/A | AK41: #N/A | AL41: #N/A | AM41: #N/A | AO41: CCGT Advanced + CCS post combustion | AP41: ProRES | AQ41: High LR | AR41: #N/A | AS41: #N/A | AT41: #N/A | AU41: #N/A | AV41: #N/A | AW41: #N/A | AX41: #N/A | AY41: #N/A
A42: 3 | E42: Diversified portfolio | F42: LR_Oxy_High | G42: #N/A | H42: #N/A | I42: 2920 | J42: 2560 | K42: 2370 | L42: 2270 | M42: 2240 | N42: 2240 | Q42: Diversified portfolio | R42: LR_Oxy_High | S42: #N/A | T42: #N/A | U42: 67.062136 | V42: 58.948459 | W42: 54.615994 | X42: 52.308007 | Y42: 51.431063 | Z42: 51.431063 | AB42: 25 | AC42: SC PC + CCS post combustion | AD42: ProRES | AE42: High LR | AF42: #N/A | AG42: #N/A | AH42: #N/A | AI42: #N/A | AJ42: #N/A | AK42: #N/A | AL42: #N/A | AM42: #N/A | AO42: SC PC + CCS post combustion | AP42: ProRES | AQ42: High LR | AR42: #N/A | AS42: #N/A | AT42: #N/A | AU42: #N/A | AV42: #N/A | AW42: #N/A | AX42: #N/A | AY42: #N/A
AB43: 40 | AC43: SC PC + CCS Oxyfuel | AD43: ProRES | AE43: LR_Oxy_High | AF43: #N/A | AG43: #N/A | AH43: #N/A | AI43: #N/A | AJ43: #N/A | AK43: #N/A | AL43: #N/A | AM43: #N/A | AO43: SC PC + CCS Oxyfuel | AP43: ProRES | AQ43: LR_Oxy_High | AR43: #N/A | AS43: #N/A | AT43: #N/A | AU43: #N/A | AV43: #N/A | AW43: #N/A | AX43: #N/A | AY43: #N/A
A44: 0 | G44: 2015 | H44: 2020 | I44: 2025 | J44: 2030 | K44: 2035 | L44: 2040 | M44: 2045 | N44: 2050 | S44: 2015 | T44: 2020 | U44: 2025 | V44: 2030 | W44: 2035 | X44: 2040 | Y44: 2045 | Z44: 2050 | AB44: 55 | AC44: IGCC lignite + CCS pre combustion | AD44: ProRES | AE44: LR_IGCC_High | AF44: #N/A | AG44: #N/A | AH44: #N/A | AI44: #N/A | AJ44: #N/A | AK44: #N/A | AL44: #N/A | AM44: #N/A | AO44: IGCC lignite + CCS pre combustion | AP44: ProRES | AQ44: LR_IGCC_High | AR44: #N/A | AS44: #N/A | AT44: #N/A | AU44: #N/A | AV44: #N/A | AW44: #N/A | AX44: #N/A | AY44: #N/A
A45: 1 | B45: CCUS_Coal_Oxy | C45: G38 | D45: SC PC + CCS Oxyfuel | E45: ProRES | F45: LR_Oxy_Low | G45: #N/A | H45: #N/A | I45: #N/A | J45: #N/A | K45: #N/A | L45: #N/A | M45: #N/A | N45: #N/A | P45: SC PC + CCS Oxyfuel | Q45: ProRES | R45: LR_Oxy_Low | S45: #N/A | T45: #N/A | U45: #N/A | V45: #N/A | W45: #N/A | X45: #N/A | Y45: #N/A | Z45: #N/A | AB45: 70 | AC45: IGCC + CCS pre combustion | AD45: ProRES | AE45: LR_IGCC_High | AF45: #N/A | AG45: #N/A | AH45: #N/A | AI45: #N/A | AJ45: #N/A | AK45: #N/A | AL45: #N/A | AM45: #N/A | AO45: IGCC + CCS pre combustion | AP45: ProRES | AQ45: LR_IGCC_High | AR45: #N/A | AS45: #N/A | AT45: #N/A | AU45: #N/A | AV45: #N/A | AW45: #N/A | AX45: #N/A | AY45: #N/A
A46: 2 | C46: -1 | E46: Baseline | F46: LR_Oxy_Low | G46: #N/A | H46: #N/A | I46: 2920 | J46: 2810 | K46: 2780 | L46: 2750 | M46: 2730 | N46: 2690 | Q46: Baseline | R46: LR_Oxy_Low | S46: #N/A | T46: #N/A | U46: 67.062136 | V46: 64.651844 | W46: 63.844039 | X46: 63.343421 | Y46: 62.714777 | Z46: 61.866461 | AB46: 85 | AC46: IGCC biomass with CCS pre combustion | AD46: ProRES | AE46: LR_IGCC_B_High | AF46: #N/A | AG46: #N/A | AH46: #N/A | AI46: #N/A | AJ46: #N/A | AK46: #N/A | AL46: #N/A | AM46: #N/A | AO46: IGCC biomass with CCS pre combustion | AP46: ProRES | AQ46: LR_IGCC_B_High | AR46: #N/A | AS46: #N/A | AT46: #N/A | AU46: #N/A | AV46: #N/A | AW46: #N/A | AX46: #N/A | AY46: #N/A
A47: 3 | E47: Diversified portfolio | F47: LR_Oxy_Low | G47: #N/A | H47: #N/A | I47: 2920 | J47: 2800 | K47: 2730 | L47: 2700 | M47: 2680 | N47: 2680 | Q47: Diversified portfolio | R47: LR_Oxy_Low | S47: #N/A | T47: #N/A | U47: 67.062136 | V47: 64.406468 | W47: 62.884244 | X47: 62.039234 | Y47: 61.711452 | Z47: 61.711452 | AB47: 100 | AC47: #REF! | AD47: #REF! | AE47: #REF! | AF47: #REF! | AG47: #REF! | AH47: #REF! | AI47: #REF! | AJ47: #REF! | AK47: #REF! | AL47: #REF! | AM47: #REF! | AO47: #REF! | AP47: #REF! | AQ47: #REF! | AR47: #REF! | AS47: #REF! | AT47: #REF! | AU47: #REF! | AV47: #REF! | AW47: #REF! | AX47: #REF! | AY47: #REF!
AB48: 115 | AC48: #REF! | AD48: #REF! | AE48: #REF! | AF48: #REF! | AG48: #REF! | AH48: #REF! | AI48: #REF! | AJ48: #REF! | AK48: #REF! | AL48: #REF! | AM48: #REF! | AO48: #REF! | AP48: #REF! | AQ48: #REF! | AR48: #REF! | AS48: #REF! | AT48: #REF! | AU48: #REF! | AV48: #REF! | AW48: #REF! | AX48: #REF! | AY48: #REF!
A49: 0 | G49: 2015 | H49: 2020 | I49: 2025 | J49: 2030 | K49: 2035 | L49: 2040 | M49: 2045 | N49: 2050 | S49: 2015 | T49: 2020 | U49: 2025 | V49: 2030 | W49: 2035 | X49: 2040 | Y49: 2045 | Z49: 2050 | AB49: 130
A50: 1 | B50: CCUS_Lignite_IGCC | C50: G24 | D50: IGCC lignite + CCS pre combustion | E50: ProRES | F50: LR_IGCC_Ref | G50: #N/A | H50: #N/A | I50: #N/A | J50: #N/A | K50: #N/A | L50: #N/A | M50: #N/A | N50: #N/A | P50: IGCC lignite + CCS pre combustion | Q50: ProRES | R50: LR_IGCC_Ref | S50: #N/A | T50: #N/A | U50: #N/A | V50: #N/A | W50: #N/A | X50: #N/A | Y50: #N/A | Z50: #N/A
A51: 2 | C51: -1 | E51: Baseline | F51: LR_IGCC_Ref | G51: #N/A | H51: #N/A | I51: 4480 | J51: 3920 | K51: 3750 | L51: 3640 | M51: 3510 | N51: 3340 | Q51: Baseline | R51: LR_IGCC_Ref | S51: #N/A | T51: #N/A | U51: 98.578993 | V51: 86.288208 | W51: 82.430018 | X51: 80.10273 | Y51: 77.248206 | Z51: 73.514067
A52: 3 | E52: Diversified portfolio | F52: LR_IGCC_Ref | G52: #N/A | H52: #N/A | I52: 4480 | J52: 3870 | K52: 3550 | L52: 3380 | M52: 3310 | N52: 3310 | Q52: Diversified portfolio | R52: LR_IGCC_Ref | S52: #N/A | T52: #N/A | U52: 98.578993 | V52: 85.102707 | W52: 78.010331 | X52: 74.263731 | Y52: 72.846169 | Z52: 72.846169 | AF52: 2015 | AG52: 2020 | AH52: 2025 | AI52: 2030 | AJ52: 2035 | AK52: 2040 | AL52: 2045 | AM52: 2050 | AR52: 2015 | AS52: 2020 | AT52: 2025 | AU52: 2030 | AV52: 2035 | AW52: 2040 | AX52: 2045 | AY52: 2050
AB53: 11 | AC53: CCGT Advanced + CCS post combustion | AD53: Baseline | AE53: High LR | AF53: #N/A | AG53: #N/A | AH53: 1510 | AI53: 1510 | AJ53: 1510 | AK53: 1510 | AL53: 1510 | AM53: 1510 | AO53: CCGT Advanced + CCS post combustion | AP53: Baseline | AQ53: High LR | AR53: #N/A | AS53: #N/A | AT53: 37.703599 | AU53: 37.703599 | AV53: 37.703599 | AW53: 37.703599 | AX53: 37.703599 | AY53: 37.703599
A54: 0 | G54: 2015 | H54: 2020 | I54: 2025 | J54: 2030 | K54: 2035 | L54: 2040 | M54: 2045 | N54: 2050 | S54: 2015 | T54: 2020 | U54: 2025 | V54: 2030 | W54: 2035 | X54: 2040 | Y54: 2045 | Z54: 2050 | AB54: 26 | AC54: SC PC + CCS post combustion | AD54: Baseline | AE54: High LR | AF54: #N/A | AG54: #N/A | AH54: 2920 | AI54: 2660 | AJ54: 2580 | AK54: 2520 | AL54: 2460 | AM54: 2380 | AO54: SC PC + CCS post combustion | AP54: Baseline | AQ54: High LR | AR54: #N/A | AS54: #N/A | AT54: 59.772773 | AU54: 54.49215 | AV54: 52.788026 | AW54: 51.748315 | AX54: 50.460369 | AY54: 48.753358
A55: 1 | B55: CCUS_Lignite_IGCC | C55: G31 | D55: IGCC lignite + CCS pre combustion | E55: ProRES | F55: LR_IGCC_High | G55: #N/A | H55: #N/A | I55: #N/A | J55: #N/A | K55: #N/A | L55: #N/A | M55: #N/A | N55: #N/A | P55: IGCC lignite + CCS pre combustion | Q55: ProRES | R55: LR_IGCC_High | S55: #N/A | T55: #N/A | U55: #N/A | V55: #N/A | W55: #N/A | X55: #N/A | Y55: #N/A | Z55: #N/A | AB55: 41 | AC55: SC PC + CCS Oxyfuel | AD55: Baseline | AE55: LR_Oxy_High | AF55: #N/A | AG55: #N/A | AH55: 2920 | AI55: 2590 | AJ55: 2490 | AK55: 2430 | AL55: 2350 | AM55: 2250 | AO55: SC PC + CCS Oxyfuel | AP55: Baseline | AQ55: LR_Oxy_High | AR55: #N/A | AS55: #N/A | AT55: 67.062136 | AU55: 59.668219 | AV55: 57.321224 | AW55: 55.899004 | AX55: 54.147632 | AY55: 51.844502
A56: 2 | C56: -1 | E56: Baseline | F56: LR_IGCC_High | G56: #N/A | H56: #N/A | I56: 4480 | J56: 3650 | K56: 3400 | L56: 3250 | M56: 3080 | N56: 2850 | Q56: Baseline | R56: LR_IGCC_High | S56: #N/A | T56: #N/A | U56: 98.578993 | V56: 80.290389 | W56: 74.825543 | X56: 71.595008 | Y56: 67.701483 | Z56: 62.724747 | AB56: 56 | AC56: IGCC lignite + CCS pre combustion | AD56: Baseline | AE56: LR_IGCC_High | AF56: #N/A | AG56: #N/A | AH56: 4480 | AI56: 3650 | AJ56: 3400 | AK56: 3250 | AL56: 3080 | AM56: 2850 | AO56: IGCC lignite + CCS pre combustion | AP56: Baseline | AQ56: LR_IGCC_High | AR56: #N/A | AS56: #N/A | AT56: 98.578993 | AU56: 80.290389 | AV56: 74.825543 | AW56: 71.595008 | AX56: 67.701483 | AY56: 62.724747
A57: 3 | E57: Diversified portfolio | F57: LR_IGCC_High | G57: #N/A | H57: #N/A | I57: 4480 | J57: 3570 | K57: 3120 | L57: 2900 | M57: 2810 | N57: 2810 | Q57: Diversified portfolio | R57: LR_IGCC_High | S57: #N/A | T57: #N/A | U57: 98.578993 | V57: 78.596841 | W57: 68.733521 | X57: 63.713148 | Y57: 61.84873 | Z57: 61.84873 | AB57: 71 | AC57: IGCC + CCS pre combustion | AD57: Baseline | AE57: LR_IGCC_High | AF57: #N/A | AG57: #N/A | AH57: 2940 | AI57: 2400 | AJ57: 2230 | AK57: 2140 | AL57: 2020 | AM57: 1870 | AO57: IGCC + CCS pre combustion | AP57: Baseline | AQ57: LR_IGCC_High | AR57: #N/A | AS57: #N/A | AT57: 88.326966 | AU57: 71.940341 | AV57: 67.043829 | AW57: 64.149264 | AX57: 60.660658 | AY57: 56.201493
AB58: 86 | AC58: IGCC biomass with CCS pre combustion | AD58: Baseline | AE58: LR_IGCC_B_High | AF58: #N/A | AG58: #N/A | AH58: 5800 | AI58: 5800 | AJ58: 5800 | AK58: 5800 | AL58: 5800 | AM58: 5800 | AO58: IGCC biomass with CCS pre combustion | AP58: Baseline | AQ58: LR_IGCC_B_High | AR58: #N/A | AS58: #N/A | AT58: 133.4 | AU58: 133.4 | AV58: 133.4 | AW58: 133.4 | AX58: 133.4 | AY58: 133.4
